Workbook
Name Print_Area: Bankgespräch!$A$5:$L$55
Name Print_Area: Cockpit!$A$5:$X$47
Name Print_Area: Deckblatt!$B$6:$M$38
Name Print_Area: Diagramme!$A$5:$S$106
Name Print_Area: Haushaltsrechnung!$B$6:$P$51
Name Print_Area: Hinweise_AT!$A$5:$O$116
Name Print_Area: Konfiguration!$A$5:$F$13
Name Print_Area: 'MFH-Kalkulator'!$A$5:$BC$224
Name Print_Area: 'Miete, Cashflow, Steuern'!$A$5:$BB$44
Name Print_Area: Sanierungsplaner!$A$6:$L$240
Name Print_Area: Szenarien!$A$5:$AW$32
Name Print_Area: Vermögensaufstellung!$B$6:$P$39
Name Print_Area: 'Wert, AfA, Darlehen'!$A$5:$BB$120
Name Print_Titles: 'MFH-Kalkulator'!$A:$D
Name Print_Titles: 'Miete, Cashflow, Steuern'!$A:$C
Name Print_Titles: 'Wert, AfA, Darlehen'!$A:$C

Sheet Deckblatt
B1: zurück zum Cockpit
C7: immocation
C18: Bei dieser Excel-Datei handelt es sich um ein kostenpflichtiges Produkt, welches unter der u.s. Internetadresse erworben werden kann. Die Datei darf ohne Zustimmung weder vervielfältigt, noch weitergegeben oder sonst irgendwie anderen Benutzern zugänglich gemacht werden. Microsoft Excel ist ein Produkt der Firma Microsoft. Wir stehen in keinerlei rechtlicher Beziehung zu Microsoft und handeln auch nicht in Microsofts Namen. Wir weisen ausdrücklich darauf hin, dass wir keinerlei Rechts-, Steuer- oder Finanzberatung erbringen und die geschilderte Rechtslage zum Teil zur besseren Verständlichkeit und Lesbarkeit außerdem auch vereinfacht dargestellt wurde. Alle von uns erteilten Ratschläge fußen ausschließlich auf unserer persönlichen Erfahrung und unserer persönlichen Meinung. Auch wenn wir jede unserer Empfehlungen mit größtmöglicher Sorgfalt und umfangreicher Recherche entwickelt und fortlaufend kritisch hinterfragt haben, können wir hierfür keinerlei Gewähr bieten. Gleiches gilt auch für die Vollständigkeit und Richtigkeit der dargestellten Rechtslage. Die erteilten Ratschläge können ferner auch keine fundierte und auf den Einzelfall zugeschnittene Rechts-, Steuer- oder Finanzberatung ersetzen. Wir können daher weder eine Erfolgsgarantie für die von uns abgegebenen Empfehlungen noch eine Haftung für evtl. Folgen ihrer Anwendung übernehmen. Auch sämtliche Kalkulationstools wurden mit größter Sorgfalt erstellt. Wir haben durch mehrfache Überprüfungen bestmöglich versucht, Berechnungsfehler auszuschließen. Trotzdem können Fehler nicht vollständig ausgeschlossen werden. Daher können wir keine juristische Verantwortung und keinerlei Haftung für eventuell verbliebene Fehler und deren Folgen übernehmen. Um etwaige Fehler so weit wie möglich auszuschließen, empfehlen wir dringend und in jedem Fall eigenständige Kontrollrechnungen durchzuführen und ggf. zusätzlichen Fachrat eines Rechts-, Steuer- oder Finanzberaters einzuholen.
C41: Copyright 2020
C42: www.immocation.de

Sheet Cockpit
C1: Cockpit | D1: Bankgespräch | G1: Kennzahlen im Verlauf | J1: Szenarien-Vergleich | M1: Diagramme | N1: MFH | P1: Sanierungsplaner | S1: Tabelle entsperren
B6: Objekt und Investition | G6: Miete, Steuern, Rücklagen | J6: Bewirtschaftungskosten | M6: Finanzierung | P6: Kennzahlen heute | S6: Kennzahlen in der Zukunft | V6: Profi Kenzahlen
B8: Objekt und Kaufdatum | G8: Soll-Miete pro Monat | J8: Bewirtschaftungskosten pro Monat | M8: Gesamt-Finanzierung | P8: Vermögenszuwachs | S8: Betrachtungszeitpunkt | V8: Break-Even
B9: Adresse | C9: Rapfstraße 3/1, Hollabrunn | G9: Kaltmiete Wohnfläche pro qm | H9: 12.5 | J9: Umlegbar | K9: =K23 -> 111 | M9: Darlehenssumme | N9: =N17+N25+N32+N39 -> 100000 | P9: Vermögenszuwachs p.a. | Q9: =12*(-Q22+Q25)+'Wert, AfA, Darlehen'!D11 -> 3607.115 | S9: Hochrechnung für das Jahr | T9: 2044 | V9: Cashflow nach Steuern erstmals positiv | W9: =IFERROR(OFFSET('Miete, Cashflow, Steuern'!C18,0,MATCH(TRUE,INDEX('Miete, Cashflow, Steuern'!$D$28:$BA$28>0,0),0)),"-") -> 2046
B10: Kaufdatum | C10: 45413 | D10: Kürzel | E10: BoEl19 | G10: Kaltmiete Wohnfläche gesamt | H10: =C11*H9 -> 529.375 | J10: Nicht umlegbar | K10: =K30 -> 99.502917 | M10: Eigenkapital | N10: =E35-N9 -> 38325 | P10: ohne Wertsteigerung | Q10: =Q9-'Wert, AfA, Darlehen'!D11 -> 1107.115 | S10: entspricht Jahre nach dem Kauf | T10: =T9-'Wert, AfA, Darlehen'!D37 -> 20 | V10: Kumulierter Cashflow bis dahin | W10: =OFFSET('Miete, Cashflow, Steuern'!C32,0,MATCH(TRUE,INDEX('Miete, Cashflow, Steuern'!$D$28:$BA$28>0,0),0)-1) -> -17087.019
B11: Wohnfläche | C11: 42.35 | D11: Stellplätze | E11: 1 | G11: + Stellplätze | H11: 0 | J11: entspricht % der Nettokaltmiete | K11: =K10/H15 -> 0.18796301 | M11: Zinssatz gewichtet | N11: =IF(N9=0,"n/a",((N18*$N$17)+(N26*$N$25)+(N33*$N$32)+(N40*$N$39))/$N$9) -> 0.037 | V11: Kumulierter Cashflow erstmals positiv | W11: =IFERROR(OFFSET('Miete, Cashflow, Steuern'!C18,0,MATCH(TRUE,INDEX('Miete, Cashflow, Steuern'!$D$32:$BA$32>0,0),0)),"-") -> 2049
G12: + Sonstiges | H12: 0 | J12: Insgesamt | K12: =K9+K10 -> 210.50292 | M12: Anfängliche Tilgung gewichtet | N12: =IF(N9=0,"n/a",((N19*$N$17)+(N27*$N$25)+(N34*$N$32)+(N41*$N$39))/$N$9) -> 0.023 | P12: Miete und Mietrendite | S12: Miete und Wert | V12: Kum. Cashflow inkl. EK erstmals positiv | W12: =IFERROR(OFFSET('Miete, Cashflow, Steuern'!C18,0,MATCH(TRUE,INDEX('Miete, Cashflow, Steuern'!$D$33:$BA$33>0,0),0)),"-") -> 2054
B13: Kaufpreis und Kaufnebenkosten | G13: = Nettokaltmiete | H13: =H10+H11+H12 -> 529.375 | M13: Annuität pro Monat | N13: =N20+N28+N35+N42 -> 500 | P13: Nettokaltmiete pro Jahr | Q13: =12*H15 -> 6352.5 | S13: Nettokaltmiete pro Jahr | T13: =OFFSET('Miete, Cashflow, Steuern'!D12,,Cockpit!T10)*12 -> 11139.147
B14: Kaufpreis | D14: 125000 | G14: Nettokaltmiete laut MFH-Kalkulator | H14: ='MFH-Kalkulator'!E12 -> 1287.5 | P14: Bruttomietrendite | Q14: =Q13/D14 -> 0.05082 | S14: pro qm und Monat | T14: =T13/12/C11 -> 21.918826 | V14: Wertschätzung über Kaufpreisfaktor
B15: pro m² | D15: =D14/C11 -> 2951.5939 | G15: = Nettokaltmiete (effektiv) | H15: =IF('MFH-Kalkulator'!$C$6="Ein",H14,H13) -> 529.375 | J15: Betriebskosten | M15: Darlehen I | P15: Faktor | Q15: =D14/Q13 -> 19.677292 | S15: Wert der Immobilie (Jahresende) | T15: =OFFSET('Wert, AfA, Darlehen'!E8,,Cockpit!T10) -> 189458.29 | V15: Nettokaltmiete pro Jahr | W15: =OFFSET('Miete, Cashflow, Steuern'!D12,,Cockpit!T10)*12 -> 11139.147
B16: Makler | D16: 0.036 | E16: =D16*$D$14 -> 4500 | G16: + umlegbare Bewirtschaftungskosten | H16: =K9 -> 111 | J16: Betriebskosten (insgesamt) | K16: 156 | M16: Darlehenssumme % Kaufpreis | N16: 0.8 | P16: Nettomietrendite | Q16: =(Q13-12*K10)/E35 -> 0.037292355 | S16: pro qm | T16: =T15/C11 -> 4473.6315 | V16: Faktor | W16: 15
B17: Notar | D17: 0.015 | E17: =D17*$D$14 -> 1875 | G17: = Bruttokaltmiete | H17: =H15+H16 -> 640.375 | J17: - enthaltene Reparaturrücklage | K17: 45 | M17: Darlehenssumme | N17: =N16*D14 -> 100000 | V17: Wert der Immobilie | W17: =W15*W16 -> 167087.21
B18: Grundbucheintragungsgeb. | D18: 0.011 | E18: =D18*$D$14 -> 1375 | J18: = umlegbare Betriebskosten | K18: =K16-K17 -> 111 | M18: Zinssatz | N18: 0.037 | P18: Cashflow pro Monat (Überschuss) | S18: Cashflow pro Monat (Überschuss) | V18: pro qm | W18: =W17/C11 -> 3945.3886
B19: Grunderwerbssteuer | D19: 0.035 | E19: =D19*$D$14 -> 4375 | G19: Steuern | M19: Anfängliche Tilgung | N19: 0.023 | P19: Bruttokaltmiete | Q19: =H17 -> 640.375 | S19: Bruttokaltmiete | T19: =OFFSET('Miete, Cashflow, Steuern'!D14,,Cockpit!T10) -> 1093.2024
B20: Sonstige | D20: 0 | E20: =D20*$D$14 -> 0 | G20: AfA Satz | H20: 0.015 | J20: Umlegbare Kosten | M20: Annuität pro Monat | N20: =(N18+N19)*N17/12 -> 500 | P20: - Bewirtschaftungskosten | Q20: =-K12 -> -210.50292 | S20: - Bewirtschaftungskosten | T20: =OFFSET('Miete, Cashflow, Steuern'!D23,,Cockpit!T10) -> -317.04543 | V20: Zinsänderungsrisiko
B21: Pfandrechtseintragungsgeb. | D21: 0.012 | E21: =D21*$N$9 -> 1200 | G21: Anteil Gebäude an Kaufpreis | H21: 0.6 | J21: Umlegbare Betriebskosten | K21: =K18 -> 111 | M21: Jahr der Volltilgung | N21: =IFERROR(HLOOKUP(0,'Wert, AfA, Darlehen'!D50:BA105,56,FALSE),"-") -> 2046 | P21: - Zinsen | Q21: =-N11*N9/12 -> -308.33333 | S21: - Zinsen | T21: =-OFFSET('Wert, AfA, Darlehen'!D110,,Cockpit!T10)/12 -> -44.313154 | V21: Monatl. Zinsen für CF 0 nach Steuern | W21: =-(T21-T25/(1-T33)) -> 28.416335
B22: Summe | D22: =SUM(D16:D21) -> 0.109 | E22: =SUM(E16:E21) -> 13325 | G22: Basis für langfristige Abschreibung | H22: =H21*(D14+E22-E21)+SUMIF(D26:D29,"Aktivieren",C26:C29) -> 82275 | J22: Sonstige umlegbare Kosten | K22: =K38 -> 0 | P22: - Tilgung | Q22: =-N12*N9/12 -> -191.66667 | S22: - Tilgung | T22: =-OFFSET('Wert, AfA, Darlehen'!D114,,Cockpit!T10)/12 -> -455.68685 | V22: = Zinssatz gewichtet (p.a.) | W22: =IF(OFFSET('Wert, AfA, Darlehen'!D106,,Cockpit!T10)=0,"n/a",W21*12/OFFSET('Wert, AfA, Darlehen'!D106,,Cockpit!T10)) -> 0.023726689
J23: Summe | K23: =SUM(K21:K22) -> 111 | P23: = Cashflow operativ | Q23: =SUM(Q19:Q22) -> -70.127917 | S23: = Cashflow operativ | T23: =SUM(T19:T22) -> 276.157
B24: Anfängliche Investitionen | G24: Rücklagen | M24: Darlehen II | P24: - Steuern | Q24: =-Q34 -> -29.279167 | S24: - Steuern | T24: =-T34 -> -285.69509 | V24: Vermögenszuwachs bis Jahresende
B25: Was | C25: Kosten | D25: Steuerlich | E25: Wertsteig. | G25: Kalkulatorischer Mietausfall | H25: 0.03 | J25: Nicht umlegbare Kosten | M25: Darlehenssumme | N25: 0 | P25: = Cashflow nach Steuern | Q25: =Q23+Q24 -> -99.407083 | S25: = Cashflow nach Steuern | T25: =T23+T24 -> -9.5380911 | V25: Wert der Immobilie | W25: =OFFSET('Wert, AfA, Darlehen'!E8,,Cockpit!T10) -> 189458.29
B26: Renovierung | C26: 0 | D26: 15 Jahre | G26: Eigene Instandhalt.-Rückl. (pro m² p.a.) | H26: 10 | J26: Reparaturrücklage in Betriebskosten | K26: =K17 -> 45 | M26: Zinssatz | N26: 0.02 | V26: - Restschuld Darlehen | W26: =-OFFSET('Wert, AfA, Darlehen'!D118,,Cockpit!T10) -> -8903.5915
D27: Sofort | G27: Empfohlene eigene Instandhalt.-Rückl. | H27: =((H21*D14)*(1/80*1.5)-(12*K26))/C11 -> 20.454545 | J27: + Eigene Instandhaltungsrücklage | K27: =C11*H26/12 -> 35.291667 | M27: Anfängliche Tilgung | N27: 0.08 | P27: Nebenrechnung Steuer (Monatsbasis) | S27: Nebenrechnung Steuer (Monatsbasis) | V27: - Eigenkapital Einsatz | W27: =-N10 -> -38325
D28: Sofort | J28: + Kalkulatorischer Mietausfall | K28: =H25*H17 -> 19.21125 | M28: Annuität pro Monat | N28: =(N26+N27)*N25/12 -> 0 | P28: Bruttokaltmiete | Q28: =Q19 -> 640.375 | S28: Bruttokaltmiete | T28: =T19 -> 1093.2024 | V28: + Kumulierter Cashflow | W28: =OFFSET('Miete, Cashflow, Steuern'!D32,,Cockpit!T10) -> -17058.709
D29: Sofort | G29: Prognose | J29: + Sonstige nicht umlegbare Kosten | K29: =K46 -> 0 | M29: Jahr der Volltilgung | N29: =HLOOKUP(0,'Wert, AfA, Darlehen'!D67:BA105,39,FALSE) -> 2024 | P29: - Bewirt.-Kosten ohne eigene Rückl. | Q29: =-K12+K27+K28 -> -156 | S29: - Bewirt.-Kosten ohne eigene Rückl. | T29: =OFFSET('Miete, Cashflow, Steuern'!D38,,Cockpit!T10) -> -231.80779 | V29: = Vermögenszuwachs | W29: =SUM(W25:W28) -> 125170.99
B30: Summe | C30: =SUM(C26:C29) -> 0 | D30: Summe | E30: =SUM(E26:E29) -> 0 | G30: Kostensteigerung p.a. | H30: 0.02 | J30: = Summe | K30: =K26+K27+K28+K29 -> 99.502917 | P30: - Zinsen | Q30: =Q21 -> -308.33333 | S30: - Zinsen | T30: =T21 -> -44.313154
B31: Neuer Wert | E31: =D14+E30 -> 125000 | G31: Mietsteigerung p.a. | H31: 0.03 | M31: Darlehen III | P31: - Abschreibung (AfA) | Q31: =-'Wert, AfA, Darlehen'!D19-'Wert, AfA, Darlehen'!D24-IF(E32="Abziehen",'Wert, AfA, Darlehen'!D34,'Wert, AfA, Darlehen'!D34-'Wert, AfA, Darlehen'!D28/12) -> -102.84375 | S31: - Abschreibung (AfA) | T31: =OFFSET('Miete, Cashflow, Steuern'!D40,,Cockpit!T10) -> -102.84375 | V31: Beleihungsreserve
B32: Sofort abzugsfähige Kosten im Cashflow | E32: Ignorieren | G32: Wertsteigerung p.a. | H32: 0.02 | J32: Sonstige umlegbare Kosten (Details) | M32: Darlehenssumme | N32: 0 | P32: = zu versteuernder Cashflow | Q32: =SUM(Q28:Q31) -> 73.197917 | S32: = zu versteuernder Cashflow | T32: =SUM(T28:T31) -> 714.23773 | V32: Wert der Immobilie | W32: =W25 -> 189458.29
J33: Kostenposition I | M33: Zinssatz | N33: 0.03 | P33: * persönlicher Grenzsteuersatz | Q33: 0.4 | S33: * persönlicher Grenzsteuersatz | T33: =OFFSET('Miete, Cashflow, Steuern'!D42,,Cockpit!T10) -> 0.4 | V33: - Restschuld Darlehen | W33: =W26 -> -8903.5915
B34: Gesamtinvestitionskosten | J34: Kostenposition II | M34: Anfängliche Tilgung | N34: 0.05 | P34: = Steuern | Q34: =Q33*Q32 -> 29.279167 | S34: = Steuern | T34: =T33*T32 -> 285.69509 | V34: = Beleihungsreserve | W34: =W32+W33 -> 180554.7
B35: Summe | E35: =D14+E22+C30 -> 138325 | J35: Kostenposition III | M35: Annuität pro Monat | N35: =(N33+N34)*N32/12 -> 0
J36: Kostenposition IV | M36: Jahr der Volltilgung | N36: =HLOOKUP(0,'Wert, AfA, Darlehen'!D84:BA105,22,FALSE) -> 2024 | P36: Eigenkapitalrendite | V36: Kontostand
B37: Hinweis für Investoren aus Österreich: Das Tool geht davon aus, dass der Eigentümer hinsichtlich seiner Mieteinnahmen nicht der Umsatzsteuerpflicht unterliegt, also < 35.000 Euro jährliche Mieteinnahmen hat. Auf dem Tabellenblatt "Hinweise_AT" findest du weitere steuerliche Hinweise für Investoren aus Österreich. | J37: Weitere Kosten | P37: Eigenkapitalrendite p.a. | Q37: =IF(N10>0,Q9/N10,"n/a") -> 0.094119113 | V37: Eigenkapital Einsatz (anfänglich) | W37: =W27 -> -38325
J38: Summe | K38: =SUM(K33:K37) -> 0 | M38: Darlehen IV | P38: ohne Wertsteigerung | Q38: =Q10/N10 -> 0.028887541 | V38: + Kumulierter Cashflow | W38: =W28 -> -17058.709
M39: Darlehenssumme | N39: 0 | V39: = Kontostand | W39: =W37+W38 -> -55383.709
J40: Sonstige nicht umlegbare Kosten (Details) | M40: Zinssatz
J41: Kostenposition I | M41: Anfängliche Tilgung
B42: Zu den Hinweisen | J42: Kostenposition II | M42: Annuität pro Monat | N42: =(N40+N41)*N39/12 -> 0
J43: Kostenposition III | M43: Jahr der Volltilgung | N43: =HLOOKUP(0,'Wert, AfA, Darlehen'!D101:BA105,5,FALSE) -> 2024
J44: Kostenposition IV
J45: Weitere Kosten
J46: Summe | K46: =SUM(K41:K45) -> 0
B49: Keine Gewähr für die Richtigkeit der Angaben. Dieses Tool ersetzt keine fundierte Rechts-, Steuer- oder Finanzberatung. Mehr Details hier.

Sheet Bankgespräch
C1: zurück zum Cockpit | E1: Bankgespräch
B6: Investitionsübersicht für das Bankgespräch | N6: Erhalte bessere Darlehen:
C8: =Cockpit!C9 -> Rapfstraße 3/1, Hollabrunn | I8: =Cockpit!C10 -> 45413 | N8: Drucke diese Übersicht aus, um deiner Bank dein Investment vorzustellen. Alle Zahlen stammen aus den vorhandenen Berechnungen. Für noch mehr Transparenz drucke auch die Tabelle "Cockpit". So zeigst du, dass du deine Zahlen wirklich im Griff hast und erhöhst deine Chance auf beste Konditionen.
N18: Um deiner Bank deine persönlichen finanziellen Verhältnisse darzustellen, kannst du folgende Vorlagen verwenden:
N23: zur Vorlage: Haushaltsrechnung
N24: zur Vorlage: Vermögensübersicht
C25: Investition | F25: Finanzierung | I25: Rentabilität
C27: Objektdetails | F27: Haupt-Darlehen | I27: Erwartete Mieteinkünfte | N27: Um die Bilder zu ändern, klicke mit rechts auf das Bild und wähle "Bild ändern".
C28: Wohnfläche | D28: =Cockpit!C11 -> 42.35 | F28: Summe | G28: =Cockpit!N17 -> 100000 | I28: Nettokaltmiete | J28: =Cockpit!H15 -> 529.375
C29: Kaufpreis pro qm | D29: =D33/D28 -> 2951.5939 | F29: Anfängliche Tilgung | G29: =Cockpit!N19 -> 0.023 | I29: Bruttomietrendite | J29: =Cockpit!Q14 -> 0.05082
F30: Annahme Zinsen | G30: =Cockpit!N18 -> 0.037 | I30: Kaufpreis Multiplikator | J30: =Cockpit!Q15 -> 19.677292
C32: Kapitalbedarf | F32: Weitere Darlehen | I32: Monatlicher Cashflow (Jahr 1)
C33: Kaufpreis | D33: =Cockpit!D14 -> 125000 | F33: Summe | G33: =Cockpit!N9-Cockpit!N17 -> 0 | I33: Nettokaltmiete | J33: =Cockpit!H15 -> 529.375
C34: Kaufnebenkosten | D34: =Cockpit!E22 -> 13325 | F34: Anfängliche Tilgung | G34: =(Cockpit!N12*Cockpit!N9-Cockpit!N19*Cockpit!N17)/(Cockpit!N9-Cockpit!N17) -> #DIV/0! | I34: =CONCATENATE("- Bewirtschaftungskosten (",TEXT(Cockpit!K11*100,"#"),"%)") -> - Bewirtschaftungskosten (19%) | J34: =Cockpit!K10 -> 99.502917
C35: Zusätzl. Investitionsbedarf | D35: =Cockpit!C30 -> 0 | F35: Annahme Zinsen | G35: =(Cockpit!N11*Cockpit!N9-Cockpit!N18*Cockpit!N17)/(Cockpit!N9-Cockpit!N17) -> #DIV/0! | I35: - Zinsen | J35: =-Cockpit!Q21 -> 308.33333
C36: Gesamtinvestitionskosten | D36: =SUM(D33:D35) -> 138325 | I36: - Tilgung | J36: =-Cockpit!Q22 -> 191.66667
F37: Eigenkapital | I37: = monatlicher Cashflow | J37: =J33-SUM(J34:J36) -> -70.127917
F38: Summe | G38: =Cockpit!N10 -> 38325
I42: Einnahme | J42: Ausgabe
H43: Nettokaltmiete | I43: =Cockpit!H15 -> 529.375
H44: Bewirt.-Kosten (nicht umlagefähig) | J44: =Cockpit!K10 -> 99.502917
H45: Zinsen | J45: =-Cockpit!Q21 -> 308.33333
H46: Tilgung | J46: =-Cockpit!Q22 -> 191.66667
B56: Keine Gewähr für die Richtigkeit der Angaben. Dieses Tool ersetzt keine fundierte Rechts-, Steuer- oder Finanzberatung. Mehr Details hier.

Sheet Miete, Cashflow, Steuern
B1: zurück zum Cockpit | E1: Miete, Cashflow, Steuern | J1: zu Wert, Abschreibung und Darlehen wechseln
B6: Miete pro Monat
D7: ='Wert, AfA, Darlehen'!D7 -> 2024 | E7: ='Wert, AfA, Darlehen'!E7 -> 2025 | F7: ='Wert, AfA, Darlehen'!F7 -> 2026 | G7: ='Wert, AfA, Darlehen'!G7 -> 2027 | H7: ='Wert, AfA, Darlehen'!H7 -> 2028 | I7: ='Wert, AfA, Darlehen'!I7 -> 2029 | J7: ='Wert, AfA, Darlehen'!J7 -> 2030 | K7: ='Wert, AfA, Darlehen'!K7 -> 2031 | ... BA7: ='Wert, AfA, Darlehen'!BA7 -> 2073
B8: Nettokaltmiete vor Erhöhung | E8: =D10 -> 529.375 | F8: =E10 -> 529.375 | G8: =F10 -> 545.25625 | H8: =G10 -> 561.61394 | I8: =H10 -> 578.46236 | J8: =I10 -> 595.81623 | K8: =J10 -> 613.69071 | L8: =K10 -> 632.10143 | ... BA8: =AZ10 -> 2123.7969
B9: + geplante Mieterhöhung | E9: 0 | F9: =Cockpit!$H$31 -> 0.03 | G9: =Cockpit!$H$31 -> 0.03 | H9: =Cockpit!$H$31 -> 0.03 | I9: =Cockpit!$H$31 -> 0.03 | J9: =Cockpit!$H$31 -> 0.03 | K9: =Cockpit!$H$31 -> 0.03 | L9: =Cockpit!$H$31 -> 0.03 | M9: =Cockpit!$H$31 -> 0.03 | ... BA9: =Cockpit!$H$31 -> 0.03
B10: = Nettokaltmiete | D10: =Cockpit!H15 -> 529.375 | E10: =E8*(1+E9) -> 529.375 | F10: =F8*(1+F9) -> 545.25625 | G10: =G8*(1+G9) -> 561.61394 | H10: =H8*(1+H9) -> 578.46236 | I10: =I8*(1+I9) -> 595.81623 | J10: =J8*(1+J9) -> 613.69071 | K10: =K8*(1+K9) -> 632.10143 | L10: =L8*(1+L9) -> 651.06448 | ... BA10: =BA8*(1+BA9) -> 2187.5108
B11: Nettokaltmiete laut MFH-Kalkulator | D11: ='MFH-Kalkulator'!E12 -> 1287.5 | E11: ='MFH-Kalkulator'!F12 -> 1326.125 | F11: ='MFH-Kalkulator'!G12 -> 1365.9088 | G11: ='MFH-Kalkulator'!H12 -> 1406.886 | H11: ='MFH-Kalkulator'!I12 -> 1449.0926 | I11: ='MFH-Kalkulator'!J12 -> 1492.5654 | J11: ='MFH-Kalkulator'!K12 -> 1537.3423 | K11: ='MFH-Kalkulator'!L12 -> 1583.4626 | ... BA11: ='MFH-Kalkulator'!BB12 -> 5479.8825
B12: = Nettokaltmiete (effektiv) | D12: =IF('MFH-Kalkulator'!$C$6="Ein",'Miete, Cashflow, Steuern'!D11,'Miete, Cashflow, Steuern'!D10) -> 529.375 | E12: =IF('MFH-Kalkulator'!$C$6="Ein",'Miete, Cashflow, Steuern'!E11,'Miete, Cashflow, Steuern'!E10) -> 529.375 | F12: =IF('MFH-Kalkulator'!$C$6="Ein",'Miete, Cashflow, Steuern'!F11,'Miete, Cashflow, Steuern'!F10) -> 545.25625 | G12: =IF('MFH-Kalkulator'!$C$6="Ein",'Miete, Cashflow, Steuern'!G11,'Miete, Cashflow, Steuern'!G10) -> 561.61394 | H12: =IF('MFH-Kalkulator'!$C$6="Ein",'Miete, Cashflow, Steuern'!H11,'Miete, Cashflow, Steuern'!H10) -> 578.46236 | I12: =IF('MFH-Kalkulator'!$C$6="Ein",'Miete, Cashflow, Steuern'!I11,'Miete, Cashflow, Steuern'!I10) -> 595.81623 | J12: =IF('MFH-Kalkulator'!$C$6="Ein",'Miete, Cashflow, Steuern'!J11,'Miete, Cashflow, Steuern'!J10) -> 613.69071 | K12: =IF('MFH-Kalkulator'!$C$6="Ein",'Miete, Cashflow, Steuern'!K11,'Miete, Cashflow, Steuern'!K10) -> 632.10143 | ... BA12: =IF('MFH-Kalkulator'!$C$6="Ein",'Miete, Cashflow, Steuern'!BA11,'Miete, Cashflow, Steuern'!BA10) -> 2187.5108
B13: + umlagefähige Kosten | D13: =Cockpit!K9 -> 111 | E13: =D13*(1+Cockpit!$H$30) -> 113.22 | F13: =E13*(1+Cockpit!$H$30) -> 115.4844 | G13: =F13*(1+Cockpit!$H$30) -> 117.79409 | H13: =G13*(1+Cockpit!$H$30) -> 120.14997 | I13: =H13*(1+Cockpit!$H$30) -> 122.55297 | J13: =I13*(1+Cockpit!$H$30) -> 125.00403 | K13: =J13*(1+Cockpit!$H$30) -> 127.50411 | L13: =K13*(1+Cockpit!$H$30) -> 130.05419 | ... BA13: =AZ13*(1+Cockpit!$H$30) -> 292.90811
B14: = Bruttokaltmiete | D14: =D12+D13 -> 640.375 | E14: =E12+E13 -> 642.595 | F14: =F12+F13 -> 660.74065 | G14: =G12+G13 -> 679.40803 | H14: =H12+H13 -> 698.61233 | I14: =I12+I13 -> 718.3692 | J14: =J12+J13 -> 738.69474 | K14: =K12+K13 -> 759.60554 | ... BA14: =BA12+BA13 -> 2480.4189
B17: Cashflow pro Monat
D18: =D7 -> 2024 | E18: =E7 -> 2025 | F18: =F7 -> 2026 | G18: =G7 -> 2027 | H18: =H7 -> 2028 | I18: =I7 -> 2029 | J18: =J7 -> 2030 | K18: =K7 -> 2031 | ... BA18: =BA7 -> 2073
B19: Bruttokaltmiete | D19: =D14 -> 640.375 | E19: =E14 -> 642.595 | F19: =F14 -> 660.74065 | G19: =G14 -> 679.40803 | H19: =H14 -> 698.61233 | I19: =I14 -> 718.3692 | J19: =J14 -> 738.69474 | K19: =K14 -> 759.60554 | ... BA19: =BA14 -> 2480.4189
B20: - Bewirtschaftungskosten ohne eigene Rücklagen | D20: =-(Cockpit!K12-Cockpit!K27-Cockpit!K28) -> -156 | E20: =D20*(1+Cockpit!$H$30) -> -159.12 | F20: =E20*(1+Cockpit!$H$30) -> -162.3024 | G20: =F20*(1+Cockpit!$H$30) -> -165.54845 | H20: =G20*(1+Cockpit!$H$30) -> -168.85942 | I20: =H20*(1+Cockpit!$H$30) -> -172.23661 | J20: =I20*(1+Cockpit!$H$30) -> -175.68134 | K20: =J20*(1+Cockpit!$H$30) -> -179.19496 | L20: =K20*(1+Cockpit!$H$30) -> -182.77886 | ... BA20: =AZ20*(1+Cockpit!$H$30) -> -411.65464
B21: - Eigene Instandhaltungsrücklage | D21: =-Cockpit!K27 -> -35.291667 | E21: =D21*(1+Cockpit!$H$30) -> -35.9975 | F21: =E21*(1+Cockpit!$H$30) -> -36.71745 | G21: =F21*(1+Cockpit!$H$30) -> -37.451799 | H21: =G21*(1+Cockpit!$H$30) -> -38.200835 | I21: =H21*(1+Cockpit!$H$30) -> -38.964852 | J21: =I21*(1+Cockpit!$H$30) -> -39.744149 | K21: =J21*(1+Cockpit!$H$30) -> -40.539032 | L21: =K21*(1+Cockpit!$H$30) -> -41.349812 | ... BA21: =AZ21*(1+Cockpit!$H$30) -> -93.128066
B22: - Rücklage Kalkulatorischer Mietausfall | D22: =-Cockpit!K28 -> -19.21125 | E22: =-Cockpit!$H$25*'Miete, Cashflow, Steuern'!E14 -> -19.27785 | F22: =-Cockpit!$H$25*'Miete, Cashflow, Steuern'!F14 -> -19.82222 | G22: =-Cockpit!$H$25*'Miete, Cashflow, Steuern'!G14 -> -20.382241 | H22: =-Cockpit!$H$25*'Miete, Cashflow, Steuern'!H14 -> -20.95837 | I22: =-Cockpit!$H$25*'Miete, Cashflow, Steuern'!I14 -> -21.551076 | J22: =-Cockpit!$H$25*'Miete, Cashflow, Steuern'!J14 -> -22.160842 | K22: =-Cockpit!$H$25*'Miete, Cashflow, Steuern'!K14 -> -22.788166 | L22: =-Cockpit!$H$25*'Miete, Cashflow, Steuern'!L14 -> -23.43356 | ... BA22: =-Cockpit!$H$25*'Miete, Cashflow, Steuern'!BA14 -> -74.412568
B23: Summe Bewirtschaftungskosten | D23: =D20+D21+D22 -> -210.50292 | E23: =E20+E21+E22 -> -214.39535 | F23: =F20+F21+F22 -> -218.84207 | G23: =G20+G21+G22 -> -223.38249 | H23: =H20+H21+H22 -> -228.01862 | I23: =I20+I21+I22 -> -232.75253 | J23: =J20+J21+J22 -> -237.58633 | K23: =K20+K21+K22 -> -242.52216 | ... BA23: =BA20+BA21+BA22 -> -579.19527
B24: - Zinsen | D24: =-'Wert, AfA, Darlehen'!D110/12 -> -308.33333 | E24: =-'Wert, AfA, Darlehen'!E110/12 -> -301.24167 | F24: =-'Wert, AfA, Darlehen'!F110/12 -> -263.05427 | G24: =-'Wert, AfA, Darlehen'!G110/12 -> -254.28728 | H24: =-'Wert, AfA, Darlehen'!H110/12 -> -245.19591 | I24: =-'Wert, AfA, Darlehen'!I110/12 -> -235.76816 | J24: =-'Wert, AfA, Darlehen'!J110/12 -> -225.99158 | K24: =-'Wert, AfA, Darlehen'!K110/12 -> -215.85327 | ... BA24: =-'Wert, AfA, Darlehen'!BA110/12 -> 0
B25: - Tilgung | C25: - Tilgung | D25: =-'Wert, AfA, Darlehen'!D114/12 -> -191.66667 | E25: =-'Wert, AfA, Darlehen'!E114/12 -> -198.75833 | F25: =-'Wert, AfA, Darlehen'!F114/12 -> -236.94573 | G25: =-'Wert, AfA, Darlehen'!G114/12 -> -245.71272 | H25: =-'Wert, AfA, Darlehen'!H114/12 -> -254.80409 | I25: =-'Wert, AfA, Darlehen'!I114/12 -> -264.23184 | J25: =-'Wert, AfA, Darlehen'!J114/12 -> -274.00842 | K25: =-'Wert, AfA, Darlehen'!K114/12 -> -284.14673 | ... BA25: =-'Wert, AfA, Darlehen'!BA114/12 -> 0
B26: = Cashflow operativ | C26: = Cashflow operativ | D26: =D19+D23+D24+D25 -> -70.127917 | E26: =E19+E23+E24+E25 -> -71.80035 | F26: =F19+F23+F24+F25 -> -58.101419 | G26: =G19+G23+G24+G25 -> -43.974462 | H26: =H19+H23+H24+H25 -> -29.406296 | I26: =I19+I23+I24+I25 -> -14.383337 | J26: =J19+J23+J24+J25 -> 1.1084133 | K26: =K19+K23+K24+K25 -> 17.083381 | ... BA26: =BA19+BA23+BA24+BA25 -> 1901.2237
B27: - Steuern | C27: - Steuern | D27: =-D43 -> -29.279167 | E27: =-E43 -> -31.755833 | F27: =-F43 -> -53.01609 | G27: =-G43 -> -62.691418 | H27: =-H43 -> -72.685298 | I27: =-I43 -> -83.008271 | J27: =-J43 -> -93.671228 | K27: =-K43 -> -104.68542 | ... BA27: =-BA43 -> -786.36822
B28: = Cashflow nach Steuern | D28: =D26+D27 -> -99.407083 | E28: =E26+E27 -> -103.55618 | F28: =F26+F27 -> -111.11751 | G28: =G26+G27 -> -106.66588 | H28: =H26+H27 -> -102.09159 | I28: =I26+I27 -> -97.391609 | J28: =J26+J27 -> -92.562815 | K28: =K26+K27 -> -87.602042 | ... BA28: =BA26+BA27 -> 1114.8555
B30: Break Even Rechnung
D31: =D7 -> 2024 | E31: =E7 -> 2025 | F31: =F7 -> 2026 | G31: =G7 -> 2027 | H31: =H7 -> 2028 | I31: =I7 -> 2029 | J31: =J7 -> 2030 | K31: =K7 -> 2031 | ... BA31: =BA7 -> 2073
B32: Kumulierter Cashflow am Jahresende | D32: =12*D28 -> -1192.885 | E32: =D32+12*E28 -> -2435.5592 | F32: =E32+12*F28 -> -3768.9693 | G32: =F32+12*G28 -> -5048.9599 | H32: =G32+12*H28 -> -6274.059 | I32: =H32+12*I28 -> -7442.7583 | J32: =I32+12*J28 -> -8553.5121 | K32: =J32+12*K28 -> -9604.7366 | L32: =K32+12*L28 -> -10594.809 | ... BA32: =AZ32+12*BA28 -> 237506.49
B33: Kumulierter Cashflow inkl. Eigenkapitaleinsatz | D33: =-Cockpit!$N$10+D32 -> -39517.885 | E33: =-Cockpit!$N$10+E32 -> -40760.559 | F33: =-Cockpit!$N$10+F32 -> -42093.969 | G33: =-Cockpit!$N$10+G32 -> -43373.96 | H33: =-Cockpit!$N$10+H32 -> -44599.059 | I33: =-Cockpit!$N$10+I32 -> -45767.758 | J33: =-Cockpit!$N$10+J32 -> -46878.512 | K33: =-Cockpit!$N$10+K32 -> -47929.737 | ... BA33: =-Cockpit!$N$10+BA32 -> 199181.49
B35: Nebenrechnung Steuer pro Monat
D36: =D7 -> 2024 | E36: =E7 -> 2025 | F36: =F7 -> 2026 | G36: =G7 -> 2027 | H36: =H7 -> 2028 | I36: =I7 -> 2029 | J36: =J7 -> 2030 | K36: =K7 -> 2031 | ... BA36: =BA7 -> 2073
B37: Bruttokaltmiete | D37: =D14 -> 640.375 | E37: =E14 -> 642.595 | F37: =F14 -> 660.74065 | G37: =G14 -> 679.40803 | H37: =H14 -> 698.61233 | I37: =I14 -> 718.3692 | J37: =J14 -> 738.69474 | K37: =K14 -> 759.60554 | ... BA37: =BA14 -> 2480.4189
B38: - Bewirtschaftungskosten ohne eigene Rücklagen | D38: =D23-D21-D22 -> -156 | E38: =E23-E21-E22 -> -159.12 | F38: =F23-F21-F22 -> -162.3024 | G38: =G23-G21-G22 -> -165.54845 | H38: =H23-H21-H22 -> -168.85942 | I38: =I23-I21-I22 -> -172.23661 | J38: =J23-J21-J22 -> -175.68134 | K38: =K23-K21-K22 -> -179.19496 | ... BA38: =BA23-BA21-BA22 -> -411.65464
B39: - Zinsen | D39: =-'Wert, AfA, Darlehen'!D110/12 -> -308.33333 | E39: =-'Wert, AfA, Darlehen'!E110/12 -> -301.24167 | F39: =-'Wert, AfA, Darlehen'!F110/12 -> -263.05427 | G39: =-'Wert, AfA, Darlehen'!G110/12 -> -254.28728 | H39: =-'Wert, AfA, Darlehen'!H110/12 -> -245.19591 | I39: =-'Wert, AfA, Darlehen'!I110/12 -> -235.76816 | J39: =-'Wert, AfA, Darlehen'!J110/12 -> -225.99158 | K39: =-'Wert, AfA, Darlehen'!K110/12 -> -215.85327 | ... BA39: =-'Wert, AfA, Darlehen'!BA110/12 -> 0
B40: - Abschreibung für Abnutzung (AfA) | D40: =-'Wert, AfA, Darlehen'!D19-'Wert, AfA, Darlehen'!D24-IF(Cockpit!E32="Abziehen",'Wert, AfA, Darlehen'!D34,'Wert, AfA, Darlehen'!D34-'Wert, AfA, Darlehen'!D28/12) -> -102.84375 | E40: =-'Wert, AfA, Darlehen'!E19-'Wert, AfA, Darlehen'!E24-'Wert, AfA, Darlehen'!E34 -> -102.84375 | F40: =-'Wert, AfA, Darlehen'!F19-'Wert, AfA, Darlehen'!F24-'Wert, AfA, Darlehen'!F34 -> -102.84375 | G40: =-'Wert, AfA, Darlehen'!G19-'Wert, AfA, Darlehen'!G24-'Wert, AfA, Darlehen'!G34 -> -102.84375 | H40: =-'Wert, AfA, Darlehen'!H19-'Wert, AfA, Darlehen'!H24-'Wert, AfA, Darlehen'!H34 -> -102.84375 | I40: =-'Wert, AfA, Darlehen'!I19-'Wert, AfA, Darlehen'!I24-'Wert, AfA, Darlehen'!I34 -> -102.84375 | J40: =-'Wert, AfA, Darlehen'!J19-'Wert, AfA, Darlehen'!J24-'Wert, AfA, Darlehen'!J34 -> -102.84375 | K40: =-'Wert, AfA, Darlehen'!K19-'Wert, AfA, Darlehen'!K24-'Wert, AfA, Darlehen'!K34 -> -102.84375 | L40: =-'Wert, AfA, Darlehen'!L19-'Wert, AfA, Darlehen'!L24-'Wert, AfA, Darlehen'!L34 -> -102.84375 | ... BA40: =-'Wert, AfA, Darlehen'!BA19-'Wert, AfA, Darlehen'!BA24-'Wert, AfA, Darlehen'!BA34 -> -102.84375
B41: = zu versteuernder Cashflow | D41: =SUM(D37:D40) -> 73.197917 | E41: =SUM(E37:E40) -> 79.389583 | F41: =SUM(F37:F40) -> 132.54023 | G41: =SUM(G37:G40) -> 156.72854 | H41: =SUM(H37:H40) -> 181.71325 | I41: =SUM(I37:I40) -> 207.52068 | J41: =SUM(J37:J40) -> 234.17807 | K41: =SUM(K37:K40) -> 261.71356 | ... BA41: =SUM(BA37:BA40) -> 1965.9206
B42: * persönlicher Grenzsteuersatz | D42: =Cockpit!Q33 -> 0.4 | E42: 0.4 | F42: =E42 -> 0.4 | G42: =F42 -> 0.4 | H42: =G42 -> 0.4 | I42: =H42 -> 0.4 | J42: =I42 -> 0.4 | K42: =J42 -> 0.4 | L42: =K42 -> 0.4 | M42: =L42 -> 0.4 | ... BA42: =AZ42 -> 0.4
B43: = Steuern | D43: =D42*D41 -> 29.279167 | E43: =E42*E41 -> 31.755833 | F43: =F42*F41 -> 53.01609 | G43: =G42*G41 -> 62.691418 | H43: =H42*H41 -> 72.685298 | I43: =I42*I41 -> 83.008271 | J43: =J42*J41 -> 93.671228 | K43: =K42*K41 -> 104.68542 | ... BA43: =BA42*BA41 -> 786.36822
B45: Keine Gewähr für die Richtigkeit der Angaben. Dieses Tool ersetzt keine fundierte Rechts-, Steuer- oder Finanzberatung. Mehr Details hier.

Sheet Wert, AfA, Darlehen
B1: zurück zum Cockpit | E1: Wert, Abschreibung und Darlehen | J1: zu Miete, Cashflow, Steuern wechseln
B6: Wertentwicklung
B7: € | D7: =YEAR(Cockpit!C10) -> 2024 | E7: =D7+1 -> 2025 | F7: =E7+1 -> 2026 | G7: =F7+1 -> 2027 | H7: =G7+1 -> 2028 | I7: =H7+1 -> 2029 | J7: =I7+1 -> 2030 | K7: =J7+1 -> 2031 | L7: =K7+1 -> 2032 | ... BA7: =AZ7+1 -> 2073
B8: Wert der Immobilie (Jahresanfang) | D8: =Cockpit!D14+Cockpit!E30 -> 125000 | E8: =D12 -> 127500 | F8: =E12 -> 130050 | G8: =F12 -> 132651 | H8: =G12 -> 135304.02 | I8: =H12 -> 138010.1 | J8: =I12 -> 140770.3 | K8: =J12 -> 143585.71 | L8: =K12 -> 146457.42 | ... BA8: =AZ12 -> 329851.47
B9: Nettovermögen (Wert - Restschuld) (Jahresanfang) | D9: =D8-'Wert, AfA, Darlehen'!D106 -> 25000 | E9: =E8-'Wert, AfA, Darlehen'!E106 -> 29800 | F9: =F8-'Wert, AfA, Darlehen'!F106 -> 44735.1 | G9: =G8-'Wert, AfA, Darlehen'!G106 -> 50179.449 | H9: =H8-'Wert, AfA, Darlehen'!H106 -> 55781.021 | I9: =I8-'Wert, AfA, Darlehen'!I106 -> 61544.751 | J9: =J8-'Wert, AfA, Darlehen'!J106 -> 67475.735 | K9: =K8-'Wert, AfA, Darlehen'!K106 -> 73579.242 | ... BA9: =BA8-'Wert, AfA, Darlehen'!BA106 -> 329851.47
B10: Wertentwicklung im Jahr | D10: =Cockpit!$H$32 -> 0.02 | E10: =D10 -> 0.02 | F10: =E10 -> 0.02 | G10: =F10 -> 0.02 | H10: =G10 -> 0.02 | I10: =H10 -> 0.02 | J10: =I10 -> 0.02 | K10: =J10 -> 0.02 | L10: =K10 -> 0.02 | ... BA10: =AZ10 -> 0.02
B11: Wertentwicklung im Jahr | D11: =D8*D10 -> 2500 | E11: =E8*E10 -> 2550 | F11: =F8*F10 -> 2601 | G11: =G8*G10 -> 2653.02 | H11: =H8*H10 -> 2706.0804 | I11: =I8*I10 -> 2760.202 | J11: =J8*J10 -> 2815.406 | K11: =K8*K10 -> 2871.7142 | ... BA11: =BA8*BA10 -> 6597.0295
B12: Wert der Immobilie (Jahresende) | D12: =D8+D11 -> 127500 | E12: =E8+E11 -> 130050 | F12: =F8+F11 -> 132651 | G12: =G8+G11 -> 135304.02 | H12: =H8+H11 -> 138010.1 | I12: =I8+I11 -> 140770.3 | J12: =J8+J11 -> 143585.71 | K12: =K8+K11 -> 146457.42 | ... BA12: =BA8+BA11 -> 336448.5
B14: Abschreibung Regulär
B15: € | D15: ='Miete, Cashflow, Steuern'!D7 -> 2024 | E15: ='Miete, Cashflow, Steuern'!E7 -> 2025 | F15: ='Miete, Cashflow, Steuern'!F7 -> 2026 | G15: ='Miete, Cashflow, Steuern'!G7 -> 2027 | H15: ='Miete, Cashflow, Steuern'!H7 -> 2028 | I15: ='Miete, Cashflow, Steuern'!I7 -> 2029 | J15: ='Miete, Cashflow, Steuern'!J7 -> 2030 | K15: ='Miete, Cashflow, Steuern'!K7 -> 2031 | ... BA15: ='Miete, Cashflow, Steuern'!BA7 -> 2073
B16: = Basis für langfristige Abschreibung | D16: =Cockpit!H22 -> 82275 | E16: =D16 -> 82275 | F16: =E16 -> 82275 | G16: =F16 -> 82275 | H16: =G16 -> 82275 | I16: =H16 -> 82275 | J16: =I16 -> 82275 | K16: =J16 -> 82275 | L16: =K16 -> 82275 | ... BA16: =AZ16 -> 82275
B17: * Abschreibungssatz pro Jahr | D17: =Cockpit!H20 -> 0.015 | E17: =D17 -> 0.015 | F17: =E17 -> 0.015 | G17: =F17 -> 0.015 | H17: =G17 -> 0.015 | I17: =H17 -> 0.015 | J17: =I17 -> 0.015 | K17: =J17 -> 0.015 | L17: =K17 -> 0.015 | ... BA17: =AZ17 -> 0.015
B18: = Abschreibung pro Jahr | D18: =D17*D16 -> 1234.125 | E18: =MIN(E17*E16,E16-D20) -> 1234.125 | F18: =MIN(F17*F16,F16-E20) -> 1234.125 | G18: =MIN(G17*G16,G16-F20) -> 1234.125 | H18: =MIN(H17*H16,H16-G20) -> 1234.125 | I18: =MIN(I17*I16,I16-H20) -> 1234.125 | J18: =MIN(J17*J16,J16-I20) -> 1234.125 | K18: =MIN(K17*K16,K16-J20) -> 1234.125 | L18: =MIN(L17*L16,L16-K20) -> 1234.125 | ... BA18: =MIN(BA17*BA16,BA16-AZ20) -> 1234.125
B19: = pro Monat | D19: =D18/12 -> 102.84375 | E19: =E18/12 -> 102.84375 | F19: =F18/12 -> 102.84375 | G19: =G18/12 -> 102.84375 | H19: =H18/12 -> 102.84375 | I19: =I18/12 -> 102.84375 | J19: =J18/12 -> 102.84375 | K19: =K18/12 -> 102.84375 | ... BA19: =BA18/12 -> 102.84375
B20: Kumulierte Abschreibung Jahresende | D20: =D18 -> 1234.125 | E20: =D20+E18 -> 2468.25 | F20: =E20+F18 -> 3702.375 | G20: =F20+G18 -> 4936.5 | H20: =G20+H18 -> 6170.625 | I20: =H20+I18 -> 7404.75 | J20: =I20+J18 -> 8638.875 | K20: =J20+K18 -> 9873 | L20: =K20+L18 -> 11107.125 | ... BA20: =AZ20+BA18 -> 61706.25
B22: Abschreibung Denkmal
B23: € | D23: =D7 -> 2024 | E23: =E7 -> 2025 | F23: =F7 -> 2026 | G23: =G7 -> 2027 | H23: =H7 -> 2028 | I23: =I7 -> 2029 | J23: =J7 -> 2030 | K23: =K7 -> 2031 | ... BA23: =BA7 -> 2073
B24: = pro Monat | D24: 0 | E24: 0 | F24: 0 | G24: 0 | H24: 0 | I24: 0 | J24: 0 | K24: 0 | L24: 0 | M24: 0 | N24: 0 | O24: 0 | P24: 0 | Q24: 0 | R24: 0 | S24: 0 | T24: 0 | U24: 0 | V24: 0 | W24: 0 | X24: 0 | Y24: 0 | Z24: 0 | AA24: 0 | AB24: 0 | AC24: 0 | AD24: 0 | AE24: 0 | AF24: 0 | AG24: 0 | AH24: 0 | AI24: 0 | AJ24: 0 | AK24: 0 | AL24: 0 | AM24: 0 | AN24: 0 | AO24: 0 | AP24: 0 | AQ24: 0 | AR24: 0 | AS24: 0 | AT24: 0 | AU24: 0 | AV24: 0 | AW24: 0 | AX24: 0 | AY24: 0 | AZ24: 0 | BA24: 0
B26: Abschreibung Investitionen
B27: € | D27: =D15 -> 2024 | E27: =E15 -> 2025 | F27: =F15 -> 2026 | G27: =G15 -> 2027 | H27: =H15 -> 2028 | I27: =I15 -> 2029 | J27: =J15 -> 2030 | K27: =K15 -> 2031 | ... BA27: =BA15 -> 2073
B28: =CONCATENATE("Sofort abzugfsähig (",SUMIF(Cockpit!D26:D29,"Sofort",Cockpit!C26:C29)," €)") -> Sofort abzugfsähig (0 €) | D28: =IF(Cockpit!E32="Abziehen",SUMIF(Cockpit!D26:D29,"Sofort",Cockpit!C26:C29),0) -> 0 | E28: 0 | F28: 0 | G28: 0 | H28: 0 | I28: 0 | J28: 0 | K28: 0 | L28: 0 | M28: 0 | N28: 0 | O28: 0 | P28: 0 | Q28: 0 | R28: 0 | S28: 0 | T28: 0 | U28: 0 | V28: 0 | W28: 0 | X28: 0 | Y28: 0 | Z28: 0 | AA28: 0 | AB28: 0 | AC28: 0 | AD28: 0 | AE28: 0 | AF28: 0 | AG28: 0 | AH28: 0 | AI28: 0 | AJ28: 0 | AK28: 0 | AL28: 0 | AM28: 0 | AN28: 0 | AO28: 0 | AP28: 0 | AQ28: 0 | AR28: 0 | AS28: 0 | AT28: 0 | AU28: 0 | AV28: 0 | AW28: 0 | AX28: 0 | AY28: 0 | AZ28: 0 | BA28: 0
B29: =CONCATENATE("Abschreibung über 10 Jahre (",SUMIF(Cockpit!D26:D29,"10 Jahre",Cockpit!C26:C29)," €)") -> Abschreibung über 10 Jahre (0 €) | D29: =SUMIF(Cockpit!D26:D29,"10 Jahre",Cockpit!C26:C29)/10 -> 0 | E29: =D29 -> 0 | F29: =E29 -> 0 | G29: =F29 -> 0 | H29: =G29 -> 0 | I29: =H29 -> 0 | J29: =I29 -> 0 | K29: =J29 -> 0 | L29: =K29 -> 0 | M29: =L29 -> 0 | N29: 0 | O29: 0 | P29: 0 | Q29: 0 | R29: 0 | S29: 0 | T29: 0 | U29: 0 | V29: 0 | W29: 0 | X29: 0 | Y29: 0 | Z29: 0 | AA29: 0 | AB29: 0 | AC29: 0 | AD29: 0 | AE29: 0 | AF29: 0 | AG29: 0 | AH29: 0 | AI29: 0 | AJ29: 0 | AK29: 0 | AL29: 0 | AM29: 0 | AN29: 0 | AO29: 0 | AP29: 0 | AQ29: 0 | AR29: 0 | AS29: 0 | AT29: 0 | AU29: 0 | AV29: 0 | AW29: 0 | AX29: 0 | AY29: 0 | AZ29: 0 | BA29: 0
B30: =CONCATENATE("Abschreibung über 15 Jahre (",SUMIF(Cockpit!D26:D29,"15 Jahre",Cockpit!C26:C29)," €)") -> Abschreibung über 15 Jahre (0 €) | D30: =SUMIF(Cockpit!D26:D29,"15 Jahre",Cockpit!C26:C29)/15 -> 0 | E30: =D30 -> 0 | F30: =E30 -> 0 | G30: =F30 -> 0 | H30: =G30 -> 0 | I30: =H30 -> 0 | J30: =I30 -> 0 | K30: =J30 -> 0 | L30: =K30 -> 0 | ... R30: =Q30 -> 0 | S30: 0 | T30: 0 | U30: 0 | V30: 0 | W30: 0 | X30: 0 | Y30: 0 | Z30: 0 | AA30: 0 | AB30: 0 | AC30: 0 | AD30: 0 | AE30: 0 | AF30: 0 | AG30: 0 | AH30: 0 | AI30: 0 | AJ30: 0 | AK30: 0 | AL30: 0 | AM30: 0 | AN30: 0 | AO30: 0 | AP30: 0 | AQ30: 0 | AR30: 0 | AS30: 0 | AT30: 0 | AU30: 0 | AV30: 0 | AW30: 0 | AX30: 0 | AY30: 0 | AZ30: 0 | BA30: 0
B31: =CONCATENATE("Abschreibung über 50 Jahre (",SUMIF(Cockpit!D26:D29,"50 Jahre",Cockpit!C26:C29)," €)") -> Abschreibung über 50 Jahre (0 €) | D31: =SUMIF(Cockpit!D26:D29,"50 Jahre",Cockpit!C26:C29)/50 -> 0 | E31: =D31 -> 0 | F31: =E31 -> 0 | G31: =F31 -> 0 | H31: =G31 -> 0 | I31: =H31 -> 0 | J31: =I31 -> 0 | K31: =J31 -> 0 | L31: =K31 -> 0 | ... BA31: =AZ31 -> 0
B32: =CONCATENATE("Abschreibung über 67 Jahre (",SUMIF(Cockpit!D26:D29,"67 Jahre",Cockpit!C26:C29)," €)") -> Abschreibung über 67 Jahre (0 €) | D32: =SUMIF(Cockpit!D26:D29,"67 Jahre",Cockpit!C26:C29)/67 -> 0 | E32: =D32 -> 0 | F32: =E32 -> 0 | G32: =F32 -> 0 | H32: =G32 -> 0 | I32: =H32 -> 0 | J32: =I32 -> 0 | K32: =J32 -> 0 | L32: =K32 -> 0 | ... BA32: =AZ32 -> 0
B33: Summe pro Jahr | D33: =SUM(D28:D32) -> 0 | E33: =SUM(E28:E32) -> 0 | F33: =SUM(F28:F32) -> 0 | G33: =SUM(G28:G32) -> 0 | H33: =SUM(H28:H32) -> 0 | I33: =SUM(I28:I32) -> 0 | J33: =SUM(J28:J32) -> 0 | K33: =SUM(K28:K32) -> 0 | ... BA33: =SUM(BA28:BA32) -> 0
B34: = pro Monat | D34: =D33/12 -> 0 | E34: =E33/12 -> 0 | F34: =F33/12 -> 0 | G34: =G33/12 -> 0 | H34: =H33/12 -> 0 | I34: =I33/12 -> 0 | J34: =J33/12 -> 0 | K34: =K33/12 -> 0 | ... BA34: =BA33/12 -> 0
B36: Darlehen I
B37: € | D37: =D$7 -> 2024 | E37: =E$7 -> 2025 | F37: =F$7 -> 2026 | G37: =G$7 -> 2027 | H37: =H$7 -> 2028 | I37: =I$7 -> 2029 | J37: =J$7 -> 2030 | K37: =K$7 -> 2031 | ... BA37: =BA$7 -> 2073
B38: Zinsänderung
B39: Gültiger Zinssatz | D39: =Cockpit!N18 -> 0.037 | E39: =IF(E38<>"",E38,D39) -> 0.037 | F39: =IF(F38<>"",F38,E39) -> 0.037 | G39: =IF(G38<>"",G38,F39) -> 0.037 | H39: =IF(H38<>"",H38,G39) -> 0.037 | I39: =IF(I38<>"",I38,H39) -> 0.037 | J39: =IF(J38<>"",J38,I39) -> 0.037 | K39: =IF(K38<>"",K38,J39) -> 0.037 | L39: =IF(L38<>"",L38,K39) -> 0.037 | ... BA39: =IF(BA38<>"",BA38,AZ39) -> 0.037
B41: Restschuld Periodenbeginn | D41: =Cockpit!N17 -> 100000 | E41: =D50 -> 97700 | F41: =E50 -> 85314.9 | G41: =F50 -> 82471.551 | H41: =G50 -> 79522.999 | I41: =H50 -> 76465.35 | J41: =I50 -> 73294.568 | K41: =J50 -> 70006.467 | L41: =K50 -> 66596.706 | ... BA41: =AZ50 -> 0
B42: Zinsen | D42: =D39*D41 -> 3700 | E42: =E39*E41 -> 3614.9 | F42: =F39*F41 -> 3156.6513 | G42: =G39*G41 -> 3051.4474 | H42: =H39*H41 -> 2942.351 | I42: =I39*I41 -> 2829.2179 | J42: =J39*J41 -> 2711.899 | K42: =K39*K41 -> 2590.2393 | ... BA42: =BA39*BA41 -> 0
B44: Neue Soll-Tilgung
B45: Effektive Tilgung | D45: =Cockpit!$N$19*D41 -> 2300 | E45: =MIN(D50,IF(E44<>"",E44,MAX(D48-E42,0))) -> 2385.1 | F45: =MIN(E50,IF(F44<>"",F44,MAX(E48-F42,0))) -> 2843.3487 | G45: =MIN(F50,IF(G44<>"",G44,MAX(F48-G42,0))) -> 2948.5526 | H45: =MIN(G50,IF(H44<>"",H44,MAX(G48-H42,0))) -> 3057.649 | I45: =MIN(H50,IF(I44<>"",I44,MAX(H48-I42,0))) -> 3170.7821 | J45: =MIN(I50,IF(J44<>"",J44,MAX(I48-J42,0))) -> 3288.101 | K45: =MIN(J50,IF(K44<>"",K44,MAX(J48-K42,0))) -> 3409.7607 | L45: =MIN(K50,IF(L44<>"",L44,MAX(K48-L42,0))) -> 3535.9219 | ... BA45: =MIN(AZ50,IF(BA44<>"",BA44,MAX(AZ48-BA42,0))) -> 0
B46: entspricht % der Restschuld | D46: =IF(D41>0,D45/D41,) -> 0.023 | E46: =IF(E41>0,E45/E41,) -> 0.024412487 | F46: =IF(F41>0,F45/F41,) -> 0.033327692 | G46: =IF(G41>0,G45/G41,) -> 0.03575236 | H46: =IF(H41>0,H45/H41,) -> 0.038449871 | I46: =IF(I41>0,I45/I41,) -> 0.041466914 | J46: =IF(J41>0,J45/J41,) -> 0.044861456 | K46: =IF(K41>0,K45/K41,) -> 0.048706368 | ... BA46: =IF(BA41>0,BA45/BA41,) -> 0
B48: Annuität | D48: =D42+D45 -> 6000 | E48: =E42+E45 -> 6000 | F48: =F42+F45 -> 6000 | G48: =G42+G45 -> 6000 | H48: =H42+H45 -> 6000 | I48: =I42+I45 -> 6000 | J48: =J42+J45 -> 6000 | K48: =K42+K45 -> 6000 | ... BA48: =BA42+BA45 -> 0
B49: Einmalige Sondertilgung | E49: 10000
B50: Restschuld Periodenende | D50: =MAX(D41-D45-D49,0) -> 97700 | E50: =MAX(E41-E45-E49,0) -> 85314.9 | F50: =MAX(F41-F45-F49,0) -> 82471.551 | G50: =MAX(G41-G45-G49,0) -> 79522.999 | H50: =MAX(H41-H45-H49,0) -> 76465.35 | I50: =MAX(I41-I45-I49,0) -> 73294.568 | J50: =MAX(J41-J45-J49,0) -> 70006.467 | K50: =MAX(K41-K45-K49,0) -> 66596.706 | ... BA50: =MAX(BA41-BA45-BA49,0) -> 0
B51: Kapitaldienst pro Monat | D51: =D48/12 -> 500 | E51: =E48/12 -> 500 | F51: =F48/12 -> 500 | G51: =G48/12 -> 500 | H51: =H48/12 -> 500 | I51: =I48/12 -> 500 | J51: =J48/12 -> 500 | K51: =K48/12 -> 500 | ... BA51: =BA48/12 -> 0
B53: Darlehen II
B54: € | D54: =D$7 -> 2024 | E54: =E$7 -> 2025 | F54: =F$7 -> 2026 | G54: =G$7 -> 2027 | H54: =H$7 -> 2028 | I54: =I$7 -> 2029 | J54: =J$7 -> 2030 | K54: =K$7 -> 2031 | ... BA54: =BA$7 -> 2073
B55: Zinsänderung
B56: Gültiger Zinssatz | D56: =Cockpit!N26 -> 0.02 | E56: =IF(E55<>"",E55,D56) -> 0.02 | F56: =IF(F55<>"",F55,E56) -> 0.02 | G56: =IF(G55<>"",G55,F56) -> 0.02 | H56: =IF(H55<>"",H55,G56) -> 0.02 | I56: =IF(I55<>"",I55,H56) -> 0.02 | J56: =IF(J55<>"",J55,I56) -> 0.02 | K56: =IF(K55<>"",K55,J56) -> 0.02 | L56: =IF(L55<>"",L55,K56) -> 0.02 | ... BA56: =IF(BA55<>"",BA55,AZ56) -> 0.02
B58: Restschuld Periodenbeginn | D58: =Cockpit!N25 -> 0 | E58: =D67 -> 0 | F58: =E67 -> 0 | G58: =F67 -> 0 | H58: =G67 -> 0 | I58: =H67 -> 0 | J58: =I67 -> 0 | K58: =J67 -> 0 | L58: =K67 -> 0 | ... BA58: =AZ67 -> 0
B59: Zinsen | D59: =D56*D58 -> 0 | E59: =E56*E58 -> 0 | F59: =F56*F58 -> 0 | G59: =G56*G58 -> 0 | H59: =H56*H58 -> 0 | I59: =I56*I58 -> 0 | J59: =J56*J58 -> 0 | K59: =K56*K58 -> 0 | ... BA59: =BA56*BA58 -> 0
B61: Neue Soll-Tilgung
B62: Effektive Tilgung | D62: =Cockpit!$N$27*D58 -> 0 | E62: =MIN(D67,IF(E61<>"",E61,MAX(D65-E59,0))) -> 0 | F62: =MIN(E67,IF(F61<>"",F61,MAX(E65-F59,0))) -> 0 | G62: =MIN(F67,IF(G61<>"",G61,MAX(F65-G59,0))) -> 0 | H62: =MIN(G67,IF(H61<>"",H61,MAX(G65-H59,0))) -> 0 | I62: =MIN(H67,IF(I61<>"",I61,MAX(H65-I59,0))) -> 0 | J62: =MIN(I67,IF(J61<>"",J61,MAX(I65-J59,0))) -> 0 | K62: =MIN(J67,IF(K61<>"",K61,MAX(J65-K59,0))) -> 0 | L62: =MIN(K67,IF(L61<>"",L61,MAX(K65-L59,0))) -> 0 | ... BA62: =MIN(AZ67,IF(BA61<>"",BA61,MAX(AZ65-BA59,0))) -> 0
B63: entspricht % der Restschuld | D63: =IF(D58>0,D62/D58,) -> 0 | E63: =IF(E58>0,E62/E58,) -> 0 | F63: =IF(F58>0,F62/F58,) -> 0 | G63: =IF(G58>0,G62/G58,) -> 0 | H63: =IF(H58>0,H62/H58,) -> 0 | I63: =IF(I58>0,I62/I58,) -> 0 | J63: =IF(J58>0,J62/J58,) -> 0 | K63: =IF(K58>0,K62/K58,) -> 0 | ... BA63: =IF(BA58>0,BA62/BA58,) -> 0
B65: Annuität | D65: =D59+D62 -> 0 | E65: =E59+E62 -> 0 | F65: =F59+F62 -> 0 | G65: =G59+G62 -> 0 | H65: =H59+H62 -> 0 | I65: =I59+I62 -> 0 | J65: =J59+J62 -> 0 | K65: =K59+K62 -> 0 | ... BA65: =BA59+BA62 -> 0
B66: Einmalige Sondertilgung
B67: Restschuld Periodenende | D67: =MAX(D58-D62-D66,0) -> 0 | E67: =MAX(E58-E62-E66,0) -> 0 | F67: =MAX(F58-F62-F66,0) -> 0 | G67: =MAX(G58-G62-G66,0) -> 0 | H67: =MAX(H58-H62-H66,0) -> 0 | I67: =MAX(I58-I62-I66,0) -> 0 | J67: =MAX(J58-J62-J66,0) -> 0 | K67: =MAX(K58-K62-K66,0) -> 0 | ... BA67: =MAX(BA58-BA62-BA66,0) -> 0
B68: Kapitaldienst pro Monat | D68: =D65/12 -> 0 | E68: =E65/12 -> 0 | F68: =F65/12 -> 0 | G68: =G65/12 -> 0 | H68: =H65/12 -> 0 | I68: =I65/12 -> 0 | J68: =J65/12 -> 0 | K68: =K65/12 -> 0 | ... BA68: =BA65/12 -> 0
B70: Darlehen III
B71: € | D71: =D$7 -> 2024 | E71: =E$7 -> 2025 | F71: =F$7 -> 2026 | G71: =G$7 -> 2027 | H71: =H$7 -> 2028 | I71: =I$7 -> 2029 | J71: =J$7 -> 2030 | K71: =K$7 -> 2031 | ... BA71: =BA$7 -> 2073
B72: Zinsänderung
B73: Gültiger Zinssatz | D73: =Cockpit!N33 -> 0.03 | E73: =IF(E72<>"",E72,D73) -> 0.03 | F73: =IF(F72<>"",F72,E73) -> 0.03 | G73: =IF(G72<>"",G72,F73) -> 0.03 | H73: =IF(H72<>"",H72,G73) -> 0.03 | I73: =IF(I72<>"",I72,H73) -> 0.03 | J73: =IF(J72<>"",J72,I73) -> 0.03 | K73: =IF(K72<>"",K72,J73) -> 0.03 | L73: =IF(L72<>"",L72,K73) -> 0.03 | ... BA73: =IF(BA72<>"",BA72,AZ73) -> 0.03
B75: Restschuld Periodenbeginn | D75: =Cockpit!N32 -> 0 | E75: =D84 -> 0 | F75: =E84 -> 0 | G75: =F84 -> 0 | H75: =G84 -> 0 | I75: =H84 -> 0 | J75: =I84 -> 0 | K75: =J84 -> 0 | L75: =K84 -> 0 | ... BA75: =AZ84 -> 0
B76: Zinsen | D76: =D73*D75 -> 0 | E76: =E73*E75 -> 0 | F76: =F73*F75 -> 0 | G76: =G73*G75 -> 0 | H76: =H73*H75 -> 0 | I76: =I73*I75 -> 0 | J76: =J73*J75 -> 0 | K76: =K73*K75 -> 0 | ... BA76: =BA73*BA75 -> 0
B78: Neue Soll-Tilgung
B79: Effektive Tilgung | D79: =Cockpit!$N$34*D75 -> 0 | E79: =MIN(D84,IF(E78<>"",E78,MAX(D82-E76,0))) -> 0 | F79: =MIN(E84,IF(F78<>"",F78,MAX(E82-F76,0))) -> 0 | G79: =MIN(F84,IF(G78<>"",G78,MAX(F82-G76,0))) -> 0 | H79: =MIN(G84,IF(H78<>"",H78,MAX(G82-H76,0))) -> 0 | I79: =MIN(H84,IF(I78<>"",I78,MAX(H82-I76,0))) -> 0 | J79: =MIN(I84,IF(J78<>"",J78,MAX(I82-J76,0))) -> 0 | K79: =MIN(J84,IF(K78<>"",K78,MAX(J82-K76,0))) -> 0 | L79: =MIN(K84,IF(L78<>"",L78,MAX(K82-L76,0))) -> 0 | ... BA79: =MIN(AZ84,IF(BA78<>"",BA78,MAX(AZ82-BA76,0))) -> 0
B80: entspricht % der Restschuld | D80: =IF(D75>0,D79/D75,) -> 0 | E80: =IF(E75>0,E79/E75,) -> 0 | F80: =IF(F75>0,F79/F75,) -> 0 | G80: =IF(G75>0,G79/G75,) -> 0 | H80: =IF(H75>0,H79/H75,) -> 0 | I80: =IF(I75>0,I79/I75,) -> 0 | J80: =IF(J75>0,J79/J75,) -> 0 | K80: =IF(K75>0,K79/K75,) -> 0 | ... BA80: =IF(BA75>0,BA79/BA75,) -> 0
B82: Annuität | D82: =D76+D79 -> 0 | E82: =E76+E79 -> 0 | F82: =F76+F79 -> 0 | G82: =G76+G79 -> 0 | H82: =H76+H79 -> 0 | I82: =I76+I79 -> 0 | J82: =J76+J79 -> 0 | K82: =K76+K79 -> 0 | ... BA82: =BA76+BA79 -> 0
B83: Einmalige Sondertilgung
B84: Restschuld Periodenende | D84: =MAX(D75-D79-D83,0) -> 0 | E84: =MAX(E75-E79-E83,0) -> 0 | F84: =MAX(F75-F79-F83,0) -> 0 | G84: =MAX(G75-G79-G83,0) -> 0 | H84: =MAX(H75-H79-H83,0) -> 0 | I84: =MAX(I75-I79-I83,0) -> 0 | J84: =MAX(J75-J79-J83,0) -> 0 | K84: =MAX(K75-K79-K83,0) -> 0 | ... BA84: =MAX(BA75-BA79-BA83,0) -> 0
B85: Kapitaldienst pro Monat | D85: =D82/12 -> 0 | E85: =E82/12 -> 0 | F85: =F82/12 -> 0 | G85: =G82/12 -> 0 | H85: =H82/12 -> 0 | I85: =I82/12 -> 0 | J85: =J82/12 -> 0 | K85: =K82/12 -> 0 | ... BA85: =BA82/12 -> 0
B87: Darlehen IV
B88: € | D88: =D$7 -> 2024 | E88: =E$7 -> 2025 | F88: =F$7 -> 2026 | G88: =G$7 -> 2027 | H88: =H$7 -> 2028 | I88: =I$7 -> 2029 | J88: =J$7 -> 2030 | K88: =K$7 -> 2031 | ... BA88: =BA$7 -> 2073
B89: Zinsänderung
B90: Gültiger Zinssatz | D90: =Cockpit!N40 -> 0 | E90: =IF(E89<>"",E89,D90) -> 0 | F90: =IF(F89<>"",F89,E90) -> 0 | G90: =IF(G89<>"",G89,F90) -> 0 | H90: =IF(H89<>"",H89,G90) -> 0 | I90: =IF(I89<>"",I89,H90) -> 0 | J90: =IF(J89<>"",J89,I90) -> 0 | K90: =IF(K89<>"",K89,J90) -> 0 | L90: =IF(L89<>"",L89,K90) -> 0 | ... BA90: =IF(BA89<>"",BA89,AZ90) -> 0
B92: Restschuld Periodenbeginn | D92: =Cockpit!N39 -> 0 | E92: =D101 -> 0 | F92: =E101 -> 0 | G92: =F101 -> 0 | H92: =G101 -> 0 | I92: =H101 -> 0 | J92: =I101 -> 0 | K92: =J101 -> 0 | L92: =K101 -> 0 | ... BA92: =AZ101 -> 0
B93: Zinsen | D93: =D90*D92 -> 0 | E93: =E90*E92 -> 0 | F93: =F90*F92 -> 0 | G93: =G90*G92 -> 0 | H93: =H90*H92 -> 0 | I93: =I90*I92 -> 0 | J93: =J90*J92 -> 0 | K93: =K90*K92 -> 0 | ... BA93: =BA90*BA92 -> 0
B95: Neue Soll-Tilgung
B96: Effektive Tilgung | D96: =Cockpit!$N$41*D92 -> 0 | E96: =MIN(D101,IF(E95<>"",E95,MAX(D99-E93,0))) -> 0 | F96: =MIN(E101,IF(F95<>"",F95,MAX(E99-F93,0))) -> 0 | G96: =MIN(F101,IF(G95<>"",G95,MAX(F99-G93,0))) -> 0 | H96: =MIN(G101,IF(H95<>"",H95,MAX(G99-H93,0))) -> 0 | I96: =MIN(H101,IF(I95<>"",I95,MAX(H99-I93,0))) -> 0 | J96: =MIN(I101,IF(J95<>"",J95,MAX(I99-J93,0))) -> 0 | K96: =MIN(J101,IF(K95<>"",K95,MAX(J99-K93,0))) -> 0 | L96: =MIN(K101,IF(L95<>"",L95,MAX(K99-L93,0))) -> 0 | ... BA96: =MIN(AZ101,IF(BA95<>"",BA95,MAX(AZ99-BA93,0))) -> 0
B97: entspricht % der Restschuld | D97: =IF(D92>0,D96/D92,) -> 0 | E97: =IF(E92>0,E96/E92,) -> 0 | F97: =IF(F92>0,F96/F92,) -> 0 | G97: =IF(G92>0,G96/G92,) -> 0 | H97: =IF(H92>0,H96/H92,) -> 0 | I97: =IF(I92>0,I96/I92,) -> 0 | J97: =IF(J92>0,J96/J92,) -> 0 | K97: =IF(K92>0,K96/K92,) -> 0 | ... BA97: =IF(BA92>0,BA96/BA92,) -> 0
B99: Annuität | D99: =D93+D96 -> 0 | E99: =E93+E96 -> 0 | F99: =F93+F96 -> 0 | G99: =G93+G96 -> 0 | H99: =H93+H96 -> 0 | I99: =I93+I96 -> 0 | J99: =J93+J96 -> 0 | K99: =K93+K96 -> 0 | ... BA99: =BA93+BA96 -> 0
B100: Einmalige Sondertilgung
B101: Restschuld Periodenende | D101: =MAX(D92-D96-D100,0) -> 0 | E101: =MAX(E92-E96-E100,0) -> 0 | F101: =MAX(F92-F96-F100,0) -> 0 | G101: =MAX(G92-G96-G100,0) -> 0 | H101: =MAX(H92-H96-H100,0) -> 0 | I101: =MAX(I92-I96-I100,0) -> 0 | J101: =MAX(J92-J96-J100,0) -> 0 | K101: =MAX(K92-K96-K100,0) -> 0 | ... BA101: =MAX(BA92-BA96-BA100,0) -> 0
B102: Kapitaldienst pro Monat | D102: =D99/12 -> 0 | E102: =E99/12 -> 0 | F102: =F99/12 -> 0 | G102: =G99/12 -> 0 | H102: =H99/12 -> 0 | I102: =I99/12 -> 0 | J102: =J99/12 -> 0 | K102: =K99/12 -> 0 | ... BA102: =BA99/12 -> 0
B104: Summe der Darlehen
B105: € | D105: =D$7 -> 2024 | E105: =E$7 -> 2025 | F105: =F$7 -> 2026 | G105: =G$7 -> 2027 | H105: =H$7 -> 2028 | I105: =I$7 -> 2029 | J105: =J$7 -> 2030 | K105: =K$7 -> 2031 | ... BA105: =BA$7 -> 2073
B106: Restschuld Periodenbeginn | D106: =D41+D58+D75+D92 -> 100000 | E106: =E41+E58+E75+E92 -> 97700 | F106: =F41+F58+F75+F92 -> 85314.9 | G106: =G41+G58+G75+G92 -> 82471.551 | H106: =H41+H58+H75+H92 -> 79522.999 | I106: =I41+I58+I75+I92 -> 76465.35 | J106: =J41+J58+J75+J92 -> 73294.568 | K106: =K41+K58+K75+K92 -> 70006.467 | ... BA106: =BA41+BA58+BA75+BA92 -> 0
B107: davon Hauptdarlehen (I) | D107: =D41 -> 100000 | E107: =E41 -> 97700 | F107: =F41 -> 85314.9 | G107: =G41 -> 82471.551 | H107: =H41 -> 79522.999 | I107: =I41 -> 76465.35 | J107: =J41 -> 73294.568 | K107: =K41 -> 70006.467 | ... BA107: =BA41 -> 0
B108: davon weitere Darlehen (II - IV) | D108: =D58+D75+D92 -> 0 | E108: =E58+E75+E92 -> 0 | F108: =F58+F75+F92 -> 0 | G108: =G58+G75+G92 -> 0 | H108: =H58+H75+H92 -> 0 | I108: =I58+I75+I92 -> 0 | J108: =J58+J75+J92 -> 0 | K108: =K58+K75+K92 -> 0 | ... BA108: =BA58+BA75+BA92 -> 0
B110: Zinsen | D110: =D42+D59+D76+D93 -> 3700 | E110: =E42+E59+E76+E93 -> 3614.9 | F110: =F42+F59+F76+F93 -> 3156.6513 | G110: =G42+G59+G76+G93 -> 3051.4474 | H110: =H42+H59+H76+H93 -> 2942.351 | I110: =I42+I59+I76+I93 -> 2829.2179 | J110: =J42+J59+J76+J93 -> 2711.899 | K110: =K42+K59+K76+K93 -> 2590.2393 | ... BA110: =BA42+BA59+BA76+BA93 -> 0
B111: = kumuliert | D111: =D110 -> 3700 | E111: =D111+E110 -> 7314.9 | F111: =E111+F110 -> 10471.551 | G111: =F111+G110 -> 13522.999 | H111: =G111+H110 -> 16465.35 | I111: =H111+I110 -> 19294.568 | J111: =I111+J110 -> 22006.467 | K111: =J111+K110 -> 24596.706 | L111: =K111+L110 -> 27060.784 | ... BA111: =AZ111+BA110 -> 45352.646
B112: = gewichteter Zinssatz | D112: =IF(D106>0,D110/D106,) -> 0.037 | E112: =IF(E106>0,E110/E106,) -> 0.037 | F112: =IF(F106>0,F110/F106,) -> 0.037 | G112: =IF(G106>0,G110/G106,) -> 0.037 | H112: =IF(H106>0,H110/H106,) -> 0.037 | I112: =IF(I106>0,I110/I106,) -> 0.037 | J112: =IF(J106>0,J110/J106,) -> 0.037 | K112: =IF(K106>0,K110/K106,) -> 0.037 | ... BA112: =IF(BA106>0,BA110/BA106,) -> 0
B114: Tilgung | D114: =D45+D62+D79+D96 -> 2300 | E114: =E45+E62+E79+E96 -> 2385.1 | F114: =F45+F62+F79+F96 -> 2843.3487 | G114: =G45+G62+G79+G96 -> 2948.5526 | H114: =H45+H62+H79+H96 -> 3057.649 | I114: =I45+I62+I79+I96 -> 3170.7821 | J114: =J45+J62+J79+J96 -> 3288.101 | K114: =K45+K62+K79+K96 -> 3409.7607 | ... BA114: =BA45+BA62+BA79+BA96 -> 0
B115: entspricht % der Restschuld | D115: =IF(D106>0,D114/D106,) -> 0.023 | E115: =IF(E106>0,E114/E106,) -> 0.024412487 | F115: =IF(F106>0,F114/F106,) -> 0.033327692 | G115: =IF(G106>0,G114/G106,) -> 0.03575236 | H115: =IF(H106>0,H114/H106,) -> 0.038449871 | I115: =IF(I106>0,I114/I106,) -> 0.041466914 | J115: =IF(J106>0,J114/J106,) -> 0.044861456 | K115: =IF(K106>0,K114/K106,) -> 0.048706368 | ... BA115: =IF(BA106>0,BA114/BA106,) -> 0
B117: Annuität | D117: =D48+D65+D82+D99 -> 6000 | E117: =E48+E65+E82+E99 -> 6000 | F117: =F48+F65+F82+F99 -> 6000 | G117: =G48+G65+G82+G99 -> 6000 | H117: =H48+H65+H82+H99 -> 6000 | I117: =I48+I65+I82+I99 -> 6000 | J117: =J48+J65+J82+J99 -> 6000 | K117: =K48+K65+K82+K99 -> 6000 | ... BA117: =BA48+BA65+BA82+BA99 -> 0
B118: Restschuld Periodenende | D118: =D50+D67+D84+D101 -> 97700 | E118: =E50+E67+E84+E101 -> 85314.9 | F118: =F50+F67+F84+F101 -> 82471.551 | G118: =G50+G67+G84+G101 -> 79522.999 | H118: =H50+H67+H84+H101 -> 76465.35 | I118: =I50+I67+I84+I101 -> 73294.568 | J118: =J50+J67+J84+J101 -> 70006.467 | K118: =K50+K67+K84+K101 -> 66596.706 | ... BA118: =BA50+BA67+BA84+BA101 -> 0
B119: Kapitaldienst pro Monat | D119: =D51+D68+D85+D102 -> 500 | E119: =E51+E68+E85+E102 -> 500 | F119: =F51+F68+F85+F102 -> 500 | G119: =G51+G68+G85+G102 -> 500 | H119: =H51+H68+H85+H102 -> 500 | I119: =I51+I68+I85+I102 -> 500 | J119: =J51+J68+J85+J102 -> 500 | K119: =K51+K68+K85+K102 -> 500 | ... BA119: =BA51+BA68+BA85+BA102 -> 0
B121: Keine Gewähr für die Richtigkeit der Angaben. Dieses Tool ersetzt keine fundierte Rechts-, Steuer- oder Finanzberatung. Mehr Details hier.

Sheet Szenarien
C1: zurück zum Cockpit | P1: Szenarien-Vergleich
B6: Sprünge | U6: Sprünge
B7: 5000 | C7: Darlehen I % Kaufpreis | D7: Darlehen I Summe | E7: Darlehen I Zinssatz | F7: Darlehen I Tilgung | G7: Kaltmiete | H7: Bruttokaltmiete | I7: Bewirtschaftungskosten | J7: Zinsen | K7: Tilgung | L7: CF operativ | M7: Hausgeld und weitere Kosten | N7: AfA | O7: Steuern | P7: Cashflow nach Steuern (Monat) | R7: Kaufpreis | S7: Darlehen I % Kaufpreis | T7: Darlehen I Summe | U7: 0.001 | V7: Darlehen I Tilgung | W7: Kaltmiete | X7: Bruttokaltmiete | Y7: Bewirtschaftungskosten | Z7: Zinsen | AA7: Tilgung | AB7: CF operativ | AC7: Hausgeld und weitere Kosten | AD7: AfA | AE7: Steuern | AF7: Cashflow nach Steuern (Monat) | AH7: Ausgangsdaten
B8: Kaufpreis | U8: Zinssatz
B9: =B10+$B$7 -> 145000 | C9: =$AL$10 -> 0.8 | D9: =B9*C9 -> 116000 | E9: =$AL$11 -> 0.037 | F9: =$AL$12 -> 0.023 | G9: =$AL$13 -> 529.375 | H9: =G9+Cockpit!$K$9 -> 640.375 | I9: =-Cockpit!$K$12-Cockpit!$H$25*(Szenarien!G9-Szenarien!$AL$13) -> -210.50292 | J9: =Cockpit!$Q$21-E9*(D9-$D13)/12 -> -357.66667 | K9: =Cockpit!$Q$22-F9*(D9-$D13)/12 -> -222.33333 | L9: =H9+I9+J9+K9 -> -150.12792 | M9: =Cockpit!$Q$29 -> -156 | N9: =Cockpit!$Q$31-Cockpit!$H$20*Cockpit!$H$21*(1+Cockpit!$D$22)*(B9-$B13)/12 -> -119.47875 | O9: =(H9+J9+M9+N9)*Cockpit!$Q$33 -> 2.8918333 | P9: =L9-O9 -> -153.01975 | R9: =$AL$9 -> 125000 | S9: =$AL$10 -> 0.8 | T9: =R9*S9 -> 100000 | U9: =U10+$U$7 -> 0.041 | V9: =$AL$12 -> 0.023 | W9: =$AL$13 -> 529.375 | X9: =W9+Cockpit!$K$9 -> 640.375 | Y9: =-Cockpit!$K$12-Cockpit!$H$25*(Szenarien!W9-Szenarien!$AL$13) -> -210.50292 | Z9: =Cockpit!$Q$21-U9*(T9-$T$13)/12-(U9-$U$13)*$T$13/12 -> -341.66667 | AA9: =Cockpit!$Q$22-V9*(T9-$T$13)/12-(V9-$V$13)*$T$13/12 -> -191.66667 | AB9: =X9+Y9+Z9+AA9 -> -103.46125 | AC9: =Cockpit!$Q$29 -> -156 | AD9: =Cockpit!$Q$31-Cockpit!$H$20*Cockpit!$H$21*(1+Cockpit!$D$22)*(R9-$R13)/12 -> -102.84375 | AE9: =(X9+Z9+AC9+AD9)*Cockpit!$Q$33 -> 15.945833 | AF9: =AB9-AE9 -> -119.40708 | AH9: Kaufpreis | AL9: =Cockpit!D14 -> 125000
B10: =B11+$B$7 -> 140000 | C10: =$AL$10 -> 0.8 | D10: =B10*C10 -> 112000 | E10: =$AL$11 -> 0.037 | F10: =$AL$12 -> 0.023 | G10: =$AL$13 -> 529.375 | H10: =G10+Cockpit!$K$9 -> 640.375 | I10: =-Cockpit!$K$12-Cockpit!$H$25*(Szenarien!G10-Szenarien!$AL$13) -> -210.50292 | J10: =Cockpit!$Q$21-E10*(D10-$D13)/12 -> -345.33333 | K10: =Cockpit!$Q$22-F10*(D10-$D13)/12 -> -214.66667 | L10: =H10+I10+J10+K10 -> -130.12792 | M10: =Cockpit!$Q$29 -> -156 | N10: =Cockpit!$Q$31-Cockpit!$H$20*Cockpit!$H$21*(1+Cockpit!$D$22)*(B10-$B13)/12 -> -115.32 | O10: =(H10+J10+M10+N10)*Cockpit!$Q$33 -> 9.4886667 | P10: =L10-O10 -> -139.61658 | R10: =$AL$9 -> 125000 | S10: =$AL$10 -> 0.8 | T10: =R10*S10 -> 100000 | U10: =U11+$U$7 -> 0.04 | V10: =$AL$12 -> 0.023 | W10: =$AL$13 -> 529.375 | X10: =W10+Cockpit!$K$9 -> 640.375 | Y10: =-Cockpit!$K$12-Cockpit!$H$25*(Szenarien!W10-Szenarien!$AL$13) -> -210.50292 | Z10: =Cockpit!$Q$21-U10*(T10-$T$13)/12-(U10-$U$13)*$T$13/12 -> -333.33333 | AA10: =Cockpit!$Q$22-V10*(T10-$T$13)/12-(V10-$V$13)*$T$13/12 -> -191.66667 | AB10: =X10+Y10+Z10+AA10 -> -95.127917 | AC10: =Cockpit!$Q$29 -> -156 | AD10: =Cockpit!$Q$31-Cockpit!$H$20*Cockpit!$H$21*(1+Cockpit!$D$22)*(R10-$R13)/12 -> -102.84375 | AE10: =(X10+Z10+AC10+AD10)*Cockpit!$Q$33 -> 19.279167 | AF10: =AB10-AE10 -> -114.40708 | AH10: Darlehen I % Kaufpreis | AL10: =Cockpit!N17/AL9 -> 0.8
B11: =B12+$B$7 -> 135000 | C11: =$AL$10 -> 0.8 | D11: =B11*C11 -> 108000 | E11: =$AL$11 -> 0.037 | F11: =$AL$12 -> 0.023 | G11: =$AL$13 -> 529.375 | H11: =G11+Cockpit!$K$9 -> 640.375 | I11: =-Cockpit!$K$12-Cockpit!$H$25*(Szenarien!G11-Szenarien!$AL$13) -> -210.50292 | J11: =Cockpit!$Q$21-E11*(D11-$D13)/12 -> -333 | K11: =Cockpit!$Q$22-F11*(D11-$D13)/12 -> -207 | L11: =H11+I11+J11+K11 -> -110.12792 | M11: =Cockpit!$Q$29 -> -156 | N11: =Cockpit!$Q$31-Cockpit!$H$20*Cockpit!$H$21*(1+Cockpit!$D$22)*(B11-$B13)/12 -> -111.16125 | O11: =(H11+J11+M11+N11)*Cockpit!$Q$33 -> 16.0855 | P11: =L11-O11 -> -126.21342 | R11: =$AL$9 -> 125000 | S11: =$AL$10 -> 0.8 | T11: =R11*S11 -> 100000 | U11: =U12+$U$7 -> 0.039 | V11: =$AL$12 -> 0.023 | W11: =$AL$13 -> 529.375 | X11: =W11+Cockpit!$K$9 -> 640.375 | Y11: =-Cockpit!$K$12-Cockpit!$H$25*(Szenarien!W11-Szenarien!$AL$13) -> -210.50292 | Z11: =Cockpit!$Q$21-U11*(T11-$T$13)/12-(U11-$U$13)*$T$13/12 -> -325 | AA11: =Cockpit!$Q$22-V11*(T11-$T$13)/12-(V11-$V$13)*$T$13/12 -> -191.66667 | AB11: =X11+Y11+Z11+AA11 -> -86.794583 | AC11: =Cockpit!$Q$29 -> -156 | AD11: =Cockpit!$Q$31-Cockpit!$H$20*Cockpit!$H$21*(1+Cockpit!$D$22)*(R11-$R13)/12 -> -102.84375 | AE11: =(X11+Z11+AC11+AD11)*Cockpit!$Q$33 -> 22.6125 | AF11: =AB11-AE11 -> -109.40708 | AH11: Zinssatz Darlehen I | AL11: =Cockpit!N18 -> 0.037
B12: =B13+$B$7 -> 130000 | C12: =$AL$10 -> 0.8 | D12: =B12*C12 -> 104000 | E12: =$AL$11 -> 0.037 | F12: =$AL$12 -> 0.023 | G12: =$AL$13 -> 529.375 | H12: =G12+Cockpit!$K$9 -> 640.375 | I12: =-Cockpit!$K$12-Cockpit!$H$25*(Szenarien!G12-Szenarien!$AL$13) -> -210.50292 | J12: =Cockpit!$Q$21-E12*(D12-$D13)/12 -> -320.66667 | K12: =Cockpit!$Q$22-F12*(D12-$D13)/12 -> -199.33333 | L12: =H12+I12+J12+K12 -> -90.127917 | M12: =Cockpit!$Q$29 -> -156 | N12: =Cockpit!$Q$31-Cockpit!$H$20*Cockpit!$H$21*(1+Cockpit!$D$22)*(B12-$B13)/12 -> -107.0025 | O12: =(H12+J12+M12+N12)*Cockpit!$Q$33 -> 22.682333 | P12: =L12-O12 -> -112.81025 | R12: =$AL$9 -> 125000 | S12: =$AL$10 -> 0.8 | T12: =R12*S12 -> 100000 | U12: =U13+$U$7 -> 0.038 | V12: =$AL$12 -> 0.023 | W12: =$AL$13 -> 529.375 | X12: =W12+Cockpit!$K$9 -> 640.375 | Y12: =-Cockpit!$K$12-Cockpit!$H$25*(Szenarien!W12-Szenarien!$AL$13) -> -210.50292 | Z12: =Cockpit!$Q$21-U12*(T12-$T$13)/12-(U12-$U$13)*$T$13/12 -> -316.66667 | AA12: =Cockpit!$Q$22-V12*(T12-$T$13)/12-(V12-$V$13)*$T$13/12 -> -191.66667 | AB12: =X12+Y12+Z12+AA12 -> -78.46125 | AC12: =Cockpit!$Q$29 -> -156 | AD12: =Cockpit!$Q$31-Cockpit!$H$20*Cockpit!$H$21*(1+Cockpit!$D$22)*(R12-$R13)/12 -> -102.84375 | AE12: =(X12+Z12+AC12+AD12)*Cockpit!$Q$33 -> 25.945833 | AF12: =AB12-AE12 -> -104.40708 | AH12: Anfängliche Tilgung Darlehen I | AL12: =Cockpit!N19 -> 0.023
B13: =$AL$9 -> 125000 | C13: =$AL$10 -> 0.8 | D13: =B13*C13 -> 100000 | E13: =$AL$11 -> 0.037 | F13: =$AL$12 -> 0.023 | G13: =$AL$13 -> 529.375 | H13: =G13+Cockpit!$K$9 -> 640.375 | I13: =-Cockpit!$K$12-Cockpit!$H$25*(Szenarien!G13-Szenarien!$AL$13) -> -210.50292 | J13: =Cockpit!$Q$21-E13*(D13-$D13)/12 -> -308.33333 | K13: =Cockpit!$Q$22-F13*(D13-$D13)/12 -> -191.66667 | L13: =H13+I13+J13+K13 -> -70.127917 | M13: =Cockpit!$Q$29 -> -156 | N13: =Cockpit!$Q$31-Cockpit!$H$20*Cockpit!$H$21*(1+Cockpit!$D$22)*(B13-$B13)/12 -> -102.84375 | O13: =(H13+J13+M13+N13)*Cockpit!$Q$33 -> 29.279167 | P13: =L13-O13 -> -99.407083 | R13: =$AL$9 -> 125000 | S13: =$AL$10 -> 0.8 | T13: =R13*S13 -> 100000 | U13: =$AL$11 -> 0.037 | V13: =$AL$12 -> 0.023 | W13: =$AL$13 -> 529.375 | X13: =W13+Cockpit!$K$9 -> 640.375 | Y13: =-Cockpit!$K$12-Cockpit!$H$25*(Szenarien!W13-Szenarien!$AL$13) -> -210.50292 | Z13: =Cockpit!$Q$21-U13*(T13-$T$13)/12-(U13-$U$13)*$T$13/12 -> -308.33333 | AA13: =Cockpit!$Q$22-V13*(T13-$T$13)/12-(V13-$V$13)*$T$13/12 -> -191.66667 | AB13: =X13+Y13+Z13+AA13 -> -70.127917 | AC13: =Cockpit!$Q$29 -> -156 | AD13: =Cockpit!$Q$31-Cockpit!$H$20*Cockpit!$H$21*(1+Cockpit!$D$22)*(R13-$R13)/12 -> -102.84375 | AE13: =(X13+Z13+AC13+AD13)*Cockpit!$Q$33 -> 29.279167 | AF13: =AB13-AE13 -> -99.407083 | AH13: Nettokaltmiete | AL13: =Cockpit!H15 -> 529.375
B14: =B13-$B$7 -> 120000 | C14: =$AL$10 -> 0.8 | D14: =B14*C14 -> 96000 | E14: =$AL$11 -> 0.037 | F14: =$AL$12 -> 0.023 | G14: =$AL$13 -> 529.375 | H14: =G14+Cockpit!$K$9 -> 640.375 | I14: =-Cockpit!$K$12-Cockpit!$H$25*(Szenarien!G14-Szenarien!$AL$13) -> -210.50292 | J14: =Cockpit!$Q$21-E14*(D14-$D13)/12 -> -296 | K14: =Cockpit!$Q$22-F14*(D14-$D13)/12 -> -184 | L14: =H14+I14+J14+K14 -> -50.127917 | M14: =Cockpit!$Q$29 -> -156 | N14: =Cockpit!$Q$31-Cockpit!$H$20*Cockpit!$H$21*(1+Cockpit!$D$22)*(B14-$B13)/12 -> -98.685 | O14: =(H14+J14+M14+N14)*Cockpit!$Q$33 -> 35.876 | P14: =L14-O14 -> -86.003917 | R14: =$AL$9 -> 125000 | S14: =$AL$10 -> 0.8 | T14: =R14*S14 -> 100000 | U14: =U13-$U$7 -> 0.036 | V14: =$AL$12 -> 0.023 | W14: =$AL$13 -> 529.375 | X14: =W14+Cockpit!$K$9 -> 640.375 | Y14: =-Cockpit!$K$12-Cockpit!$H$25*(Szenarien!W14-Szenarien!$AL$13) -> -210.50292 | Z14: =Cockpit!$Q$21-U14*(T14-$T$13)/12-(U14-$U$13)*$T$13/12 -> -300 | AA14: =Cockpit!$Q$22-V14*(T14-$T$13)/12-(V14-$V$13)*$T$13/12 -> -191.66667 | AB14: =X14+Y14+Z14+AA14 -> -61.794583 | AC14: =Cockpit!$Q$29 -> -156 | AD14: =Cockpit!$Q$31-Cockpit!$H$20*Cockpit!$H$21*(1+Cockpit!$D$22)*(R14-$R13)/12 -> -102.84375 | AE14: =(X14+Z14+AC14+AD14)*Cockpit!$Q$33 -> 32.6125 | AF14: =AB14-AE14 -> -94.407083
B15: =B14-$B$7 -> 115000 | C15: =$AL$10 -> 0.8 | D15: =B15*C15 -> 92000 | E15: =$AL$11 -> 0.037 | F15: =$AL$12 -> 0.023 | G15: =$AL$13 -> 529.375 | H15: =G15+Cockpit!$K$9 -> 640.375 | I15: =-Cockpit!$K$12-Cockpit!$H$25*(Szenarien!G15-Szenarien!$AL$13) -> -210.50292 | J15: =Cockpit!$Q$21-E15*(D15-$D13)/12 -> -283.66667 | K15: =Cockpit!$Q$22-F15*(D15-$D13)/12 -> -176.33333 | L15: =H15+I15+J15+K15 -> -30.127917 | M15: =Cockpit!$Q$29 -> -156 | N15: =Cockpit!$Q$31-Cockpit!$H$20*Cockpit!$H$21*(1+Cockpit!$D$22)*(B15-$B13)/12 -> -94.52625 | O15: =(H15+J15+M15+N15)*Cockpit!$Q$33 -> 42.472833 | P15: =L15-O15 -> -72.60075 | R15: =$AL$9 -> 125000 | S15: =$AL$10 -> 0.8 | T15: =R15*S15 -> 100000 | U15: =U14-$U$7 -> 0.035 | V15: =$AL$12 -> 0.023 | W15: =$AL$13 -> 529.375 | X15: =W15+Cockpit!$K$9 -> 640.375 | Y15: =-Cockpit!$K$12-Cockpit!$H$25*(Szenarien!W15-Szenarien!$AL$13) -> -210.50292 | Z15: =Cockpit!$Q$21-U15*(T15-$T$13)/12-(U15-$U$13)*$T$13/12 -> -291.66667 | AA15: =Cockpit!$Q$22-V15*(T15-$T$13)/12-(V15-$V$13)*$T$13/12 -> -191.66667 | AB15: =X15+Y15+Z15+AA15 -> -53.46125 | AC15: =Cockpit!$Q$29 -> -156 | AD15: =Cockpit!$Q$31-Cockpit!$H$20*Cockpit!$H$21*(1+Cockpit!$D$22)*(R15-$R13)/12 -> -102.84375 | AE15: =(X15+Z15+AC15+AD15)*Cockpit!$Q$33 -> 35.945833 | AF15: =AB15-AE15 -> -89.407083
B16: =B15-$B$7 -> 110000 | C16: =$AL$10 -> 0.8 | D16: =B16*C16 -> 88000 | E16: =$AL$11 -> 0.037 | F16: =$AL$12 -> 0.023 | G16: =$AL$13 -> 529.375 | H16: =G16+Cockpit!$K$9 -> 640.375 | I16: =-Cockpit!$K$12-Cockpit!$H$25*(Szenarien!G16-Szenarien!$AL$13) -> -210.50292 | J16: =Cockpit!$Q$21-E16*(D16-$D13)/12 -> -271.33333 | K16: =Cockpit!$Q$22-F16*(D16-$D13)/12 -> -168.66667 | L16: =H16+I16+J16+K16 -> -10.127917 | M16: =Cockpit!$Q$29 -> -156 | N16: =Cockpit!$Q$31-Cockpit!$H$20*Cockpit!$H$21*(1+Cockpit!$D$22)*(B16-$B13)/12 -> -90.3675 | O16: =(H16+J16+M16+N16)*Cockpit!$Q$33 -> 49.069667 | P16: =L16-O16 -> -59.197583 | R16: =$AL$9 -> 125000 | S16: =$AL$10 -> 0.8 | T16: =R16*S16 -> 100000 | U16: =U15-$U$7 -> 0.034 | V16: =$AL$12 -> 0.023 | W16: =$AL$13 -> 529.375 | X16: =W16+Cockpit!$K$9 -> 640.375 | Y16: =-Cockpit!$K$12-Cockpit!$H$25*(Szenarien!W16-Szenarien!$AL$13) -> -210.50292 | Z16: =Cockpit!$Q$21-U16*(T16-$T$13)/12-(U16-$U$13)*$T$13/12 -> -283.33333 | AA16: =Cockpit!$Q$22-V16*(T16-$T$13)/12-(V16-$V$13)*$T$13/12 -> -191.66667 | AB16: =X16+Y16+Z16+AA16 -> -45.127917 | AC16: =Cockpit!$Q$29 -> -156 | AD16: =Cockpit!$Q$31-Cockpit!$H$20*Cockpit!$H$21*(1+Cockpit!$D$22)*(R16-$R13)/12 -> -102.84375 | AE16: =(X16+Z16+AC16+AD16)*Cockpit!$Q$33 -> 39.279167 | AF16: =AB16-AE16 -> -84.407083
B17: =B16-$B$7 -> 105000 | C17: =$AL$10 -> 0.8 | D17: =B17*C17 -> 84000 | E17: =$AL$11 -> 0.037 | F17: =$AL$12 -> 0.023 | G17: =$AL$13 -> 529.375 | H17: =G17+Cockpit!$K$9 -> 640.375 | I17: =-Cockpit!$K$12-Cockpit!$H$25*(Szenarien!G17-Szenarien!$AL$13) -> -210.50292 | J17: =Cockpit!$Q$21-E17*(D17-$D13)/12 -> -259 | K17: =Cockpit!$Q$22-F17*(D17-$D13)/12 -> -161 | L17: =H17+I17+J17+K17 -> 9.8720833 | M17: =Cockpit!$Q$29 -> -156 | N17: =Cockpit!$Q$31-Cockpit!$H$20*Cockpit!$H$21*(1+Cockpit!$D$22)*(B17-$B13)/12 -> -86.20875 | O17: =(H17+J17+M17+N17)*Cockpit!$Q$33 -> 55.6665 | P17: =L17-O17 -> -45.794417 | R17: =$AL$9 -> 125000 | S17: =$AL$10 -> 0.8 | T17: =R17*S17 -> 100000 | U17: =U16-$U$7 -> 0.033 | V17: =$AL$12 -> 0.023 | W17: =$AL$13 -> 529.375 | X17: =W17+Cockpit!$K$9 -> 640.375 | Y17: =-Cockpit!$K$12-Cockpit!$H$25*(Szenarien!W17-Szenarien!$AL$13) -> -210.50292 | Z17: =Cockpit!$Q$21-U17*(T17-$T$13)/12-(U17-$U$13)*$T$13/12 -> -275 | AA17: =Cockpit!$Q$22-V17*(T17-$T$13)/12-(V17-$V$13)*$T$13/12 -> -191.66667 | AB17: =X17+Y17+Z17+AA17 -> -36.794583 | AC17: =Cockpit!$Q$29 -> -156 | AD17: =Cockpit!$Q$31-Cockpit!$H$20*Cockpit!$H$21*(1+Cockpit!$D$22)*(R17-$R13)/12 -> -102.84375 | AE17: =(X17+Z17+AC17+AD17)*Cockpit!$Q$33 -> 42.6125 | AF17: =AB17-AE17 -> -79.407083
C20: Sprünge | V20: Sprünge | AM20: Sprünge
B21: Kaufpreis | C21: 0.05 | D21: Darlehen I Summe | E21: Darlehen I Zinssatz | F21: Darlehen I Tilgung | G21: Kaltmiete | H21: Bruttokaltmiete | I21: Bewirtschaftungskosten | J21: Zinsen | K21: Tilgung | L21: CF operativ | M21: Hausgeld und weitere Kosten | N21: AfA | O21: Steuern | P21: Cashflow nach Steuern (Monat) | R21: Kaufpreis | S21: Darlehen I % Kaufpreis | T21: Darlehen I Summe | U21: Darlehen I Zinssatz | V21: 0.005 | W21: Kaltmiete | X21: Bruttokaltmiete | Y21: Bewirtschaftungskosten | Z21: Zinsen | AA21: Tilgung | AB21: CF operativ | AC21: Hausgeld und weitere Kosten | AD21: AfA | AE21: Steuern | AF21: Cashflow nach Steuern (Monat) | AH21: Kaufpreis | AI21: Darlehen I % Kaufpreis | AJ21: Darlehen I Summe | AK21: Darlehen I Zinssatz | AL21: Darlehen I Tilgung | AM21: 20 | AN21: Bruttokaltmiete | AO21: Bewirtschaftungskosten | AP21: Zinsen | AQ21: Tilgung | AR21: CF operativ | AS21: Hausgeld und weitere Kosten | AT21: AfA | AU21: Steuern | AV21: Cashflow nach Steuern (Monat)
C22: % Kaufpreis | V22: Tilgung | AM22: Kaltmiete
B23: =$AL$9 -> 125000 | C23: =C24+$C$21 -> 1 | D23: =C23*B23 -> 125000 | E23: =$AL$11 -> 0.037 | F23: =$AL$12 -> 0.023 | G23: =$AL$13 -> 529.375 | H23: =G23+Cockpit!$K$9 -> 640.375 | I23: =-Cockpit!$K$12-Cockpit!$H$25*(Szenarien!G23-Szenarien!$AL$13) -> -210.50292 | J23: =Cockpit!$Q$21-E23*(D23-$D27)/12 -> -385.41667 | K23: =Cockpit!$Q$22-F23*(D23-$D27)/12 -> -239.58333 | L23: =H23+I23+J23+K23 -> -195.12792 | M23: =Cockpit!$Q$29 -> -156 | N23: =Cockpit!$Q$31-Cockpit!$H$20*Cockpit!$H$21*(1+Cockpit!$D$22)*(B23-$B27)/12 -> -102.84375 | O23: =(H23+J23+M23+N23)*Cockpit!$Q$33 -> -1.5541667 | P23: =L23-O23 -> -193.57375 | R23: =$AL$9 -> 125000 | S23: =$AL$10 -> 0.8 | T23: =R23*S23 -> 100000 | U23: =$AL$11 -> 0.037 | V23: =V24+$V$21 -> 0.043 | W23: =$AL$13 -> 529.375 | X23: =W23+Cockpit!$K$9 -> 640.375 | Y23: =-Cockpit!$K$12-Cockpit!$H$25*(Szenarien!W23-Szenarien!$AL$13) -> -210.50292 | Z23: =Cockpit!$Q$21-U23*(T23-$T$13)/12-(U23-$U$13)*$T$13/12 -> -308.33333 | AA23: =Cockpit!$Q$22-V23*(T23-$T$13)/12-(V23-$V$13)*$T$13/12 -> -358.33333 | AB23: =X23+Y23+Z23+AA23 -> -236.79458 | AC23: =Cockpit!$Q$29 -> -156 | AD23: =Cockpit!$Q$31-Cockpit!$H$20*Cockpit!$H$21*(1+Cockpit!$D$22)*(R23-$R27)/12 -> -102.84375 | AE23: =(X23+Z23+AC23+AD23)*Cockpit!$Q$33 -> 29.279167 | AF23: =AB23-AE23 -> -266.07375 | AH23: =$AL$9 -> 125000 | AI23: =$AL$10 -> 0.8 | AJ23: =AH23*AI23 -> 100000 | AK23: =$AL$11 -> 0.037 | AL23: =$AL$12 -> 0.023 | AM23: =AM24+$AM$21 -> 609.375 | AN23: =AM23+Cockpit!$K$9 -> 720.375 | AO23: =-Cockpit!$K$12-Cockpit!$H$25*(Szenarien!AM23-Szenarien!$AL$13) -> -212.90292 | AP23: =Cockpit!$Q$21-AK23*(AJ23-$T$13)/12-(AK23-$U$13)*$T$13/12 -> -308.33333 | AQ23: =Cockpit!$Q$22-AL23*(AJ23-$T$13)/12-(AL23-$V$13)*$T$13/12 -> -191.66667 | AR23: =AN23+AO23+AP23+AQ23 -> 7.4720833 | AS23: =Cockpit!$Q$29 -> -156 | AT23: =Cockpit!$Q$31-Cockpit!$H$20*Cockpit!$H$21*(1+Cockpit!$D$22)*(AH23-$AH27)/12 -> -102.84375 | AU23: =(AN23+AP23+AS23+AT23)*Cockpit!$Q$33 -> 61.279167 | AV23: =AR23-AU23 -> -53.807083
B24: =$AL$9 -> 125000 | C24: =C25+$C$21 -> 0.95 | D24: =C24*B24 -> 118750 | E24: =$AL$11 -> 0.037 | F24: =$AL$12 -> 0.023 | G24: =$AL$13 -> 529.375 | H24: =G24+Cockpit!$K$9 -> 640.375 | I24: =-Cockpit!$K$12-Cockpit!$H$25*(Szenarien!G24-Szenarien!$AL$13) -> -210.50292 | J24: =Cockpit!$Q$21-E24*(D24-$D27)/12 -> -366.14583 | K24: =Cockpit!$Q$22-F24*(D24-$D27)/12 -> -227.60417 | L24: =H24+I24+J24+K24 -> -163.87792 | M24: =Cockpit!$Q$29 -> -156 | N24: =Cockpit!$Q$31-Cockpit!$H$20*Cockpit!$H$21*(1+Cockpit!$D$22)*(B24-$B27)/12 -> -102.84375 | O24: =(H24+J24+M24+N24)*Cockpit!$Q$33 -> 6.1541667 | P24: =L24-O24 -> -170.03208 | R24: =$AL$9 -> 125000 | S24: =$AL$10 -> 0.8 | T24: =R24*S24 -> 100000 | U24: =$AL$11 -> 0.037 | V24: =V25+$V$21 -> 0.038 | W24: =$AL$13 -> 529.375 | X24: =W24+Cockpit!$K$9 -> 640.375 | Y24: =-Cockpit!$K$12-Cockpit!$H$25*(Szenarien!W24-Szenarien!$AL$13) -> -210.50292 | Z24: =Cockpit!$Q$21-U24*(T24-$T$13)/12-(U24-$U$13)*$T$13/12 -> -308.33333 | AA24: =Cockpit!$Q$22-V24*(T24-$T$13)/12-(V24-$V$13)*$T$13/12 -> -316.66667 | AB24: =X24+Y24+Z24+AA24 -> -195.12792 | AC24: =Cockpit!$Q$29 -> -156 | AD24: =Cockpit!$Q$31-Cockpit!$H$20*Cockpit!$H$21*(1+Cockpit!$D$22)*(R24-$R27)/12 -> -102.84375 | AE24: =(X24+Z24+AC24+AD24)*Cockpit!$Q$33 -> 29.279167 | AF24: =AB24-AE24 -> -224.40708 | AH24: =$AL$9 -> 125000 | AI24: =$AL$10 -> 0.8 | AJ24: =AH24*AI24 -> 100000 | AK24: =$AL$11 -> 0.037 | AL24: =$AL$12 -> 0.023 | AM24: =AM25+$AM$21 -> 589.375 | AN24: =AM24+Cockpit!$K$9 -> 700.375 | AO24: =-Cockpit!$K$12-Cockpit!$H$25*(Szenarien!AM24-Szenarien!$AL$13) -> -212.30292 | AP24: =Cockpit!$Q$21-AK24*(AJ24-$T$13)/12-(AK24-$U$13)*$T$13/12 -> -308.33333 | AQ24: =Cockpit!$Q$22-AL24*(AJ24-$T$13)/12-(AL24-$V$13)*$T$13/12 -> -191.66667 | AR24: =AN24+AO24+AP24+AQ24 -> -11.927917 | AS24: =Cockpit!$Q$29 -> -156 | AT24: =Cockpit!$Q$31-Cockpit!$H$20*Cockpit!$H$21*(1+Cockpit!$D$22)*(AH24-$AH27)/12 -> -102.84375 | AU24: =(AN24+AP24+AS24+AT24)*Cockpit!$Q$33 -> 53.279167 | AV24: =AR24-AU24 -> -65.207083
B25: =$AL$9 -> 125000 | C25: =C26+$C$21 -> 0.9 | D25: =C25*B25 -> 112500 | E25: =$AL$11 -> 0.037 | F25: =$AL$12 -> 0.023 | G25: =$AL$13 -> 529.375 | H25: =G25+Cockpit!$K$9 -> 640.375 | I25: =-Cockpit!$K$12-Cockpit!$H$25*(Szenarien!G25-Szenarien!$AL$13) -> -210.50292 | J25: =Cockpit!$Q$21-E25*(D25-$D27)/12 -> -346.875 | K25: =Cockpit!$Q$22-F25*(D25-$D27)/12 -> -215.625 | L25: =H25+I25+J25+K25 -> -132.62792 | M25: =Cockpit!$Q$29 -> -156 | N25: =Cockpit!$Q$31-Cockpit!$H$20*Cockpit!$H$21*(1+Cockpit!$D$22)*(B25-$B27)/12 -> -102.84375 | O25: =(H25+J25+M25+N25)*Cockpit!$Q$33 -> 13.8625 | P25: =L25-O25 -> -146.49042 | R25: =$AL$9 -> 125000 | S25: =$AL$10 -> 0.8 | T25: =R25*S25 -> 100000 | U25: =$AL$11 -> 0.037 | V25: =V26+$V$21 -> 0.033 | W25: =$AL$13 -> 529.375 | X25: =W25+Cockpit!$K$9 -> 640.375 | Y25: =-Cockpit!$K$12-Cockpit!$H$25*(Szenarien!W25-Szenarien!$AL$13) -> -210.50292 | Z25: =Cockpit!$Q$21-U25*(T25-$T$13)/12-(U25-$U$13)*$T$13/12 -> -308.33333 | AA25: =Cockpit!$Q$22-V25*(T25-$T$13)/12-(V25-$V$13)*$T$13/12 -> -275 | AB25: =X25+Y25+Z25+AA25 -> -153.46125 | AC25: =Cockpit!$Q$29 -> -156 | AD25: =Cockpit!$Q$31-Cockpit!$H$20*Cockpit!$H$21*(1+Cockpit!$D$22)*(R25-$R27)/12 -> -102.84375 | AE25: =(X25+Z25+AC25+AD25)*Cockpit!$Q$33 -> 29.279167 | AF25: =AB25-AE25 -> -182.74042 | AH25: =$AL$9 -> 125000 | AI25: =$AL$10 -> 0.8 | AJ25: =AH25*AI25 -> 100000 | AK25: =$AL$11 -> 0.037 | AL25: =$AL$12 -> 0.023 | AM25: =AM26+$AM$21 -> 569.375 | AN25: =AM25+Cockpit!$K$9 -> 680.375 | AO25: =-Cockpit!$K$12-Cockpit!$H$25*(Szenarien!AM25-Szenarien!$AL$13) -> -211.70292 | AP25: =Cockpit!$Q$21-AK25*(AJ25-$T$13)/12-(AK25-$U$13)*$T$13/12 -> -308.33333 | AQ25: =Cockpit!$Q$22-AL25*(AJ25-$T$13)/12-(AL25-$V$13)*$T$13/12 -> -191.66667 | AR25: =AN25+AO25+AP25+AQ25 -> -31.327917 | AS25: =Cockpit!$Q$29 -> -156 | AT25: =Cockpit!$Q$31-Cockpit!$H$20*Cockpit!$H$21*(1+Cockpit!$D$22)*(AH25-$AH27)/12 -> -102.84375 | AU25: =(AN25+AP25+AS25+AT25)*Cockpit!$Q$33 -> 45.279167 | AV25: =AR25-AU25 -> -76.607083
B26: =$AL$9 -> 125000 | C26: =C27+$C$21 -> 0.85 | D26: =C26*B26 -> 106250 | E26: =$AL$11 -> 0.037 | F26: =$AL$12 -> 0.023 | G26: =$AL$13 -> 529.375 | H26: =G26+Cockpit!$K$9 -> 640.375 | I26: =-Cockpit!$K$12-Cockpit!$H$25*(Szenarien!G26-Szenarien!$AL$13) -> -210.50292 | J26: =Cockpit!$Q$21-E26*(D26-$D27)/12 -> -327.60417 | K26: =Cockpit!$Q$22-F26*(D26-$D27)/12 -> -203.64583 | L26: =H26+I26+J26+K26 -> -101.37792 | M26: =Cockpit!$Q$29 -> -156 | N26: =Cockpit!$Q$31-Cockpit!$H$20*Cockpit!$H$21*(1+Cockpit!$D$22)*(B26-$B27)/12 -> -102.84375 | O26: =(H26+J26+M26+N26)*Cockpit!$Q$33 -> 21.570833 | P26: =L26-O26 -> -122.94875 | R26: =$AL$9 -> 125000 | S26: =$AL$10 -> 0.8 | T26: =R26*S26 -> 100000 | U26: =$AL$11 -> 0.037 | V26: =V27+$V$21 -> 0.028 | W26: =$AL$13 -> 529.375 | X26: =W26+Cockpit!$K$9 -> 640.375 | Y26: =-Cockpit!$K$12-Cockpit!$H$25*(Szenarien!W26-Szenarien!$AL$13) -> -210.50292 | Z26: =Cockpit!$Q$21-U26*(T26-$T$13)/12-(U26-$U$13)*$T$13/12 -> -308.33333 | AA26: =Cockpit!$Q$22-V26*(T26-$T$13)/12-(V26-$V$13)*$T$13/12 -> -233.33333 | AB26: =X26+Y26+Z26+AA26 -> -111.79458 | AC26: =Cockpit!$Q$29 -> -156 | AD26: =Cockpit!$Q$31-Cockpit!$H$20*Cockpit!$H$21*(1+Cockpit!$D$22)*(R26-$R27)/12 -> -102.84375 | AE26: =(X26+Z26+AC26+AD26)*Cockpit!$Q$33 -> 29.279167 | AF26: =AB26-AE26 -> -141.07375 | AH26: =$AL$9 -> 125000 | AI26: =$AL$10 -> 0.8 | AJ26: =AH26*AI26 -> 100000 | AK26: =$AL$11 -> 0.037 | AL26: =$AL$12 -> 0.023 | AM26: =AM27+$AM$21 -> 549.375 | AN26: =AM26+Cockpit!$K$9 -> 660.375 | AO26: =-Cockpit!$K$12-Cockpit!$H$25*(Szenarien!AM26-Szenarien!$AL$13) -> -211.10292 | AP26: =Cockpit!$Q$21-AK26*(AJ26-$T$13)/12-(AK26-$U$13)*$T$13/12 -> -308.33333 | AQ26: =Cockpit!$Q$22-AL26*(AJ26-$T$13)/12-(AL26-$V$13)*$T$13/12 -> -191.66667 | AR26: =AN26+AO26+AP26+AQ26 -> -50.727917 | AS26: =Cockpit!$Q$29 -> -156 | AT26: =Cockpit!$Q$31-Cockpit!$H$20*Cockpit!$H$21*(1+Cockpit!$D$22)*(AH26-$AH27)/12 -> -102.84375 | AU26: =(AN26+AP26+AS26+AT26)*Cockpit!$Q$33 -> 37.279167 | AV26: =AR26-AU26 -> -88.007083
B27: =$AL$9 -> 125000 | C27: =$AL$10 -> 0.8 | D27: =C27*B27 -> 100000 | E27: =$AL$11 -> 0.037 | F27: =$AL$12 -> 0.023 | G27: =$AL$13 -> 529.375 | H27: =G27+Cockpit!$K$9 -> 640.375 | I27: =-Cockpit!$K$12-Cockpit!$H$25*(Szenarien!G27-Szenarien!$AL$13) -> -210.50292 | J27: =Cockpit!$Q$21-E27*(D27-$D27)/12 -> -308.33333 | K27: =Cockpit!$Q$22-F27*(D27-$D27)/12 -> -191.66667 | L27: =H27+I27+J27+K27 -> -70.127917 | M27: =Cockpit!$Q$29 -> -156 | N27: =Cockpit!$Q$31-Cockpit!$H$20*Cockpit!$H$21*(1+Cockpit!$D$22)*(B27-$B27)/12 -> -102.84375 | O27: =(H27+J27+M27+N27)*Cockpit!$Q$33 -> 29.279167 | P27: =L27-O27 -> -99.407083 | R27: =$AL$9 -> 125000 | S27: =$AL$10 -> 0.8 | T27: =R27*S27 -> 100000 | U27: =$AL$11 -> 0.037 | V27: =$AL$12 -> 0.023 | W27: =$AL$13 -> 529.375 | X27: =W27+Cockpit!$K$9 -> 640.375 | Y27: =-Cockpit!$K$12-Cockpit!$H$25*(Szenarien!W27-Szenarien!$AL$13) -> -210.50292 | Z27: =Cockpit!$Q$21-U27*(T27-$T$13)/12-(U27-$U$13)*$T$13/12 -> -308.33333 | AA27: =Cockpit!$Q$22-V27*(T27-$T$13)/12-(V27-$V$13)*$T$13/12 -> -191.66667 | AB27: =X27+Y27+Z27+AA27 -> -70.127917 | AC27: =Cockpit!$Q$29 -> -156 | AD27: =Cockpit!$Q$31-Cockpit!$H$20*Cockpit!$H$21*(1+Cockpit!$D$22)*(R27-$R27)/12 -> -102.84375 | AE27: =(X27+Z27+AC27+AD27)*Cockpit!$Q$33 -> 29.279167 | AF27: =AB27-AE27 -> -99.407083 | AH27: =$AL$9 -> 125000 | AI27: =$AL$10 -> 0.8 | AJ27: =AH27*AI27 -> 100000 | AK27: =$AL$11 -> 0.037 | AL27: =$AL$12 -> 0.023 | AM27: =$AL$13 -> 529.375 | AN27: =AM27+Cockpit!$K$9 -> 640.375 | AO27: =-Cockpit!$K$12-Cockpit!$H$25*(Szenarien!AM27-Szenarien!$AL$13) -> -210.50292 | AP27: =Cockpit!$Q$21-AK27*(AJ27-$T$13)/12-(AK27-$U$13)*$T$13/12 -> -308.33333 | AQ27: =Cockpit!$Q$22-AL27*(AJ27-$T$13)/12-(AL27-$V$13)*$T$13/12 -> -191.66667 | AR27: =AN27+AO27+AP27+AQ27 -> -70.127917 | AS27: =Cockpit!$Q$29 -> -156 | AT27: =Cockpit!$Q$31-Cockpit!$H$20*Cockpit!$H$21*(1+Cockpit!$D$22)*(AH27-$AH27)/12 -> -102.84375 | AU27: =(AN27+AP27+AS27+AT27)*Cockpit!$Q$33 -> 29.279167 | AV27: =AR27-AU27 -> -99.407083
B28: =$AL$9 -> 125000 | C28: =C27-$C$21 -> 0.75 | D28: =C28*B28 -> 93750 | E28: =$AL$11 -> 0.037 | F28: =$AL$12 -> 0.023 | G28: =$AL$13 -> 529.375 | H28: =G28+Cockpit!$K$9 -> 640.375 | I28: =-Cockpit!$K$12-Cockpit!$H$25*(Szenarien!G28-Szenarien!$AL$13) -> -210.50292 | J28: =Cockpit!$Q$21-E28*(D28-$D27)/12 -> -289.0625 | K28: =Cockpit!$Q$22-F28*(D28-$D27)/12 -> -179.6875 | L28: =H28+I28+J28+K28 -> -38.877917 | M28: =Cockpit!$Q$29 -> -156 | N28: =Cockpit!$Q$31-Cockpit!$H$20*Cockpit!$H$21*(1+Cockpit!$D$22)*(B28-$B27)/12 -> -102.84375 | O28: =(H28+J28+M28+N28)*Cockpit!$Q$33 -> 36.9875 | P28: =L28-O28 -> -75.865417 | R28: =$AL$9 -> 125000 | S28: =$AL$10 -> 0.8 | T28: =R28*S28 -> 100000 | U28: =$AL$11 -> 0.037 | V28: =V27-$V$21 -> 0.018 | W28: =$AL$13 -> 529.375 | X28: =W28+Cockpit!$K$9 -> 640.375 | Y28: =-Cockpit!$K$12-Cockpit!$H$25*(Szenarien!W28-Szenarien!$AL$13) -> -210.50292 | Z28: =Cockpit!$Q$21-U28*(T28-$T$13)/12-(U28-$U$13)*$T$13/12 -> -308.33333 | AA28: =Cockpit!$Q$22-V28*(T28-$T$13)/12-(V28-$V$13)*$T$13/12 -> -150 | AB28: =X28+Y28+Z28+AA28 -> -28.46125 | AC28: =Cockpit!$Q$29 -> -156 | AD28: =Cockpit!$Q$31-Cockpit!$H$20*Cockpit!$H$21*(1+Cockpit!$D$22)*(R28-$R27)/12 -> -102.84375 | AE28: =(X28+Z28+AC28+AD28)*Cockpit!$Q$33 -> 29.279167 | AF28: =AB28-AE28 -> -57.740417 | AH28: =$AL$9 -> 125000 | AI28: =$AL$10 -> 0.8 | AJ28: =AH28*AI28 -> 100000 | AK28: =$AL$11 -> 0.037 | AL28: =$AL$12 -> 0.023 | AM28: =AM27-$AM$21 -> 509.375 | AN28: =AM28+Cockpit!$K$9 -> 620.375 | AO28: =-Cockpit!$K$12-Cockpit!$H$25*(Szenarien!AM28-Szenarien!$AL$13) -> -209.90292 | AP28: =Cockpit!$Q$21-AK28*(AJ28-$T$13)/12-(AK28-$U$13)*$T$13/12 -> -308.33333 | AQ28: =Cockpit!$Q$22-AL28*(AJ28-$T$13)/12-(AL28-$V$13)*$T$13/12 -> -191.66667 | AR28: =AN28+AO28+AP28+AQ28 -> -89.527917 | AS28: =Cockpit!$Q$29 -> -156 | AT28: =Cockpit!$Q$31-Cockpit!$H$20*Cockpit!$H$21*(1+Cockpit!$D$22)*(AH28-$AH27)/12 -> -102.84375 | AU28: =(AN28+AP28+AS28+AT28)*Cockpit!$Q$33 -> 21.279167 | AV28: =AR28-AU28 -> -110.80708
B29: =$AL$9 -> 125000 | C29: =C28-$C$21 -> 0.7 | D29: =C29*B29 -> 87500 | E29: =$AL$11 -> 0.037 | F29: =$AL$12 -> 0.023 | G29: =$AL$13 -> 529.375 | H29: =G29+Cockpit!$K$9 -> 640.375 | I29: =-Cockpit!$K$12-Cockpit!$H$25*(Szenarien!G29-Szenarien!$AL$13) -> -210.50292 | J29: =Cockpit!$Q$21-E29*(D29-$D27)/12 -> -269.79167 | K29: =Cockpit!$Q$22-F29*(D29-$D27)/12 -> -167.70833 | L29: =H29+I29+J29+K29 -> -7.6279167 | M29: =Cockpit!$Q$29 -> -156 | N29: =Cockpit!$Q$31-Cockpit!$H$20*Cockpit!$H$21*(1+Cockpit!$D$22)*(B29-$B27)/12 -> -102.84375 | O29: =(H29+J29+M29+N29)*Cockpit!$Q$33 -> 44.695833 | P29: =L29-O29 -> -52.32375 | R29: =$AL$9 -> 125000 | S29: =$AL$10 -> 0.8 | T29: =R29*S29 -> 100000 | U29: =$AL$11 -> 0.037 | V29: =V28-$V$21 -> 0.013 | W29: =$AL$13 -> 529.375 | X29: =W29+Cockpit!$K$9 -> 640.375 | Y29: =-Cockpit!$K$12-Cockpit!$H$25*(Szenarien!W29-Szenarien!$AL$13) -> -210.50292 | Z29: =Cockpit!$Q$21-U29*(T29-$T$13)/12-(U29-$U$13)*$T$13/12 -> -308.33333 | AA29: =Cockpit!$Q$22-V29*(T29-$T$13)/12-(V29-$V$13)*$T$13/12 -> -108.33333 | AB29: =X29+Y29+Z29+AA29 -> 13.205417 | AC29: =Cockpit!$Q$29 -> -156 | AD29: =Cockpit!$Q$31-Cockpit!$H$20*Cockpit!$H$21*(1+Cockpit!$D$22)*(R29-$R27)/12 -> -102.84375 | AE29: =(X29+Z29+AC29+AD29)*Cockpit!$Q$33 -> 29.279167 | AF29: =AB29-AE29 -> -16.07375 | AH29: =$AL$9 -> 125000 | AI29: =$AL$10 -> 0.8 | AJ29: =AH29*AI29 -> 100000 | AK29: =$AL$11 -> 0.037 | AL29: =$AL$12 -> 0.023 | AM29: =AM28-$AM$21 -> 489.375 | AN29: =AM29+Cockpit!$K$9 -> 600.375 | AO29: =-Cockpit!$K$12-Cockpit!$H$25*(Szenarien!AM29-Szenarien!$AL$13) -> -209.30292 | AP29: =Cockpit!$Q$21-AK29*(AJ29-$T$13)/12-(AK29-$U$13)*$T$13/12 -> -308.33333 | AQ29: =Cockpit!$Q$22-AL29*(AJ29-$T$13)/12-(AL29-$V$13)*$T$13/12 -> -191.66667 | AR29: =AN29+AO29+AP29+AQ29 -> -108.92792 | AS29: =Cockpit!$Q$29 -> -156 | AT29: =Cockpit!$Q$31-Cockpit!$H$20*Cockpit!$H$21*(1+Cockpit!$D$22)*(AH29-$AH27)/12 -> -102.84375 | AU29: =(AN29+AP29+AS29+AT29)*Cockpit!$Q$33 -> 13.279167 | AV29: =AR29-AU29 -> -122.20708
B30: =$AL$9 -> 125000 | C30: =C29-$C$21 -> 0.65 | D30: =C30*B30 -> 81250 | E30: =$AL$11 -> 0.037 | F30: =$AL$12 -> 0.023 | G30: =$AL$13 -> 529.375 | H30: =G30+Cockpit!$K$9 -> 640.375 | I30: =-Cockpit!$K$12-Cockpit!$H$25*(Szenarien!G30-Szenarien!$AL$13) -> -210.50292 | J30: =Cockpit!$Q$21-E30*(D30-$D27)/12 -> -250.52083 | K30: =Cockpit!$Q$22-F30*(D30-$D27)/12 -> -155.72917 | L30: =H30+I30+J30+K30 -> 23.622083 | M30: =Cockpit!$Q$29 -> -156 | N30: =Cockpit!$Q$31-Cockpit!$H$20*Cockpit!$H$21*(1+Cockpit!$D$22)*(B30-$B27)/12 -> -102.84375 | O30: =(H30+J30+M30+N30)*Cockpit!$Q$33 -> 52.404167 | P30: =L30-O30 -> -28.782083 | R30: =$AL$9 -> 125000 | S30: =$AL$10 -> 0.8 | T30: =R30*S30 -> 100000 | U30: =$AL$11 -> 0.037 | V30: =V29-$V$21 -> 0.008 | W30: =$AL$13 -> 529.375 | X30: =W30+Cockpit!$K$9 -> 640.375 | Y30: =-Cockpit!$K$12-Cockpit!$H$25*(Szenarien!W30-Szenarien!$AL$13) -> -210.50292 | Z30: =Cockpit!$Q$21-U30*(T30-$T$13)/12-(U30-$U$13)*$T$13/12 -> -308.33333 | AA30: =Cockpit!$Q$22-V30*(T30-$T$13)/12-(V30-$V$13)*$T$13/12 -> -66.666667 | AB30: =X30+Y30+Z30+AA30 -> 54.872083 | AC30: =Cockpit!$Q$29 -> -156 | AD30: =Cockpit!$Q$31-Cockpit!$H$20*Cockpit!$H$21*(1+Cockpit!$D$22)*(R30-$R27)/12 -> -102.84375 | AE30: =(X30+Z30+AC30+AD30)*Cockpit!$Q$33 -> 29.279167 | AF30: =AB30-AE30 -> 25.592917 | AH30: =$AL$9 -> 125000 | AI30: =$AL$10 -> 0.8 | AJ30: =AH30*AI30 -> 100000 | AK30: =$AL$11 -> 0.037 | AL30: =$AL$12 -> 0.023 | AM30: =AM29-$AM$21 -> 469.375 | AN30: =AM30+Cockpit!$K$9 -> 580.375 | AO30: =-Cockpit!$K$12-Cockpit!$H$25*(Szenarien!AM30-Szenarien!$AL$13) -> -208.70292 | AP30: =Cockpit!$Q$21-AK30*(AJ30-$T$13)/12-(AK30-$U$13)*$T$13/12 -> -308.33333 | AQ30: =Cockpit!$Q$22-AL30*(AJ30-$T$13)/12-(AL30-$V$13)*$T$13/12 -> -191.66667 | AR30: =AN30+AO30+AP30+AQ30 -> -128.32792 | AS30: =Cockpit!$Q$29 -> -156 | AT30: =Cockpit!$Q$31-Cockpit!$H$20*Cockpit!$H$21*(1+Cockpit!$D$22)*(AH30-$AH27)/12 -> -102.84375 | AU30: =(AN30+AP30+AS30+AT30)*Cockpit!$Q$33 -> 5.2791667 | AV30: =AR30-AU30 -> -133.60708
B31: =$AL$9 -> 125000 | C31: =C30-$C$21 -> 0.6 | D31: =C31*B31 -> 75000 | E31: =$AL$11 -> 0.037 | F31: =$AL$12 -> 0.023 | G31: =$AL$13 -> 529.375 | H31: =G31+Cockpit!$K$9 -> 640.375 | I31: =-Cockpit!$K$12-Cockpit!$H$25*(Szenarien!G31-Szenarien!$AL$13) -> -210.50292 | J31: =Cockpit!$Q$21-E31*(D31-$D27)/12 -> -231.25 | K31: =Cockpit!$Q$22-F31*(D31-$D27)/12 -> -143.75 | L31: =H31+I31+J31+K31 -> 54.872083 | M31: =Cockpit!$Q$29 -> -156 | N31: =Cockpit!$Q$31-Cockpit!$H$20*Cockpit!$H$21*(1+Cockpit!$D$22)*(B31-$B27)/12 -> -102.84375 | O31: =(H31+J31+M31+N31)*Cockpit!$Q$33 -> 60.1125 | P31: =L31-O31 -> -5.2404167 | R31: =$AL$9 -> 125000 | S31: =$AL$10 -> 0.8 | T31: =R31*S31 -> 100000 | U31: =$AL$11 -> 0.037 | V31: =V30-$V$21 -> 0.003 | W31: =$AL$13 -> 529.375 | X31: =W31+Cockpit!$K$9 -> 640.375 | Y31: =-Cockpit!$K$12-Cockpit!$H$25*(Szenarien!W31-Szenarien!$AL$13) -> -210.50292 | Z31: =Cockpit!$Q$21-U31*(T31-$T$13)/12-(U31-$U$13)*$T$13/12 -> -308.33333 | AA31: =Cockpit!$Q$22-V31*(T31-$T$13)/12-(V31-$V$13)*$T$13/12 -> -25 | AB31: =X31+Y31+Z31+AA31 -> 96.53875 | AC31: =Cockpit!$Q$29 -> -156 | AD31: =Cockpit!$Q$31-Cockpit!$H$20*Cockpit!$H$21*(1+Cockpit!$D$22)*(R31-$R27)/12 -> -102.84375 | AE31: =(X31+Z31+AC31+AD31)*Cockpit!$Q$33 -> 29.279167 | AF31: =AB31-AE31 -> 67.259583 | AH31: =$AL$9 -> 125000 | AI31: =$AL$10 -> 0.8 | AJ31: =AH31*AI31 -> 100000 | AK31: =$AL$11 -> 0.037 | AL31: =$AL$12 -> 0.023 | AM31: =AM30-$AM$21 -> 449.375 | AN31: =AM31+Cockpit!$K$9 -> 560.375 | AO31: =-Cockpit!$K$12-Cockpit!$H$25*(Szenarien!AM31-Szenarien!$AL$13) -> -208.10292 | AP31: =Cockpit!$Q$21-AK31*(AJ31-$T$13)/12-(AK31-$U$13)*$T$13/12 -> -308.33333 | AQ31: =Cockpit!$Q$22-AL31*(AJ31-$T$13)/12-(AL31-$V$13)*$T$13/12 -> -191.66667 | AR31: =AN31+AO31+AP31+AQ31 -> -147.72792 | AS31: =Cockpit!$Q$29 -> -156 | AT31: =Cockpit!$Q$31-Cockpit!$H$20*Cockpit!$H$21*(1+Cockpit!$D$22)*(AH31-$AH27)/12 -> -102.84375 | AU31: =(AN31+AP31+AS31+AT31)*Cockpit!$Q$33 -> -2.7208333 | AV31: =AR31-AU31 -> -145.00708
B33: Keine Gewähr für die Richtigkeit der Angaben. Dieses Tool ersetzt keine fundierte Rechts-, Steuer- oder Finanzberatung. Mehr Details hier.

Sheet Diagramme
B1: zurück zum Cockpit | E1: Diagramme
B6: =Cockpit!C9 -> Rapfstraße 3/1, Hollabrunn
M9: Einnahmen | N9: Ausgaben
C10: Kaufpreis | D10: =Cockpit!D14 -> 125000 | H10: Hauptdarlehen | I10: =IF((Cockpit!N17)=0,#N/A,Cockpit!N17) -> 100000 | L10: Bruttokaltmiete | M10: =Cockpit!Q19 -> 640.375
C11: Nebenkosten | D11: =IF(Cockpit!E22=0,#N/A,Cockpit!E22) -> 13325 | H11: Weitere Darlehen | I11: =IF((Cockpit!N9-Cockpit!N17)=0,#N/A,Cockpit!N9-Cockpit!N17) -> #N/A | L11: Bewirtschaftungskosten | N11: =-Cockpit!Q20 -> 210.50292
C12: Anfängl. Invest. | D12: =IF(Cockpit!C30=0,#N/A,Cockpit!C30) -> #N/A | H12: Eigenkapital | I12: =Cockpit!N10 -> 38325 | L12: Zinsen | N12: =-Cockpit!Q21 -> 308.33333
L13: Tilgung | N13: =-Cockpit!Q22 -> 191.66667
L14: Steuern | N14: =-Cockpit!Q24 -> 29.279167
B107: Keine Gewähr für die Richtigkeit der Angaben. Dieses Tool ersetzt keine fundierte Rechts-, Steuer- oder Finanzberatung. Mehr Details hier.

Sheet MFH-Kalkulator
B1: zurück zum Cockpit | F1: Mehrfamilienhaus-Kalkulator
B6: Mieten von diesem Blatt verwenden | C6: Aus | E6: =IF(C6="Aus","Achtung: Die Mieten von diesem Tabellenblatt werden derzeit nicht im Rest des Tools berücksichtigt. Hierzu bitte links auf 'Ein' schalten.","") -> Achtung: Die Mieten von diesem Tabellenblatt werden derzeit nicht im Rest des Tools berücksichtigt. Hierzu bitte links auf 'Ein' schalten.
B8: Summe aller Einheiten | E8: =IF(ROUND(C9,0)<>ROUND(Cockpit!C11,0),"Achtung: Wohnfläche der Einheiten entspricht nicht der Gesamt-Wohnfläche des Hauses (Reiter 'Cockpit')","") -> Achtung: Wohnfläche der Einheiten entspricht nicht der Gesamt-Wohnfläche des Hauses (Reiter 'Cockpit')
B9: Wohnfläche | C9: =C16+C23+C30+C37+C44+C51+C58+C65+C72+C79+C86+C93+C100+C107+C114+C121+C128+C135+C142+C149+C156+C163+C170+C177+C184+C191+C198+C205+C212+C219 -> 100 | E9: ='Wert, AfA, Darlehen'!D7 -> 2024 | F9: ='Wert, AfA, Darlehen'!E7 -> 2025 | G9: ='Wert, AfA, Darlehen'!F7 -> 2026 | H9: ='Wert, AfA, Darlehen'!G7 -> 2027 | I9: ='Wert, AfA, Darlehen'!H7 -> 2028 | J9: ='Wert, AfA, Darlehen'!I7 -> 2029 | K9: ='Wert, AfA, Darlehen'!J7 -> 2030 | L9: ='Wert, AfA, Darlehen'!K7 -> 2031 | ... BB9: ='Wert, AfA, Darlehen'!BA7 -> 2073
B10: Nettokaltmiete vor Erhöhung | E10: =E17+E24+E31+E38+E45+E52+E59+E66+E73+E80+E87+E94+E101+E108+E115+E122+E129+E136+E143+E150+E157+E164+E171+E178+E185+E192+E199+E206+E213+E220 -> 1250 | F10: =F17+F24+F31+F38+F45+F52+F59+F66+F73+F80+F87+F94+F101+F108+F115+F122+F129+F136+F143+F150+F157+F164+F171+F178+F185+F192+F199+F206+F213+F220 -> 1287.5 | G10: =G17+G24+G31+G38+G45+G52+G59+G66+G73+G80+G87+G94+G101+G108+G115+G122+G129+G136+G143+G150+G157+G164+G171+G178+G185+G192+G199+G206+G213+G220 -> 1326.125 | H10: =H17+H24+H31+H38+H45+H52+H59+H66+H73+H80+H87+H94+H101+H108+H115+H122+H129+H136+H143+H150+H157+H164+H171+H178+H185+H192+H199+H206+H213+H220 -> 1365.9088 | I10: =I17+I24+I31+I38+I45+I52+I59+I66+I73+I80+I87+I94+I101+I108+I115+I122+I129+I136+I143+I150+I157+I164+I171+I178+I185+I192+I199+I206+I213+I220 -> 1406.886 | J10: =J17+J24+J31+J38+J45+J52+J59+J66+J73+J80+J87+J94+J101+J108+J115+J122+J129+J136+J143+J150+J157+J164+J171+J178+J185+J192+J199+J206+J213+J220 -> 1449.0926 | K10: =K17+K24+K31+K38+K45+K52+K59+K66+K73+K80+K87+K94+K101+K108+K115+K122+K129+K136+K143+K150+K157+K164+K171+K178+K185+K192+K199+K206+K213+K220 -> 1492.5654 | L10: =L17+L24+L31+L38+L45+L52+L59+L66+L73+L80+L87+L94+L101+L108+L115+L122+L129+L136+L143+L150+L157+L164+L171+L178+L185+L192+L199+L206+L213+L220 -> 1537.3423 | ... BB10: =BB17+BB24+BB31+BB38+BB45+BB52+BB59+BB66+BB73+BB80+BB87+BB94+BB101+BB108+BB115+BB122+BB129+BB136+BB143+BB150+BB157+BB164+BB171+BB178+BB185+BB192+BB199+BB206+BB213+BB220 -> 5320.2743
B11: + geplante Mieterhöhung | E11: =E12/E10-1 -> 0.03 | F11: =F12/F10-1 -> 0.03 | G11: =G12/G10-1 -> 0.03 | H11: =H12/H10-1 -> 0.03 | I11: =I12/I10-1 -> 0.03 | J11: =J12/J10-1 -> 0.03 | K11: =K12/K10-1 -> 0.03 | L11: =L12/L10-1 -> 0.03 | ... BB11: =BB12/BB10-1 -> 0.03
B12: = Nettokaltmiete | E12: =E19+E26+E33+E40+E47+E54+E61+E68+E75+E82+E89+E96+E103+E110+E117+E124+E131+E138+E145+E152+E159+E166+E173+E180+E187+E194+E201+E208+E215+E222 -> 1287.5 | F12: =F19+F26+F33+F40+F47+F54+F61+F68+F75+F82+F89+F96+F103+F110+F117+F124+F131+F138+F145+F152+F159+F166+F173+F180+F187+F194+F201+F208+F215+F222 -> 1326.125 | G12: =G19+G26+G33+G40+G47+G54+G61+G68+G75+G82+G89+G96+G103+G110+G117+G124+G131+G138+G145+G152+G159+G166+G173+G180+G187+G194+G201+G208+G215+G222 -> 1365.9088 | H12: =H19+H26+H33+H40+H47+H54+H61+H68+H75+H82+H89+H96+H103+H110+H117+H124+H131+H138+H145+H152+H159+H166+H173+H180+H187+H194+H201+H208+H215+H222 -> 1406.886 | I12: =I19+I26+I33+I40+I47+I54+I61+I68+I75+I82+I89+I96+I103+I110+I117+I124+I131+I138+I145+I152+I159+I166+I173+I180+I187+I194+I201+I208+I215+I222 -> 1449.0926 | J12: =J19+J26+J33+J40+J47+J54+J61+J68+J75+J82+J89+J96+J103+J110+J117+J124+J131+J138+J145+J152+J159+J166+J173+J180+J187+J194+J201+J208+J215+J222 -> 1492.5654 | K12: =K19+K26+K33+K40+K47+K54+K61+K68+K75+K82+K89+K96+K103+K110+K117+K124+K131+K138+K145+K152+K159+K166+K173+K180+K187+K194+K201+K208+K215+K222 -> 1537.3423 | L12: =L19+L26+L33+L40+L47+L54+L61+L68+L75+L82+L89+L96+L103+L110+L117+L124+L131+L138+L145+L152+L159+L166+L173+L180+L187+L194+L201+L208+L215+L222 -> 1583.4626 | ... BB12: =BB19+BB26+BB33+BB40+BB47+BB54+BB61+BB68+BB75+BB82+BB89+BB96+BB103+BB110+BB117+BB124+BB131+BB138+BB145+BB152+BB159+BB166+BB173+BB180+BB187+BB194+BB201+BB208+BB215+BB222 -> 5479.8825
B13: = pro m² Wohnfläche | E13: =E12/$C9 -> 12.875 | F13: =F12/$C9 -> 13.26125 | G13: =G12/$C9 -> 13.659088 | H13: =H12/$C9 -> 14.06886 | I13: =I12/$C9 -> 14.490926 | J13: =J12/$C9 -> 14.925654 | K13: =K12/$C9 -> 15.373423 | L13: =L12/$C9 -> 15.834626 | ... BB13: =BB12/$C9 -> 54.798825
B15: Einheit 1: EG vo. li. / Meyer
B16: Wohnfläche | C16: 40 | E16: =E$9 -> 2024 | F16: =F$9 -> 2025 | G16: =G$9 -> 2026 | H16: =H$9 -> 2027 | I16: =I$9 -> 2028 | J16: =J$9 -> 2029 | K16: =K$9 -> 2030 | L16: =L$9 -> 2031 | ... BB16: =BB$9 -> 2073
B17: Nettokaltmiete vor Erhöhung | E17: 300 | F17: =E19 -> 309 | G17: =F19 -> 318.27 | H17: =G19 -> 327.8181 | I17: =H19 -> 337.65264 | J17: =I19 -> 347.78222 | K17: =J19 -> 358.21569 | L17: =K19 -> 368.96216 | M17: =L19 -> 380.03102 | ... BB17: =BA19 -> 1276.8658
B18: + geplante Mieterhöhung | E18: =Cockpit!$H$31 -> 0.03 | F18: =Cockpit!$H$31 -> 0.03 | G18: =Cockpit!$H$31 -> 0.03 | H18: =Cockpit!$H$31 -> 0.03 | I18: =Cockpit!$H$31 -> 0.03 | J18: =Cockpit!$H$31 -> 0.03 | K18: =Cockpit!$H$31 -> 0.03 | L18: =Cockpit!$H$31 -> 0.03 | ... BB18: =Cockpit!$H$31 -> 0.03
B19: = Nettokaltmiete | E19: =E17*(1+E18) -> 309 | F19: =F17*(1+F18) -> 318.27 | G19: =G17*(1+G18) -> 327.8181 | H19: =H17*(1+H18) -> 337.65264 | I19: =I17*(1+I18) -> 347.78222 | J19: =J17*(1+J18) -> 358.21569 | K19: =K17*(1+K18) -> 368.96216 | L19: =L17*(1+L18) -> 380.03102 | ... BB19: =BB17*(1+BB18) -> 1315.1718
B20: = pro m² Wohnfläche | E20: =E19/$C16 -> 7.725 | F20: =F19/$C16 -> 7.95675 | G20: =G19/$C16 -> 8.1954525 | H20: =H19/$C16 -> 8.4413161 | I20: =I19/$C16 -> 8.6945556 | J20: =J19/$C16 -> 8.9553922 | K20: =K19/$C16 -> 9.224054 | L20: =L19/$C16 -> 9.5007756 | ... BB20: =BB19/$C16 -> 32.879295
B22: Einheit 2: EG hi. li. / Müller
B23: Wohnfläche | C23: 20 | D23: 25 | E23: =E$9 -> 2024 | F23: =F$9 -> 2025 | G23: =G$9 -> 2026 | H23: =H$9 -> 2027 | I23: =I$9 -> 2028 | J23: =J$9 -> 2029 | K23: =K$9 -> 2030 | L23: =L$9 -> 2031 | ... BB23: =BB$9 -> 2073
B24: Nettokaltmiete vor Erhöhung | E24: 350 | F24: =E26 -> 360.5 | G24: =F26 -> 371.315 | H24: =G26 -> 382.45445 | I24: =H26 -> 393.92808 | J24: =I26 -> 405.74593 | K24: =J26 -> 417.9183 | L24: =K26 -> 430.45585 | M24: =L26 -> 443.36953 | ... BB24: =BA26 -> 1489.6768
B25: + geplante Mieterhöhung | E25: =Cockpit!$H$31 -> 0.03 | F25: =Cockpit!$H$31 -> 0.03 | G25: =Cockpit!$H$31 -> 0.03 | H25: =Cockpit!$H$31 -> 0.03 | I25: =Cockpit!$H$31 -> 0.03 | J25: =Cockpit!$H$31 -> 0.03 | K25: =Cockpit!$H$31 -> 0.03 | L25: =Cockpit!$H$31 -> 0.03 | ... BB25: =Cockpit!$H$31 -> 0.03
B26: = Nettokaltmiete | E26: =E24*(1+E25) -> 360.5 | F26: =F24*(1+F25) -> 371.315 | G26: =G24*(1+G25) -> 382.45445 | H26: =H24*(1+H25) -> 393.92808 | I26: =I24*(1+I25) -> 405.74593 | J26: =J24*(1+J25) -> 417.9183 | K26: =K24*(1+K25) -> 430.45585 | L26: =L24*(1+L25) -> 443.36953 | ... BB26: =BB24*(1+BB25) -> 1534.3671
B27: = pro m² Wohnfläche | E27: =E26/$C23 -> 18.025 | F27: =F26/$C23 -> 18.56575 | G27: =G26/$C23 -> 19.122723 | H27: =H26/$C23 -> 19.696404 | I27: =I26/$C23 -> 20.287296 | J27: =J26/$C23 -> 20.895915 | K27: =K26/$C23 -> 21.522793 | L27: =L26/$C23 -> 22.168476 | ... BB27: =BB26/$C23 -> 76.718355
B29: Einheit 3: EG vo. re. / Schulze
B30: Wohnfläche | C30: 20 | E30: =E$9 -> 2024 | F30: =F$9 -> 2025 | G30: =G$9 -> 2026 | H30: =H$9 -> 2027 | I30: =I$9 -> 2028 | J30: =J$9 -> 2029 | K30: =K$9 -> 2030 | L30: =L$9 -> 2031 | ... BB30: =BB$9 -> 2073
B31: Nettokaltmiete vor Erhöhung | E31: 300 | F31: =E33 -> 309 | G31: =F33 -> 318.27 | H31: =G33 -> 327.8181 | I31: =H33 -> 337.65264 | J31: =I33 -> 347.78222 | K31: =J33 -> 358.21569 | L31: =K33 -> 368.96216 | M31: =L33 -> 380.03102 | ... BB31: =BA33 -> 1276.8658
B32: + geplante Mieterhöhung | E32: =Cockpit!$H$31 -> 0.03 | F32: =Cockpit!$H$31 -> 0.03 | G32: =Cockpit!$H$31 -> 0.03 | H32: =Cockpit!$H$31 -> 0.03 | I32: =Cockpit!$H$31 -> 0.03 | J32: =Cockpit!$H$31 -> 0.03 | K32: =Cockpit!$H$31 -> 0.03 | L32: =Cockpit!$H$31 -> 0.03 | ... BB32: =Cockpit!$H$31 -> 0.03
B33: = Nettokaltmiete | E33: =E31*(1+E32) -> 309 | F33: =F31*(1+F32) -> 318.27 | G33: =G31*(1+G32) -> 327.8181 | H33: =H31*(1+H32) -> 337.65264 | I33: =I31*(1+I32) -> 347.78222 | J33: =J31*(1+J32) -> 358.21569 | K33: =K31*(1+K32) -> 368.96216 | L33: =L31*(1+L32) -> 380.03102 | ... BB33: =BB31*(1+BB32) -> 1315.1718
B34: = pro m² Wohnfläche | E34: =E33/$C30 -> 15.45 | F34: =F33/$C30 -> 15.9135 | G34: =G33/$C30 -> 16.390905 | H34: =H33/$C30 -> 16.882632 | I34: =I33/$C30 -> 17.389111 | J34: =J33/$C30 -> 17.910784 | K34: =K33/$C30 -> 18.448108 | L34: =L33/$C30 -> 19.001551 | ... BB34: =BB33/$C30 -> 65.75859
B36: Einheit 4: EG vor. li. / Mustermann
B37: Wohnfläche | C37: 20 | E37: =E$9 -> 2024 | F37: =F$9 -> 2025 | G37: =G$9 -> 2026 | H37: =H$9 -> 2027 | I37: =I$9 -> 2028 | J37: =J$9 -> 2029 | K37: =K$9 -> 2030 | L37: =L$9 -> 2031 | ... BB37: =BB$9 -> 2073
B38: Nettokaltmiete vor Erhöhung | E38: 300 | F38: =E40 -> 309 | G38: =F40 -> 318.27 | H38: =G40 -> 327.8181 | I38: =H40 -> 337.65264 | J38: =I40 -> 347.78222 | K38: =J40 -> 358.21569 | L38: =K40 -> 368.96216 | M38: =L40 -> 380.03102 | ... BB38: =BA40 -> 1276.8658
B39: + geplante Mieterhöhung | E39: =Cockpit!$H$31 -> 0.03 | F39: =Cockpit!$H$31 -> 0.03 | G39: =Cockpit!$H$31 -> 0.03 | H39: =Cockpit!$H$31 -> 0.03 | I39: =Cockpit!$H$31 -> 0.03 | J39: =Cockpit!$H$31 -> 0.03 | K39: =Cockpit!$H$31 -> 0.03 | L39: =Cockpit!$H$31 -> 0.03 | ... BB39: =Cockpit!$H$31 -> 0.03
B40: = Nettokaltmiete | E40: =E38*(1+E39) -> 309 | F40: =F38*(1+F39) -> 318.27 | G40: =G38*(1+G39) -> 327.8181 | H40: =H38*(1+H39) -> 337.65264 | I40: =I38*(1+I39) -> 347.78222 | J40: =J38*(1+J39) -> 358.21569 | K40: =K38*(1+K39) -> 368.96216 | L40: =L38*(1+L39) -> 380.03102 | ... BB40: =BB38*(1+BB39) -> 1315.1718
B41: = pro m² Wohnfläche | E41: =E40/$C37 -> 15.45 | F41: =F40/$C37 -> 15.9135 | G41: =G40/$C37 -> 16.390905 | H41: =H40/$C37 -> 16.882632 | I41: =I40/$C37 -> 17.389111 | J41: =J40/$C37 -> 17.910784 | K41: =K40/$C37 -> 18.448108 | L41: =L40/$C37 -> 19.001551 | ... BB41: =BB40/$C37 -> 65.75859
B43: Einheit 5:
B44: Wohnfläche | C44: 0 | E44: =E$9 -> 2024 | F44: =F$9 -> 2025 | G44: =G$9 -> 2026 | H44: =H$9 -> 2027 | I44: =I$9 -> 2028 | J44: =J$9 -> 2029 | K44: =K$9 -> 2030 | L44: =L$9 -> 2031 | ... BB44: =BB$9 -> 2073
B45: Nettokaltmiete vor Erhöhung | E45: 0 | F45: =E47 -> 0 | G45: =F47 -> 0 | H45: =G47 -> 0 | I45: =H47 -> 0 | J45: =I47 -> 0 | K45: =J47 -> 0 | L45: =K47 -> 0 | M45: =L47 -> 0 | ... BB45: =BA47 -> 0
B46: + geplante Mieterhöhung | E46: =Cockpit!$H$31 -> 0.03 | F46: =Cockpit!$H$31 -> 0.03 | G46: =Cockpit!$H$31 -> 0.03 | H46: =Cockpit!$H$31 -> 0.03 | I46: =Cockpit!$H$31 -> 0.03 | J46: =Cockpit!$H$31 -> 0.03 | K46: =Cockpit!$H$31 -> 0.03 | L46: =Cockpit!$H$31 -> 0.03 | ... BB46: =Cockpit!$H$31 -> 0.03
B47: = Nettokaltmiete | E47: =E45*(1+E46) -> 0 | F47: =F45*(1+F46) -> 0 | G47: =G45*(1+G46) -> 0 | H47: =H45*(1+H46) -> 0 | I47: =I45*(1+I46) -> 0 | J47: =J45*(1+J46) -> 0 | K47: =K45*(1+K46) -> 0 | L47: =L45*(1+L46) -> 0 | ... BB47: =BB45*(1+BB46) -> 0
B48: = pro m² Wohnfläche | E48: =IFERROR(E47/$C44,"-") -> - | F48: =IFERROR(F47/$C44,"-") -> - | G48: =IFERROR(G47/$C44,"-") -> - | H48: =IFERROR(H47/$C44,"-") -> - | I48: =IFERROR(I47/$C44,"-") -> - | J48: =IFERROR(J47/$C44,"-") -> - | K48: =IFERROR(K47/$C44,"-") -> - | L48: =IFERROR(L47/$C44,"-") -> - | ... BB48: =IFERROR(BB47/$C44,"-") -> -
B50: Einheit 6:
B51: Wohnfläche | C51: 0 | E51: =E$9 -> 2024 | F51: =F$9 -> 2025 | G51: =G$9 -> 2026 | H51: =H$9 -> 2027 | I51: =I$9 -> 2028 | J51: =J$9 -> 2029 | K51: =K$9 -> 2030 | L51: =L$9 -> 2031 | ... BB51: =BB$9 -> 2073
B52: Nettokaltmiete vor Erhöhung | E52: 0 | F52: =E54 -> 0 | G52: =F54 -> 0 | H52: =G54 -> 0 | I52: =H54 -> 0 | J52: =I54 -> 0 | K52: =J54 -> 0 | L52: =K54 -> 0 | M52: =L54 -> 0 | ... BB52: =BA54 -> 0
B53: + geplante Mieterhöhung | E53: =Cockpit!$H$31 -> 0.03 | F53: =Cockpit!$H$31 -> 0.03 | G53: =Cockpit!$H$31 -> 0.03 | H53: =Cockpit!$H$31 -> 0.03 | I53: =Cockpit!$H$31 -> 0.03 | J53: =Cockpit!$H$31 -> 0.03 | K53: =Cockpit!$H$31 -> 0.03 | L53: =Cockpit!$H$31 -> 0.03 | ... BB53: =Cockpit!$H$31 -> 0.03
B54: = Nettokaltmiete | E54: =E52*(1+E53) -> 0 | F54: =F52*(1+F53) -> 0 | G54: =G52*(1+G53) -> 0 | H54: =H52*(1+H53) -> 0 | I54: =I52*(1+I53) -> 0 | J54: =J52*(1+J53) -> 0 | K54: =K52*(1+K53) -> 0 | L54: =L52*(1+L53) -> 0 | ... BB54: =BB52*(1+BB53) -> 0
B55: = pro m² Wohnfläche | E55: =IFERROR(E54/$C51,"-") -> - | F55: =IFERROR(F54/$C51,"-") -> - | G55: =IFERROR(G54/$C51,"-") -> - | H55: =IFERROR(H54/$C51,"-") -> - | I55: =IFERROR(I54/$C51,"-") -> - | J55: =IFERROR(J54/$C51,"-") -> - | K55: =IFERROR(K54/$C51,"-") -> - | L55: =IFERROR(L54/$C51,"-") -> - | ... BB55: =IFERROR(BB54/$C51,"-") -> -
B57: Einheit 7:
B58: Wohnfläche | C58: 0 | E58: =E$9 -> 2024 | F58: =F$9 -> 2025 | G58: =G$9 -> 2026 | H58: =H$9 -> 2027 | I58: =I$9 -> 2028 | J58: =J$9 -> 2029 | K58: =K$9 -> 2030 | L58: =L$9 -> 2031 | ... BB58: =BB$9 -> 2073
B59: Nettokaltmiete vor Erhöhung | E59: 0 | F59: =E61 -> 0 | G59: =F61 -> 0 | H59: =G61 -> 0 | I59: =H61 -> 0 | J59: =I61 -> 0 | K59: =J61 -> 0 | L59: =K61 -> 0 | M59: =L61 -> 0 | ... BB59: =BA61 -> 0
B60: + geplante Mieterhöhung | E60: =Cockpit!$H$31 -> 0.03 | F60: =Cockpit!$H$31 -> 0.03 | G60: =Cockpit!$H$31 -> 0.03 | H60: =Cockpit!$H$31 -> 0.03 | I60: =Cockpit!$H$31 -> 0.03 | J60: =Cockpit!$H$31 -> 0.03 | K60: =Cockpit!$H$31 -> 0.03 | L60: =Cockpit!$H$31 -> 0.03 | ... BB60: =Cockpit!$H$31 -> 0.03
B61: = Nettokaltmiete | E61: =E59*(1+E60) -> 0 | F61: =F59*(1+F60) -> 0 | G61: =G59*(1+G60) -> 0 | H61: =H59*(1+H60) -> 0 | I61: =I59*(1+I60) -> 0 | J61: =J59*(1+J60) -> 0 | K61: =K59*(1+K60) -> 0 | L61: =L59*(1+L60) -> 0 | ... BB61: =BB59*(1+BB60) -> 0
B62: = pro m² Wohnfläche | E62: =IFERROR(E61/$C58,"-") -> - | F62: =IFERROR(F61/$C58,"-") -> - | G62: =IFERROR(G61/$C58,"-") -> - | H62: =IFERROR(H61/$C58,"-") -> - | I62: =IFERROR(I61/$C58,"-") -> - | J62: =IFERROR(J61/$C58,"-") -> - | K62: =IFERROR(K61/$C58,"-") -> - | L62: =IFERROR(L61/$C58,"-") -> - | ... BB62: =IFERROR(BB61/$C58,"-") -> -
B64: Einheit 8:
B65: Wohnfläche | C65: 0 | E65: =E$9 -> 2024 | F65: =F$9 -> 2025 | G65: =G$9 -> 2026 | H65: =H$9 -> 2027 | I65: =I$9 -> 2028 | J65: =J$9 -> 2029 | K65: =K$9 -> 2030 | L65: =L$9 -> 2031 | ... BB65: =BB$9 -> 2073
B66: Nettokaltmiete vor Erhöhung | E66: 0 | F66: =E68 -> 0 | G66: =F68 -> 0 | H66: =G68 -> 0 | I66: =H68 -> 0 | J66: =I68 -> 0 | K66: =J68 -> 0 | L66: =K68 -> 0 | M66: =L68 -> 0 | ... BB66: =BA68 -> 0
B67: + geplante Mieterhöhung | E67: =Cockpit!$H$31 -> 0.03 | F67: =Cockpit!$H$31 -> 0.03 | G67: =Cockpit!$H$31 -> 0.03 | H67: =Cockpit!$H$31 -> 0.03 | I67: =Cockpit!$H$31 -> 0.03 | J67: =Cockpit!$H$31 -> 0.03 | K67: =Cockpit!$H$31 -> 0.03 | L67: =Cockpit!$H$31 -> 0.03 | ... BB67: =Cockpit!$H$31 -> 0.03
B68: = Nettokaltmiete | E68: =E66*(1+E67) -> 0 | F68: =F66*(1+F67) -> 0 | G68: =G66*(1+G67) -> 0 | H68: =H66*(1+H67) -> 0 | I68: =I66*(1+I67) -> 0 | J68: =J66*(1+J67) -> 0 | K68: =K66*(1+K67) -> 0 | L68: =L66*(1+L67) -> 0 | ... BB68: =BB66*(1+BB67) -> 0
B69: = pro m² Wohnfläche | E69: =IFERROR(E68/$C65,"-") -> - | F69: =IFERROR(F68/$C65,"-") -> - | G69: =IFERROR(G68/$C65,"-") -> - | H69: =IFERROR(H68/$C65,"-") -> - | I69: =IFERROR(I68/$C65,"-") -> - | J69: =IFERROR(J68/$C65,"-") -> - | K69: =IFERROR(K68/$C65,"-") -> - | L69: =IFERROR(L68/$C65,"-") -> - | ... BB69: =IFERROR(BB68/$C65,"-") -> -
B71: Einheit 9:
B72: Wohnfläche | C72: 0 | E72: =E$9 -> 2024 | F72: =F$9 -> 2025 | G72: =G$9 -> 2026 | H72: =H$9 -> 2027 | I72: =I$9 -> 2028 | J72: =J$9 -> 2029 | K72: =K$9 -> 2030 | L72: =L$9 -> 2031 | ... BB72: =BB$9 -> 2073
B73: Nettokaltmiete vor Erhöhung | E73: 0 | F73: =E75 -> 0 | G73: =F75 -> 0 | H73: =G75 -> 0 | I73: =H75 -> 0 | J73: =I75 -> 0 | K73: =J75 -> 0 | L73: =K75 -> 0 | M73: =L75 -> 0 | ... BB73: =BA75 -> 0
B74: + geplante Mieterhöhung | E74: =Cockpit!$H$31 -> 0.03 | F74: =Cockpit!$H$31 -> 0.03 | G74: =Cockpit!$H$31 -> 0.03 | H74: =Cockpit!$H$31 -> 0.03 | I74: =Cockpit!$H$31 -> 0.03 | J74: =Cockpit!$H$31 -> 0.03 | K74: =Cockpit!$H$31 -> 0.03 | L74: =Cockpit!$H$31 -> 0.03 | ... BB74: =Cockpit!$H$31 -> 0.03
B75: = Nettokaltmiete | E75: =E73*(1+E74) -> 0 | F75: =F73*(1+F74) -> 0 | G75: =G73*(1+G74) -> 0 | H75: =H73*(1+H74) -> 0 | I75: =I73*(1+I74) -> 0 | J75: =J73*(1+J74) -> 0 | K75: =K73*(1+K74) -> 0 | L75: =L73*(1+L74) -> 0 | ... BB75: =BB73*(1+BB74) -> 0
B76: = pro m² Wohnfläche | E76: =IFERROR(E75/$C72,"-") -> - | F76: =IFERROR(F75/$C72,"-") -> - | G76: =IFERROR(G75/$C72,"-") -> - | H76: =IFERROR(H75/$C72,"-") -> - | I76: =IFERROR(I75/$C72,"-") -> - | J76: =IFERROR(J75/$C72,"-") -> - | K76: =IFERROR(K75/$C72,"-") -> - | L76: =IFERROR(L75/$C72,"-") -> - | ... BB76: =IFERROR(BB75/$C72,"-") -> -
B78: Einheit 10:
B79: Wohnfläche | C79: 0 | E79: =E$9 -> 2024 | F79: =F$9 -> 2025 | G79: =G$9 -> 2026 | H79: =H$9 -> 2027 | I79: =I$9 -> 2028 | J79: =J$9 -> 2029 | K79: =K$9 -> 2030 | L79: =L$9 -> 2031 | ... BB79: =BB$9 -> 2073
B80: Nettokaltmiete vor Erhöhung | E80: 0 | F80: =E82 -> 0 | G80: =F82 -> 0 | H80: =G82 -> 0 | I80: =H82 -> 0 | J80: =I82 -> 0 | K80: =J82 -> 0 | L80: =K82 -> 0 | M80: =L82 -> 0 | ... BB80: =BA82 -> 0
B81: + geplante Mieterhöhung | E81: =Cockpit!$H$31 -> 0.03 | F81: =Cockpit!$H$31 -> 0.03 | G81: =Cockpit!$H$31 -> 0.03 | H81: =Cockpit!$H$31 -> 0.03 | I81: =Cockpit!$H$31 -> 0.03 | J81: =Cockpit!$H$31 -> 0.03 | K81: =Cockpit!$H$31 -> 0.03 | L81: =Cockpit!$H$31 -> 0.03 | ... BB81: =Cockpit!$H$31 -> 0.03
B82: = Nettokaltmiete | E82: =E80*(1+E81) -> 0 | F82: =F80*(1+F81) -> 0 | G82: =G80*(1+G81) -> 0 | H82: =H80*(1+H81) -> 0 | I82: =I80*(1+I81) -> 0 | J82: =J80*(1+J81) -> 0 | K82: =K80*(1+K81) -> 0 | L82: =L80*(1+L81) -> 0 | ... BB82: =BB80*(1+BB81) -> 0
B83: = pro m² Wohnfläche | E83: =IFERROR(E82/$C79,"-") -> - | F83: =IFERROR(F82/$C79,"-") -> - | G83: =IFERROR(G82/$C79,"-") -> - | H83: =IFERROR(H82/$C79,"-") -> - | I83: =IFERROR(I82/$C79,"-") -> - | J83: =IFERROR(J82/$C79,"-") -> - | K83: =IFERROR(K82/$C79,"-") -> - | L83: =IFERROR(L82/$C79,"-") -> - | ... BB83: =IFERROR(BB82/$C79,"-") -> -
B85: Einheit 11:
B86: Wohnfläche | C86: 0 | E86: =E$9 -> 2024 | F86: =F$9 -> 2025 | G86: =G$9 -> 2026 | H86: =H$9 -> 2027 | I86: =I$9 -> 2028 | J86: =J$9 -> 2029 | K86: =K$9 -> 2030 | L86: =L$9 -> 2031 | ... BB86: =BB$9 -> 2073
B87: Nettokaltmiete vor Erhöhung | E87: 0 | F87: =E89 -> 0 | G87: =F89 -> 0 | H87: =G89 -> 0 | I87: =H89 -> 0 | J87: =I89 -> 0 | K87: =J89 -> 0 | L87: =K89 -> 0 | M87: =L89 -> 0 | ... BB87: =BA89 -> 0
B88: + geplante Mieterhöhung | E88: =Cockpit!$H$31 -> 0.03 | F88: =Cockpit!$H$31 -> 0.03 | G88: =Cockpit!$H$31 -> 0.03 | H88: =Cockpit!$H$31 -> 0.03 | I88: =Cockpit!$H$31 -> 0.03 | J88: =Cockpit!$H$31 -> 0.03 | K88: =Cockpit!$H$31 -> 0.03 | L88: =Cockpit!$H$31 -> 0.03 | ... BB88: =Cockpit!$H$31 -> 0.03
B89: = Nettokaltmiete | E89: =E87*(1+E88) -> 0 | F89: =F87*(1+F88) -> 0 | G89: =G87*(1+G88) -> 0 | H89: =H87*(1+H88) -> 0 | I89: =I87*(1+I88) -> 0 | J89: =J87*(1+J88) -> 0 | K89: =K87*(1+K88) -> 0 | L89: =L87*(1+L88) -> 0 | ... BB89: =BB87*(1+BB88) -> 0
B90: = pro m² Wohnfläche | E90: =IFERROR(E89/$C86,"-") -> - | F90: =IFERROR(F89/$C86,"-") -> - | G90: =IFERROR(G89/$C86,"-") -> - | H90: =IFERROR(H89/$C86,"-") -> - | I90: =IFERROR(I89/$C86,"-") -> - | J90: =IFERROR(J89/$C86,"-") -> - | K90: =IFERROR(K89/$C86,"-") -> - | L90: =IFERROR(L89/$C86,"-") -> - | ... BB90: =IFERROR(BB89/$C86,"-") -> -
B92: Einheit 12:
B93: Wohnfläche | C93: 0 | E93: =E$9 -> 2024 | F93: =F$9 -> 2025 | G93: =G$9 -> 2026 | H93: =H$9 -> 2027 | I93: =I$9 -> 2028 | J93: =J$9 -> 2029 | K93: =K$9 -> 2030 | L93: =L$9 -> 2031 | ... BB93: =BB$9 -> 2073
B94: Nettokaltmiete vor Erhöhung | E94: 0 | F94: =E96 -> 0 | G94: =F96 -> 0 | H94: =G96 -> 0 | I94: =H96 -> 0 | J94: =I96 -> 0 | K94: =J96 -> 0 | L94: =K96 -> 0 | M94: =L96 -> 0 | ... BB94: =BA96 -> 0
B95: + geplante Mieterhöhung | E95: =Cockpit!$H$31 -> 0.03 | F95: =Cockpit!$H$31 -> 0.03 | G95: =Cockpit!$H$31 -> 0.03 | H95: =Cockpit!$H$31 -> 0.03 | I95: =Cockpit!$H$31 -> 0.03 | J95: =Cockpit!$H$31 -> 0.03 | K95: =Cockpit!$H$31 -> 0.03 | L95: =Cockpit!$H$31 -> 0.03 | ... BB95: =Cockpit!$H$31 -> 0.03
B96: = Nettokaltmiete | E96: =E94*(1+E95) -> 0 | F96: =F94*(1+F95) -> 0 | G96: =G94*(1+G95) -> 0 | H96: =H94*(1+H95) -> 0 | I96: =I94*(1+I95) -> 0 | J96: =J94*(1+J95) -> 0 | K96: =K94*(1+K95) -> 0 | L96: =L94*(1+L95) -> 0 | ... BB96: =BB94*(1+BB95) -> 0
B97: = pro m² Wohnfläche | E97: =IFERROR(E96/$C93,"-") -> - | F97: =IFERROR(F96/$C93,"-") -> - | G97: =IFERROR(G96/$C93,"-") -> - | H97: =IFERROR(H96/$C93,"-") -> - | I97: =IFERROR(I96/$C93,"-") -> - | J97: =IFERROR(J96/$C93,"-") -> - | K97: =IFERROR(K96/$C93,"-") -> - | L97: =IFERROR(L96/$C93,"-") -> - | ... BB97: =IFERROR(BB96/$C93,"-") -> -
B99: Einheit 13:
B100: Wohnfläche | C100: 0 | E100: =E$9 -> 2024 | F100: =F$9 -> 2025 | G100: =G$9 -> 2026 | H100: =H$9 -> 2027 | I100: =I$9 -> 2028 | J100: =J$9 -> 2029 | K100: =K$9 -> 2030 | L100: =L$9 -> 2031 | ... BB100: =BB$9 -> 2073
B101: Nettokaltmiete vor Erhöhung | E101: 0 | F101: =E103 -> 0 | G101: =F103 -> 0 | H101: =G103 -> 0 | I101: =H103 -> 0 | J101: =I103 -> 0 | K101: =J103 -> 0 | L101: =K103 -> 0 | M101: =L103 -> 0 | ... BB101: =BA103 -> 0
B102: + geplante Mieterhöhung | E102: =Cockpit!$H$31 -> 0.03 | F102: =Cockpit!$H$31 -> 0.03 | G102: =Cockpit!$H$31 -> 0.03 | H102: =Cockpit!$H$31 -> 0.03 | I102: =Cockpit!$H$31 -> 0.03 | J102: =Cockpit!$H$31 -> 0.03 | K102: =Cockpit!$H$31 -> 0.03 | L102: =Cockpit!$H$31 -> 0.03 | ... BB102: =Cockpit!$H$31 -> 0.03
B103: = Nettokaltmiete | E103: =E101*(1+E102) -> 0 | F103: =F101*(1+F102) -> 0 | G103: =G101*(1+G102) -> 0 | H103: =H101*(1+H102) -> 0 | I103: =I101*(1+I102) -> 0 | J103: =J101*(1+J102) -> 0 | K103: =K101*(1+K102) -> 0 | L103: =L101*(1+L102) -> 0 | ... BB103: =BB101*(1+BB102) -> 0
B104: = pro m² Wohnfläche | E104: =IFERROR(E103/$C100,"-") -> - | F104: =IFERROR(F103/$C100,"-") -> - | G104: =IFERROR(G103/$C100,"-") -> - | H104: =IFERROR(H103/$C100,"-") -> - | I104: =IFERROR(I103/$C100,"-") -> - | J104: =IFERROR(J103/$C100,"-") -> - | K104: =IFERROR(K103/$C100,"-") -> - | L104: =IFERROR(L103/$C100,"-") -> - | ... BB104: =IFERROR(BB103/$C100,"-") -> -
B106: Einheit 14:
B107: Wohnfläche | C107: 0 | E107: =E$9 -> 2024 | F107: =F$9 -> 2025 | G107: =G$9 -> 2026 | H107: =H$9 -> 2027 | I107: =I$9 -> 2028 | J107: =J$9 -> 2029 | K107: =K$9 -> 2030 | L107: =L$9 -> 2031 | ... BB107: =BB$9 -> 2073
B108: Nettokaltmiete vor Erhöhung | E108: 0 | F108: =E110 -> 0 | G108: =F110 -> 0 | H108: =G110 -> 0 | I108: =H110 -> 0 | J108: =I110 -> 0 | K108: =J110 -> 0 | L108: =K110 -> 0 | M108: =L110 -> 0 | ... BB108: =BA110 -> 0
B109: + geplante Mieterhöhung | E109: =Cockpit!$H$31 -> 0.03 | F109: =Cockpit!$H$31 -> 0.03 | G109: =Cockpit!$H$31 -> 0.03 | H109: =Cockpit!$H$31 -> 0.03 | I109: =Cockpit!$H$31 -> 0.03 | J109: =Cockpit!$H$31 -> 0.03 | K109: =Cockpit!$H$31 -> 0.03 | L109: =Cockpit!$H$31 -> 0.03 | ... BB109: =Cockpit!$H$31 -> 0.03
B110: = Nettokaltmiete | E110: =E108*(1+E109) -> 0 | F110: =F108*(1+F109) -> 0 | G110: =G108*(1+G109) -> 0 | H110: =H108*(1+H109) -> 0 | I110: =I108*(1+I109) -> 0 | J110: =J108*(1+J109) -> 0 | K110: =K108*(1+K109) -> 0 | L110: =L108*(1+L109) -> 0 | ... BB110: =BB108*(1+BB109) -> 0
B111: = pro m² Wohnfläche | E111: =IFERROR(E110/$C107,"-") -> - | F111: =IFERROR(F110/$C107,"-") -> - | G111: =IFERROR(G110/$C107,"-") -> - | H111: =IFERROR(H110/$C107,"-") -> - | I111: =IFERROR(I110/$C107,"-") -> - | J111: =IFERROR(J110/$C107,"-") -> - | K111: =IFERROR(K110/$C107,"-") -> - | L111: =IFERROR(L110/$C107,"-") -> - | ... BB111: =IFERROR(BB110/$C107,"-") -> -
B113: Einheit 15:
B114: Wohnfläche | C114: 0 | E114: =E$9 -> 2024 | F114: =F$9 -> 2025 | G114: =G$9 -> 2026 | H114: =H$9 -> 2027 | I114: =I$9 -> 2028 | J114: =J$9 -> 2029 | K114: =K$9 -> 2030 | L114: =L$9 -> 2031 | ... BB114: =BB$9 -> 2073
B115: Nettokaltmiete vor Erhöhung | E115: 0 | F115: =E117 -> 0 | G115: =F117 -> 0 | H115: =G117 -> 0 | I115: =H117 -> 0 | J115: =I117 -> 0 | K115: =J117 -> 0 | L115: =K117 -> 0 | M115: =L117 -> 0 | ... BB115: =BA117 -> 0
B116: + geplante Mieterhöhung | E116: =Cockpit!$H$31 -> 0.03 | F116: =Cockpit!$H$31 -> 0.03 | G116: =Cockpit!$H$31 -> 0.03 | H116: =Cockpit!$H$31 -> 0.03 | I116: =Cockpit!$H$31 -> 0.03 | J116: =Cockpit!$H$31 -> 0.03 | K116: =Cockpit!$H$31 -> 0.03 | L116: =Cockpit!$H$31 -> 0.03 | ... BB116: =Cockpit!$H$31 -> 0.03
B117: = Nettokaltmiete | E117: =E115*(1+E116) -> 0 | F117: =F115*(1+F116) -> 0 | G117: =G115*(1+G116) -> 0 | H117: =H115*(1+H116) -> 0 | I117: =I115*(1+I116) -> 0 | J117: =J115*(1+J116) -> 0 | K117: =K115*(1+K116) -> 0 | L117: =L115*(1+L116) -> 0 | ... BB117: =BB115*(1+BB116) -> 0
B118: = pro m² Wohnfläche | E118: =IFERROR(E117/$C114,"-") -> - | F118: =IFERROR(F117/$C114,"-") -> - | G118: =IFERROR(G117/$C114,"-") -> - | H118: =IFERROR(H117/$C114,"-") -> - | I118: =IFERROR(I117/$C114,"-") -> - | J118: =IFERROR(J117/$C114,"-") -> - | K118: =IFERROR(K117/$C114,"-") -> - | L118: =IFERROR(L117/$C114,"-") -> - | ... BB118: =IFERROR(BB117/$C114,"-") -> -
B120: Einheit 16:
B121: Wohnfläche | C121: 0 | E121: =E$9 -> 2024 | F121: =F$9 -> 2025 | G121: =G$9 -> 2026 | H121: =H$9 -> 2027 | I121: =I$9 -> 2028 | J121: =J$9 -> 2029 | K121: =K$9 -> 2030 | L121: =L$9 -> 2031 | ... BB121: =BB$9 -> 2073
...

Sheet Sanierungsplaner
B1: zurück zum Cockpit | C1: Sanierungsplaner
A5: ↓ | B5: Filter
B6: Tätigkeit | C6: Einheit | D6: Kosten pro Einheit | E6: Typische Schwankung | F6: Geplanter Aufwand (Einheiten) | G6: Kosten | H6: Kosten min | I6: Kosten max | J6: Kommentar
A7: Nur Tätigkeiten mit geplantem Aufwand
B8: Dieser Planer funktioniert wie (d)ein persönlicher wachsender Sanierungskatalog. Du füllst ihn nach und nach mit den für deine Investments relevanten Tätigkeiten und den für deinen Standort realistischen Preisen. In Zukunft schätzt du dann vor Sanierungen / Renovierungen nur noch, wie viele Einheiten du von welcher Tätigkeit benötigst. Du kannst die Tätigkeitsgruppen (bspw. "Fassade / Außenhülle") umbenennen und deinen Bedürfnissen anpassen. Möchtest du dir nur die Tätigkeiten anzeigen lassen, für die du tatsächlich Arbeit eingeplant hast? Dann klicke oben Links auf den Filter und wähle "Nur Tätigkeiten mit geplantem Aufwand" aus. Möchtest du Maßnahmen finanziell im Zeitverlauf deines Investments berücksichtigen? Dies kannst du im Bereich "Kennzahlen im Verlauf -> Miete, Cashflow, Steuern" tun.
A16: =IF(COUNTIF(A17:A31,"Nur Tätigkeiten mit geplantem Aufwand")>0,"Nur Tätigkeiten mit geplantem Aufwand","") -> Nur Tätigkeiten mit geplantem Aufwand | B16: Fassade / Gebäudehülle | G16: =SUM(G17:G31) -> 5810 | H16: =SUM(H17:H31) -> 4887 | I16: =SUM(I17:I31) -> 6733
A17: =IF(OR(H17>0,I17>0),"Nur Tätigkeiten mit geplantem Aufwand","") -> Nur Tätigkeiten mit geplantem Aufwand | B17: Gerüst: Aufstellen, 4 Wochen, Abbau (ohne Staubschutz) | C17: m² Wandfläche | D17: 11.4 | E17: 30 | F17: 150 | G17: =D17*F17 -> 1710 | H17: =G17*(100-E17)/100 -> 1197 | I17: =G17*(100+E17)/100 -> 2223
A18: =IF(OR(H18>0,I18>0),"Nur Tätigkeiten mit geplantem Aufwand","") -> Nur Tätigkeiten mit geplantem Aufwand | B18: Anstrich und einfache Beschichtung auf Altplutz inkl. Gerüst | C18: m² Wandfläche | D18: 20.5 | E18: 10 | F18: 200 | G18: =D18*F18 -> 4100 | H18: =G18*(100-E18)/100 -> 3690 | I18: =G18*(100+E18)/100 -> 4510
A19: =IF(OR(H19>0,I19>0),"Nur Tätigkeiten mit geplantem Aufwand","") | G19: =D19*F19 -> 0 | H19: =G19*(100-E19)/100 -> 0 | I19: =G19*(100+E19)/100 -> 0
A20: =IF(OR(H20>0,I20>0),"Nur Tätigkeiten mit geplantem Aufwand","") | G20: =D20*F20 -> 0 | H20: =G20*(100-E20)/100 -> 0 | I20: =G20*(100+E20)/100 -> 0
A21: =IF(OR(H21>0,I21>0),"Nur Tätigkeiten mit geplantem Aufwand","") | G21: =D21*F21 -> 0 | H21: =G21*(100-E21)/100 -> 0 | I21: =G21*(100+E21)/100 -> 0
A22: =IF(OR(H22>0,I22>0),"Nur Tätigkeiten mit geplantem Aufwand","") | G22: =D22*F22 -> 0 | H22: =G22*(100-E22)/100 -> 0 | I22: =G22*(100+E22)/100 -> 0
A23: =IF(OR(H23>0,I23>0),"Nur Tätigkeiten mit geplantem Aufwand","") | G23: =D23*F23 -> 0 | H23: =G23*(100-E23)/100 -> 0 | I23: =G23*(100+E23)/100 -> 0
A24: =IF(OR(H24>0,I24>0),"Nur Tätigkeiten mit geplantem Aufwand","") | G24: =D24*F24 -> 0 | H24: =G24*(100-E24)/100 -> 0 | I24: =G24*(100+E24)/100 -> 0
A25: =IF(OR(H25>0,I25>0),"Nur Tätigkeiten mit geplantem Aufwand","") | G25: =D25*F25 -> 0 | H25: =G25*(100-E25)/100 -> 0 | I25: =G25*(100+E25)/100 -> 0
A26: =IF(OR(H26>0,I26>0),"Nur Tätigkeiten mit geplantem Aufwand","") | G26: =D26*F26 -> 0 | H26: =G26*(100-E26)/100 -> 0 | I26: =G26*(100+E26)/100 -> 0
A27: =IF(OR(H27>0,I27>0),"Nur Tätigkeiten mit geplantem Aufwand","") | G27: =D27*F27 -> 0 | H27: =G27*(100-E27)/100 -> 0 | I27: =G27*(100+E27)/100 -> 0
A28: =IF(OR(H28>0,I28>0),"Nur Tätigkeiten mit geplantem Aufwand","") | G28: =D28*F28 -> 0 | H28: =G28*(100-E28)/100 -> 0 | I28: =G28*(100+E28)/100 -> 0
A29: =IF(OR(H29>0,I29>0),"Nur Tätigkeiten mit geplantem Aufwand","") | G29: =D29*F29 -> 0 | H29: =G29*(100-E29)/100 -> 0 | I29: =G29*(100+E29)/100 -> 0
A30: =IF(OR(H30>0,I30>0),"Nur Tätigkeiten mit geplantem Aufwand","") | G30: =D30*F30 -> 0 | H30: =G30*(100-E30)/100 -> 0 | I30: =G30*(100+E30)/100 -> 0
A31: =IF(OR(H31>0,I31>0),"Nur Tätigkeiten mit geplantem Aufwand","") | G31: =D31*F31 -> 0 | H31: =G31*(100-E31)/100 -> 0 | I31: =G31*(100+E31)/100 -> 0
A32: =IF(COUNTIF(A34:A48,"Nur Tätigkeiten mit geplantem Aufwand")>0,"Nur Tätigkeiten mit geplantem Aufwand","")
A33: =IF(COUNTIF(A34:A48,"Nur Tätigkeiten mit geplantem Aufwand")>0,"Nur Tätigkeiten mit geplantem Aufwand","") | B33: Dach (inkl. Dachfenster / Ausbau) | G33: =SUM(G34:G48) -> 0 | H33: =SUM(H34:H48) -> 0 | I33: =SUM(I34:I48) -> 0
A34: =IF(OR(H34>0,I34>0),"Nur Tätigkeiten mit geplantem Aufwand","") | G34: =D34*F34 -> 0 | H34: =G34*(100-E34)/100 -> 0 | I34: =G34*(100+E34)/100 -> 0
A35: =IF(OR(H35>0,I35>0),"Nur Tätigkeiten mit geplantem Aufwand","") | G35: =D35*F35 -> 0 | H35: =G35*(100-E35)/100 -> 0 | I35: =G35*(100+E35)/100 -> 0
A36: =IF(OR(H36>0,I36>0),"Nur Tätigkeiten mit geplantem Aufwand","") | G36: =D36*F36 -> 0 | H36: =G36*(100-E36)/100 -> 0 | I36: =G36*(100+E36)/100 -> 0
A37: =IF(OR(H37>0,I37>0),"Nur Tätigkeiten mit geplantem Aufwand","") | G37: =D37*F37 -> 0 | H37: =G37*(100-E37)/100 -> 0 | I37: =G37*(100+E37)/100 -> 0
A38: =IF(OR(H38>0,I38>0),"Nur Tätigkeiten mit geplantem Aufwand","") | G38: =D38*F38 -> 0 | H38: =G38*(100-E38)/100 -> 0 | I38: =G38*(100+E38)/100 -> 0
A39: =IF(OR(H39>0,I39>0),"Nur Tätigkeiten mit geplantem Aufwand","") | G39: =D39*F39 -> 0 | H39: =G39*(100-E39)/100 -> 0 | I39: =G39*(100+E39)/100 -> 0
A40: =IF(OR(H40>0,I40>0),"Nur Tätigkeiten mit geplantem Aufwand","") | G40: =D40*F40 -> 0 | H40: =G40*(100-E40)/100 -> 0 | I40: =G40*(100+E40)/100 -> 0
A41: =IF(OR(H41>0,I41>0),"Nur Tätigkeiten mit geplantem Aufwand","") | G41: =D41*F41 -> 0 | H41: =G41*(100-E41)/100 -> 0 | I41: =G41*(100+E41)/100 -> 0
A42: =IF(OR(H42>0,I42>0),"Nur Tätigkeiten mit geplantem Aufwand","") | G42: =D42*F42 -> 0 | H42: =G42*(100-E42)/100 -> 0 | I42: =G42*(100+E42)/100 -> 0
A43: =IF(OR(H43>0,I43>0),"Nur Tätigkeiten mit geplantem Aufwand","") | G43: =D43*F43 -> 0 | H43: =G43*(100-E43)/100 -> 0 | I43: =G43*(100+E43)/100 -> 0
A44: =IF(OR(H44>0,I44>0),"Nur Tätigkeiten mit geplantem Aufwand","") | G44: =D44*F44 -> 0 | H44: =G44*(100-E44)/100 -> 0 | I44: =G44*(100+E44)/100 -> 0
A45: =IF(OR(H45>0,I45>0),"Nur Tätigkeiten mit geplantem Aufwand","") | G45: =D45*F45 -> 0 | H45: =G45*(100-E45)/100 -> 0 | I45: =G45*(100+E45)/100 -> 0
... A48: =IF(OR(H48>0,I48>0),"Nur Tätigkeiten mit geplantem Aufwand","") | G48: =D48*F48 -> 0 | H48: =G48*(100-E48)/100 -> 0 | I48: =G48*(100+E48)/100 -> 0
A49: =IF(COUNTIF(A51:A65,"Nur Tätigkeiten mit geplantem Aufwand")>0,"Nur Tätigkeiten mit geplantem Aufwand","")
A50: =IF(COUNTIF(A51:A65,"Nur Tätigkeiten mit geplantem Aufwand")>0,"Nur Tätigkeiten mit geplantem Aufwand","") | B50: Keller | G50: =SUM(G51:G65) -> 0 | H50: =SUM(H51:H65) -> 0 | I50: =SUM(I51:I65) -> 0
A51: =IF(OR(H51>0,I51>0),"Nur Tätigkeiten mit geplantem Aufwand","") | G51: =D51*F51 -> 0 | H51: =G51*(100-E51)/100 -> 0 | I51: =G51*(100+E51)/100 -> 0
A52: =IF(OR(H52>0,I52>0),"Nur Tätigkeiten mit geplantem Aufwand","") | G52: =D52*F52 -> 0 | H52: =G52*(100-E52)/100 -> 0 | I52: =G52*(100+E52)/100 -> 0
A53: =IF(OR(H53>0,I53>0),"Nur Tätigkeiten mit geplantem Aufwand","") | G53: =D53*F53 -> 0 | H53: =G53*(100-E53)/100 -> 0 | I53: =G53*(100+E53)/100 -> 0
A54: =IF(OR(H54>0,I54>0),"Nur Tätigkeiten mit geplantem Aufwand","") | G54: =D54*F54 -> 0 | H54: =G54*(100-E54)/100 -> 0 | I54: =G54*(100+E54)/100 -> 0
A55: =IF(OR(H55>0,I55>0),"Nur Tätigkeiten mit geplantem Aufwand","") | G55: =D55*F55 -> 0 | H55: =G55*(100-E55)/100 -> 0 | I55: =G55*(100+E55)/100 -> 0
A56: =IF(OR(H56>0,I56>0),"Nur Tätigkeiten mit geplantem Aufwand","") | G56: =D56*F56 -> 0 | H56: =G56*(100-E56)/100 -> 0 | I56: =G56*(100+E56)/100 -> 0
A57: =IF(OR(H57>0,I57>0),"Nur Tätigkeiten mit geplantem Aufwand","") | G57: =D57*F57 -> 0 | H57: =G57*(100-E57)/100 -> 0 | I57: =G57*(100+E57)/100 -> 0
A58: =IF(OR(H58>0,I58>0),"Nur Tätigkeiten mit geplantem Aufwand","") | G58: =D58*F58 -> 0 | H58: =G58*(100-E58)/100 -> 0 | I58: =G58*(100+E58)/100 -> 0
A59: =IF(OR(H59>0,I59>0),"Nur Tätigkeiten mit geplantem Aufwand","") | G59: =D59*F59 -> 0 | H59: =G59*(100-E59)/100 -> 0 | I59: =G59*(100+E59)/100 -> 0
A60: =IF(OR(H60>0,I60>0),"Nur Tätigkeiten mit geplantem Aufwand","") | G60: =D60*F60 -> 0 | H60: =G60*(100-E60)/100 -> 0 | I60: =G60*(100+E60)/100 -> 0
A61: =IF(OR(H61>0,I61>0),"Nur Tätigkeiten mit geplantem Aufwand","") | G61: =D61*F61 -> 0 | H61: =G61*(100-E61)/100 -> 0 | I61: =G61*(100+E61)/100 -> 0
A62: =IF(OR(H62>0,I62>0),"Nur Tätigkeiten mit geplantem Aufwand","") | G62: =D62*F62 -> 0 | H62: =G62*(100-E62)/100 -> 0 | I62: =G62*(100+E62)/100 -> 0
... A65: =IF(OR(H65>0,I65>0),"Nur Tätigkeiten mit geplantem Aufwand","") | G65: =D65*F65 -> 0 | H65: =G65*(100-E65)/100 -> 0 | I65: =G65*(100+E65)/100 -> 0
A66: =IF(COUNTIF(A68:A82,"Nur Tätigkeiten mit geplantem Aufwand")>0,"Nur Tätigkeiten mit geplantem Aufwand","")
A67: =IF(COUNTIF(A68:A82,"Nur Tätigkeiten mit geplantem Aufwand")>0,"Nur Tätigkeiten mit geplantem Aufwand","") | B67: Heizung (inkl. zentrales Warmwasser) | G67: =SUM(G68:G82) -> 0 | H67: =SUM(H68:H82) -> 0 | I67: =SUM(I68:I82) -> 0
A68: =IF(OR(H68>0,I68>0),"Nur Tätigkeiten mit geplantem Aufwand","") | G68: =D68*F68 -> 0 | H68: =G68*(100-E68)/100 -> 0 | I68: =G68*(100+E68)/100 -> 0
A69: =IF(OR(H69>0,I69>0),"Nur Tätigkeiten mit geplantem Aufwand","") | G69: =D69*F69 -> 0 | H69: =G69*(100-E69)/100 -> 0 | I69: =G69*(100+E69)/100 -> 0
A70: =IF(OR(H70>0,I70>0),"Nur Tätigkeiten mit geplantem Aufwand","") | G70: =D70*F70 -> 0 | H70: =G70*(100-E70)/100 -> 0 | I70: =G70*(100+E70)/100 -> 0
A71: =IF(OR(H71>0,I71>0),"Nur Tätigkeiten mit geplantem Aufwand","") | G71: =D71*F71 -> 0 | H71: =G71*(100-E71)/100 -> 0 | I71: =G71*(100+E71)/100 -> 0
A72: =IF(OR(H72>0,I72>0),"Nur Tätigkeiten mit geplantem Aufwand","") | G72: =D72*F72 -> 0 | H72: =G72*(100-E72)/100 -> 0 | I72: =G72*(100+E72)/100 -> 0
A73: =IF(OR(H73>0,I73>0),"Nur Tätigkeiten mit geplantem Aufwand","") | G73: =D73*F73 -> 0 | H73: =G73*(100-E73)/100 -> 0 | I73: =G73*(100+E73)/100 -> 0
A74: =IF(OR(H74>0,I74>0),"Nur Tätigkeiten mit geplantem Aufwand","") | G74: =D74*F74 -> 0 | H74: =G74*(100-E74)/100 -> 0 | I74: =G74*(100+E74)/100 -> 0
A75: =IF(OR(H75>0,I75>0),"Nur Tätigkeiten mit geplantem Aufwand","") | G75: =D75*F75 -> 0 | H75: =G75*(100-E75)/100 -> 0 | I75: =G75*(100+E75)/100 -> 0
A76: =IF(OR(H76>0,I76>0),"Nur Tätigkeiten mit geplantem Aufwand","") | G76: =D76*F76 -> 0 | H76: =G76*(100-E76)/100 -> 0 | I76: =G76*(100+E76)/100 -> 0
A77: =IF(OR(H77>0,I77>0),"Nur Tätigkeiten mit geplantem Aufwand","") | G77: =D77*F77 -> 0 | H77: =G77*(100-E77)/100 -> 0 | I77: =G77*(100+E77)/100 -> 0
A78: =IF(OR(H78>0,I78>0),"Nur Tätigkeiten mit geplantem Aufwand","") | G78: =D78*F78 -> 0 | H78: =G78*(100-E78)/100 -> 0 | I78: =G78*(100+E78)/100 -> 0
A79: =IF(OR(H79>0,I79>0),"Nur Tätigkeiten mit geplantem Aufwand","") | G79: =D79*F79 -> 0 | H79: =G79*(100-E79)/100 -> 0 | I79: =G79*(100+E79)/100 -> 0
... A82: =IF(OR(H82>0,I82>0),"Nur Tätigkeiten mit geplantem Aufwand","") | G82: =D82*F82 -> 0 | H82: =G82*(100-E82)/100 -> 0 | I82: =G82*(100+E82)/100 -> 0
A83: =IF(COUNTIF(A85:A98,"Nur Tätigkeiten mit geplantem Aufwand")>0,"Nur Tätigkeiten mit geplantem Aufwand","")
A84: =IF(COUNTIF(A85:A98,"Nur Tätigkeiten mit geplantem Aufwand")>0,"Nur Tätigkeiten mit geplantem Aufwand","") | B84: Elektrik | G84: =SUM(G85:G99) -> 0 | H84: =SUM(H85:H99) -> 0 | I84: =SUM(I85:I99) -> 0
A85: =IF(OR(H85>0,I85>0),"Nur Tätigkeiten mit geplantem Aufwand","") | G85: =D85*F85 -> 0 | H85: =G85*(100-E85)/100 -> 0 | I85: =G85*(100+E85)/100 -> 0
A86: =IF(OR(H86>0,I86>0),"Nur Tätigkeiten mit geplantem Aufwand","") | G86: =D86*F86 -> 0 | H86: =G86*(100-E86)/100 -> 0 | I86: =G86*(100+E86)/100 -> 0
A87: =IF(OR(H87>0,I87>0),"Nur Tätigkeiten mit geplantem Aufwand","") | G87: =D87*F87 -> 0 | H87: =G87*(100-E87)/100 -> 0 | I87: =G87*(100+E87)/100 -> 0
A88: =IF(OR(H88>0,I88>0),"Nur Tätigkeiten mit geplantem Aufwand","") | G88: =D88*F88 -> 0 | H88: =G88*(100-E88)/100 -> 0 | I88: =G88*(100+E88)/100 -> 0
A89: =IF(OR(H89>0,I89>0),"Nur Tätigkeiten mit geplantem Aufwand","") | G89: =D89*F89 -> 0 | H89: =G89*(100-E89)/100 -> 0 | I89: =G89*(100+E89)/100 -> 0
A90: =IF(OR(H90>0,I90>0),"Nur Tätigkeiten mit geplantem Aufwand","") | G90: =D90*F90 -> 0 | H90: =G90*(100-E90)/100 -> 0 | I90: =G90*(100+E90)/100 -> 0
A91: =IF(OR(H91>0,I91>0),"Nur Tätigkeiten mit geplantem Aufwand","") | G91: =D91*F91 -> 0 | H91: =G91*(100-E91)/100 -> 0 | I91: =G91*(100+E91)/100 -> 0
A92: =IF(OR(H92>0,I92>0),"Nur Tätigkeiten mit geplantem Aufwand","") | G92: =D92*F92 -> 0 | H92: =G92*(100-E92)/100 -> 0 | I92: =G92*(100+E92)/100 -> 0
A93: =IF(OR(H93>0,I93>0),"Nur Tätigkeiten mit geplantem Aufwand","") | G93: =D93*F93 -> 0 | H93: =G93*(100-E93)/100 -> 0 | I93: =G93*(100+E93)/100 -> 0
A94: =IF(OR(H94>0,I94>0),"Nur Tätigkeiten mit geplantem Aufwand","") | G94: =D94*F94 -> 0 | H94: =G94*(100-E94)/100 -> 0 | I94: =G94*(100+E94)/100 -> 0
A95: =IF(OR(H95>0,I95>0),"Nur Tätigkeiten mit geplantem Aufwand","") | G95: =D95*F95 -> 0 | H95: =G95*(100-E95)/100 -> 0 | I95: =G95*(100+E95)/100 -> 0
A96: =IF(OR(H96>0,I96>0),"Nur Tätigkeiten mit geplantem Aufwand","") | G96: =D96*F96 -> 0 | H96: =G96*(100-E96)/100 -> 0 | I96: =G96*(100+E96)/100 -> 0
... A99: =IF(OR(H99>0,I99>0),"Nur Tätigkeiten mit geplantem Aufwand","") | G99: =D99*F99 -> 0 | H99: =G99*(100-E99)/100 -> 0 | I99: =G99*(100+E99)/100 -> 0
A100: =IF(COUNTIF(A102:A115,"Nur Tätigkeiten mit geplantem Aufwand")>0,"Nur Tätigkeiten mit geplantem Aufwand","")
A101: =IF(COUNTIF(A102:A115,"Nur Tätigkeiten mit geplantem Aufwand")>0,"Nur Tätigkeiten mit geplantem Aufwand","") | B101: Fenster/Türen | G101: =SUM(G102:G116) -> 0 | H101: =SUM(H102:H116) -> 0 | I101: =SUM(I102:I116) -> 0
A102: =IF(OR(H102>0,I102>0),"Nur Tätigkeiten mit geplantem Aufwand","") | G102: =D102*F102 -> 0 | H102: =G102*(100-E102)/100 -> 0 | I102: =G102*(100+E102)/100 -> 0
A103: =IF(OR(H103>0,I103>0),"Nur Tätigkeiten mit geplantem Aufwand","") | G103: =D103*F103 -> 0 | H103: =G103*(100-E103)/100 -> 0 | I103: =G103*(100+E103)/100 -> 0
A104: =IF(OR(H104>0,I104>0),"Nur Tätigkeiten mit geplantem Aufwand","") | G104: =D104*F104 -> 0 | H104: =G104*(100-E104)/100 -> 0 | I104: =G104*(100+E104)/100 -> 0
A105: =IF(OR(H105>0,I105>0),"Nur Tätigkeiten mit geplantem Aufwand","") | G105: =D105*F105 -> 0 | H105: =G105*(100-E105)/100 -> 0 | I105: =G105*(100+E105)/100 -> 0
A106: =IF(OR(H106>0,I106>0),"Nur Tätigkeiten mit geplantem Aufwand","") | G106: =D106*F106 -> 0 | H106: =G106*(100-E106)/100 -> 0 | I106: =G106*(100+E106)/100 -> 0
A107: =IF(OR(H107>0,I107>0),"Nur Tätigkeiten mit geplantem Aufwand","") | G107: =D107*F107 -> 0 | H107: =G107*(100-E107)/100 -> 0 | I107: =G107*(100+E107)/100 -> 0
A108: =IF(OR(H108>0,I108>0),"Nur Tätigkeiten mit geplantem Aufwand","") | G108: =D108*F108 -> 0 | H108: =G108*(100-E108)/100 -> 0 | I108: =G108*(100+E108)/100 -> 0
A109: =IF(OR(H109>0,I109>0),"Nur Tätigkeiten mit geplantem Aufwand","") | G109: =D109*F109 -> 0 | H109: =G109*(100-E109)/100 -> 0 | I109: =G109*(100+E109)/100 -> 0
A110: =IF(OR(H110>0,I110>0),"Nur Tätigkeiten mit geplantem Aufwand","") | G110: =D110*F110 -> 0 | H110: =G110*(100-E110)/100 -> 0 | I110: =G110*(100+E110)/100 -> 0
A111: =IF(OR(H111>0,I111>0),"Nur Tätigkeiten mit geplantem Aufwand","") | G111: =D111*F111 -> 0 | H111: =G111*(100-E111)/100 -> 0 | I111: =G111*(100+E111)/100 -> 0
A112: =IF(OR(H112>0,I112>0),"Nur Tätigkeiten mit geplantem Aufwand","") | G112: =D112*F112 -> 0 | H112: =G112*(100-E112)/100 -> 0 | I112: =G112*(100+E112)/100 -> 0
A113: =IF(OR(H113>0,I113>0),"Nur Tätigkeiten mit geplantem Aufwand","") | G113: =D113*F113 -> 0 | H113: =G113*(100-E113)/100 -> 0 | I113: =G113*(100+E113)/100 -> 0
... A116: =IF(OR(H116>0,I116>0),"Nur Tätigkeiten mit geplantem Aufwand","") | G116: =D116*F116 -> 0 | H116: =G116*(100-E116)/100 -> 0 | I116: =G116*(100+E116)/100 -> 0
A117: =IF(COUNTIF(A119:A133,"Nur Tätigkeiten mit geplantem Aufwand")>0,"Nur Tätigkeiten mit geplantem Aufwand","") -> Nur Tätigkeiten mit geplantem Aufwand
A118: =IF(COUNTIF(A119:A133,"Nur Tätigkeiten mit geplantem Aufwand")>0,"Nur Tätigkeiten mit geplantem Aufwand","") -> Nur Tätigkeiten mit geplantem Aufwand | B118: Estrich/Boden/Wandfliesen | G118: =SUM(G119:G133) -> 1260 | H118: =SUM(H119:H133) -> 1008 | I118: =SUM(I119:I133) -> 1512
A119: =IF(OR(H119>0,I119>0),"Nur Tätigkeiten mit geplantem Aufwand","") -> Nur Tätigkeiten mit geplantem Aufwand | B119: Verklebten Teppich/PVC entfernen, Boden neu grundieren, komplett | C119: m² Fläche | D119: 10 | E119: 20 | F119: 30 | G119: =D119*F119 -> 300 | H119: =G119*(100-E119)/100 -> 240 | I119: =G119*(100+E119)/100 -> 360
A120: =IF(OR(H120>0,I120>0),"Nur Tätigkeiten mit geplantem Aufwand","") -> Nur Tätigkeiten mit geplantem Aufwand | B120: Vinyl Material und Verlegen auf Estrich (mittel) | C120: m² Fläche | D120: 32 | E120: 20 | F120: 30 | G120: =D120*F120 -> 960 | H120: =G120*(100-E120)/100 -> 768 | I120: =G120*(100+E120)/100 -> 1152
...

Sheet Konfiguration
B1: zurück zum Cockpit | E1: Konfiguration
B6: Schwellwerte für Kennzahlen-Farben
B7: Kennzahl | C7: Grün | D7: Gelb | E7: Rot
B8: Bruttomietrendite | C8: 0.06 | D8: 0.05 | E8: 0.04 | F8: =IF(NOT(AND(C8>D8,D8>E8)),"Ungültige Kombination. Grün muss > gelb muss > rot sein.","")
B9: Nettomietrendite | C9: 0.05 | D9: 0.04 | E9: 0.03 | F9: =IF(NOT(AND(C9>D9,D9>E9)),"Ungültige Kombination. Grün muss > gelb muss > rot sein.","")
B10: Eigenkapitalrendite | C10: 0.2 | D10: 0.1 | E10: 0.05 | F10: =IF(NOT(AND(C10>D10,D10>E10)),"Ungültige Kombination. Grün muss > gelb muss > rot sein.","")
B11: Cashflow operativ | C11: 100 | D11: 0 | E11: -50 | F11: =IF(NOT(AND(C11>D11,D11>E11)),"Ungültige Kombination. Grün muss > gelb muss > rot sein.","")
B12: Cashflow nach Steuern | C12: 100 | D12: 0 | E12: -50 | F12: =IF(NOT(AND(C12>D12,D12>E12)),"Ungültige Kombination. Grün muss > gelb muss > rot sein.","")
B14: Keine Gewähr für die Richtigkeit der Angaben. Dieses Tool ersetzt keine fundierte Rechts-, Steuer- oder Finanzberatung. Mehr Details hier.

Sheet Hinweise_AT
B1: zurück zum Cockpit | E1: Hinweise AT
B6: Auf diesem Blatt findest du einige wertvolle Informationen zur steuerlichen Situation in Österreich (Stand 2020/01)
B7: über das Menü am oberen Bildschirmrand gelangst du zur eigentlichen Kalkulation
B9: Ermittlung des Grenzsteuersatzes für die Cashflow Kalkulation
B11: bis 11.000 | D11: 0
B12: über 11.000 bis 18.000 | D12: 0.25
B13: über 18.000 bis 31.000 | D13: 0.35
B14: über 31.000 bis 60.000 | D14: 0.42
B15: über 60.000 bis 90.000 | D15: 0.48
B16: über 90.000 bis 1.000.000 | D16: 0.5
B17: über 1.000.000 (bis 2020) | D17: 0.55
B19: Beispiel: Du hast ein steuerpflichtiges Einkommen von 50.000. Deine Immobilie erwirtschaftet einen jährlichen Gewinn von € 1.000. Bei € 50.000 Einkommen beträgt der Grenzsteuersatz 42%. Das bedeutet, die zusätzlichen € 1.000 werden mit 42% besteuert.
B26: Ermittlung des Gebäudeanteils am Kaufpreis
B28: Die Aufteilung der Anschaffungskosten (inkl. Anschaffungsnebenkosten) ist für die Ermittlung der Abschreibungsbasis relevant. Der Grundanteil ist steuerlich nicht abnutzbar, wird daher nicht abgeschrieben. Der Gebäudeanteil ist abnutzbar und wird steuerlich auf 66,67 Jahre verteilt abgeschrieben.
B31: Die Aufteilung erfolgt folgendermaßen:
B33: a) 80% Gebäudeanteil / 20% Grundanteil
B34: Gemeinden mit weniger als 100.000 Einwohnern UND durchschnittlicher
B35: Quadratmeterpreis für Bauland bis € 400
B37: b) 70% Gebäudeanteil / 30% Grundanteil
B38: Gemeinden mit mehr als 100.000 Einwohnern ODER durchschnittlicher Quadratmeterpreis
B39: für Bauland ab € 400 UND mehr als 10 Wohneinheiten im Gebäude
B41: c) 60% Gebäudeanteil / 40% Grundanteil
B42: Gemeinden mit mehr als 100.000 Einwohnern ODER durchschnittlicher Quadratmeterpreis
... B60: Einfache Reparaturen, Austausch unwesentlicher Gebäudeteile die keine wesentliche Erhöhung des Nutzwertes oder der Nutzungsdauer des Gebäudes bewirken. Instandhaltungsaufwendungen sind im Jahr der Bezahlung sofort in voller Höhe von den Einnahmen abzugsfähig. Alternativ können sie freiwillig auf 15 Jahre verteilt werden.
B63: Beispiele: | C63: Laufende Wartungsarbeiten
C64: Reparaturen, auch wenn diese nicht jährlich anfallen
C65: Ausmalen des Stiegenhauses und der Räume
C66: Anfärbeln der Fassade ohne Erneuerung des Außenputzes
C67: Ausbessern des Verputzes
C68: Erneuerung von Gebäudeteilen infolge höherer Gewalt (z.B. Sturm- und Hagelschäden)
B71: Instandsetzung:
B72: Arbeiten, die den Nutzwert des Gebäudes oder dessen Nutzungsdauer wesentlich erhöhen bzw. verlängern. Austausch von mehr als 25% von unselbständigen Gebäudeteilen (z.B. Fenster). Verpflichtende Verteilung auf 15 Jahre.
B75: Beispiele: | C75: Austausch von Fenstern
C76: Austausch von Türen
C77: Austausch von Dach oder Dachstuhl
C78: Austausch von Stiegen
C79: Austausch von Zwischenwänden und Zwischendecken
C80: Austausch von Unterböden (z.B. Estrich statt Holzboden)
C81: Austausch von Aufzugsanlagen
C82: Austausch von Heizungsanlagen
C83: Austausch einer Gaseinzelofenheizung durch eine Gasetagenheizung
C84: Austausch von Elektroinstallationen
C85: Austausch von Gas-, Wasser- und Heizungsinstallationen
C86: Austausch von Sanitärinstallationen (auch mit Erneuerung der Bodenbeläge und Fliesen)
C87: Umfangreiche Erneuerung des Außenputzes z.B. mit Erneuerung der Wärmedämmung
... C89: Kanalanschluss bei bestehenden Gebäuden
B92: Herstellungsaufwand:
B93: Das Gebäude wird in seiner Wesensart verändert Herstellungsaufwand auf ein vorhandenes Gebäude ist grundsätzlich auf die Restnutzungsdauer zu verteilen. Gegebenenfalls ist eine neue Restnutzungsdauer zu ermitteln.
B96: Beispiele: | C96: Aufstockung eines Gebäudes
C97: Zusammenlegung von Wohnungen
C98: Erstmaliger Einbau von Zentralheizungen
C99: Erstmaliger Einbau von Aufzugsanlagen
C100: Umstellung der Wärmeversorgung von Öl, Gas oder einem festen Brennstoff auf Fernwärme
C101: Versetzung von Zwischenwänden
C102: Einbau von Badezimmer und WC (Kategorieanhebung)
C103: Einbau von Gebäudeteilen an anderen Stellen (z.B. Versetzen von Türen und Fenstern)
B105: Folgende Herstellungsaufwendungen können über Antrag auf fünfzehn Jahre verteilt werden:
B107: a) Aufwendungen nach §§ 3 bis 5 MRG, wenn das Gebäude dem MRG unterliegt
B108: b) Sanierungsmaßnahmen, wenn eine Zusage für eine Förderung nach Wohnhaussanierungsgesetz, Startwohnungsgesetz oder Landesgesetzen über Wohnhaussanierung vorliegt
B109: c) Sanierungsaufwendungen nach §19 Denkmalschutzgesetz
B113: erstellt und geprüft von Paul Zödi
B116: Keine Gewähr für die Richtigkeit der Angaben. Dieses Tool ersetzt keine fundierte Rechts-, Steuer- oder Finanzberatung. Mehr Details hier.

Sheet Haushaltsrechnung
B1: zurück zum Bankgespräch | G1: Vorlage: Haushaltsrechnung
C7: Haushaltsrechnung
C8: Max Mustermann | O8: Stichtag: 01.01.2017
C10: Persönliche Angaben
C11: Name: | D11: Max Mustermann | K11: Familienstand: | M11: Verheiratet
C12: Anschrift: | D12: Musterstraße 11 | K12: Güterstand: | M12: Gesetzlich
D13: 12345 Musterstadt | K13: Kinder: | M13: Keine
C15: Einkommensverhältnisse
C17: Einkünfte | H17: Betrag p.a. | I17: mntl. | K17: Kommentar
C18: Lohn / Gehalt (netto) I
C19: Lohn / Gehalt (netto) II
C20: Einkünfte aus selbstständiger Arbeit
C21: Rente / Pension
C22: Zinsen
C23: Miet- / Pachteinnahmen (netto/kalt)
C24: Staatliche Leistungen
C25: Sonstige Einkünfte
C26: Summe | H26: =12*I26 -> 0 | I26: =SUM(I18:I25) -> 0
C28: Ausgaben | H28: Betrag p.a. | I28: mntl. | K28: Kommentar
C29: Wohnen inkl. Nebenkosten
C30: Nahrungs- und Genussmittel
C31: Anschaffungen
C32: Freizeit, Kultur und Hobby
C33: Urlaub
C34: Mobilität
C35: Kommunikation
C36: Spenden
C37: Laufende Sparverträge
C38: Beiträge zur Altersvorsorge
C39: Private Versicherungen
C40: Vermietete Immobilien: Bewirtschaftung
... C44: Sonstiges
C45: Summe | H45: =I45*12 -> 0 | I45: =SUM(I29:I44) -> 0
C47: Haushaltsüberschuss | H47: Betrag p.a. | I47: mntl. | K47: Kommentar
C48: Einnahmen | H48: =12*I48 -> 0 | I48: =I26 -> 0
C49: Ausgaben | H49: =12*I49 -> 0 | I49: =I45 -> 0
C50: Differenz | H50: =12*I50 -> 0 | I50: =I48-I49 -> 0 | K50: = Haushaltsüberschuss
B53: Keine Gewähr für die Richtigkeit der Angaben. Dieses Tool ersetzt keine fundierte Rechts-, Steuer- oder Finanzberatung. Mehr Details hier.

Sheet Vermögensaufstellung
B1: zurück zum Bankgespräch | G1: Vorlage: Vermögensaufstellung
C7: Vermögensaufstellung
C8: Max Mustermann | O8: Stichtag: 01.01.2017
C10: Persönliche Angaben
C11: Name: | D11: Max Mustermann | K11: Familienstand: | M11: Verheiratet
C12: Anschrift: | D12: Musterstraße 11 | K12: Güterstand: | M12: Gesetzlich
D13: 12345 Musterstadt | K13: Kinder: | M13: Keine
C15: Vermögensverhältnisse
C17: Vermögensgegenstände | H17: Betrag | I17: Verpfändet | K17: Kommentar
C18: Girokonto Deutsche Bank | H18: 5100 | I18: Nein
C19: Girokonto Postbank | H19: 4200 | I19: Nein | K19: Ehe-Konto
C20: Wertpapier Depot Deutsche Bank | H20: 22000 | I20: Nein | K20: aktueller Kurswert
C21: Tagesgeldkonto Deutsche Bank | H21: 4500 | I21: Nein
C22: Immobilienvermögen | H22: 179000 | I22: Nein | K22: siehe separate Übersicht
C23: Lebensversicherung Allianz | H23: 24000 | I23: Nein | K23: aktueller Rückkaufswert
C24: Bausparvertrag Schwäbisch Hall | H24: 22000 | I24: Nein | K24: aktuelles Guthaben
C25: Summe | H25: =SUM(H18:H24) -> 260800
C27: Verbindlichkeiten | H27: Valuta | K27: Kommentar
C28: Dispositionskredite | H28: 0 | K28: keine
C29: Konsumkredite | H29: 16000 | K29: Finanzierung PKW
C30: Immobiliendarlehen | H30: 122000 | K30: siehe separate Übersicht
C31: Übernommene Bürgschaften | H31: 0 | K31: keine
C32: Steuerschulden | H32: 0 | K32: keine
C33: Summe | H33: =SUM(H28:H32) -> 138000
C35: Vermögensaufstellung | H35: Betrag | K35: Kommentar
C36: Vermögensgegenstände | H36: =H25 -> 260800
C37: Verbindlichkeiten | H37: =-H33 -> -138000
C38: Differenz | H38: =SUM(H36:H37) -> 122800 | K38: = Netto-Vermögen
B41: Keine Gewähr für die Richtigkeit der Angaben. Dieses Tool ersetzt keine fundierte Rechts-, Steuer- oder Finanzberatung. Mehr Details hier.
